Workbook

Sheet Как читать
A1: Цены билетных платформ: полная раскладка, 09.10.2026
A3: Листы
A4: Сценарии — сколько стоит продажа одного билета за €10/25/50/100 на ~90 тарифах, включая наши варианты (жёлтые строки). Цены билета можно менять.
A5: Direct merchant — 65 записей: деньги покупателя идут прямо на платёжный счёт организатора (как у Arena), плюс платформы, где организатор может выбрать этот режим.
A6: Собирают на себя — 176 записей: платформа принимает деньги как продавец и выплачивает организатору позже (или режим не выяснен).
A7: Эквайринг — ставки платёжных провайдеров по странам (Stripe, PayPal, Mollie, Flitt, AllPay, местные), чтобы сравнивать полную стоимость.
A8: Курсы — курсы на 09.10.2026, по ним считаются сценарии.
A10: Как собрано
A11: Открытые страницы цен, справочные статьи о сборах, оферты и условия для организаторов; Bright Data + WebFetch; 9 групп по регионам. У каждой цифры есть ссылка (последний столбец).
A12: Уверенность: page — прочитано на странице платформы; snippet — только из выдачи поиска; third_party — из сторонней статьи/обзора. «По запросу» значит, что цена не опубликована — цифр не придумывали.
A13: Ничего не запрашивали у продаж, не регистрировались, форм не заполняли.
A15: Ограничения
... A20: Отчёт с выводами: docs/competitive/pricing_2026-10/report_ru.md

Sheet Сценарии
A1: Сколько стоит продать один билет: сбор платформы + эквайринг, в евро
A2: Жёлтые ячейки P3:S3 — цена билета в евро, можно менять. Ставки (синие) взяты из сырых данных с источниками (листы Direct merchant / Собирают на себя). Эквайринг: если не включён в сбор платформы — стандартная ставка Stripe (или местного провайдера) для внутренних карт этого рынка. Абонентская плата, НДС на сбор и сборы с заказа в сценарий НЕ входят — смотрите «Примечание».
O3: Цена билета, € → | P3: 10 | Q3: 25 | R3: 50 | S3: 100
A4: Модель | B4: Платформа | C4: Рынок | D4: Тариф / вариант | E4: Валюта | F4: Курс за 1 EUR | G4: Сбор, % | H4: Сбор, фикс. (валюта) | I4: Минимум | J4: Потолок | K4: Эквайринг включён | L4: Эквайринг, % | M4: Эквайринг, фикс. | N4: Кто платит по умолчанию | O4: Примечание / уверенность | P4: Всего €, билет €10 | Q4: Всего €, билет €25 | R4: Всего €, билет €50 | S4: Всего €, билет €100 | T4: % от цены, билет €10 | U4: % от цены, билет €25 | V4: % от цены, билет €50 | W4: % от цены, билет €100
A5: Direct merchant | B5: Arena Sold Out | C5: EU | D5: Вариант А: старый сайт, без мест | E5: EUR | F5: =INDEX('Курсы'!$B$4:$B$46,MATCH($E5,'Курсы'!$A$4:$A$46,0)) | G5: 0 | H5: 0.5 | K5: нет | L5: 0.015 | M5: 0.25 | N5: организатор (счёт после сеанса) | O5: Тариф старого сайта, 08_architecture/33 §4.4 | P5: =(MIN(IF($J5="",1E+9,$J5),MAX(IF($I5="",0,$I5),$G5*P$3*$F5+$H5))+IF($K5="да",0,$L5*P$3*$F5+$M5))/$F5 | Q5: =(MIN(IF($J5="",1E+9,$J5),MAX(IF($I5="",0,$I5),$G5*Q$3*$F5+$H5))+IF($K5="да",0,$L5*Q$3*$F5+$M5))/$F5 | R5: =(MIN(IF($J5="",1E+9,$J5),MAX(IF($I5="",0,$I5),$G5*R$3*$F5+$H5))+IF($K5="да",0,$L5*R$3*$F5+$M5))/$F5 | S5: =(MIN(IF($J5="",1E+9,$J5),MAX(IF($I5="",0,$I5),$G5*S$3*$F5+$H5))+IF($K5="да",0,$L5*S$3*$F5+$M5))/$F5 | T5: =P5/P$3 | U5: =Q5/Q$3 | V5: =R5/R$3 | W5: =S5/S$3
A6: Direct merchant | B6: Arena Sold Out | C6: EU | D6: Вариант А: старый сайт, с планом зала | E6: EUR | F6: =INDEX('Курсы'!$B$4:$B$46,MATCH($E6,'Курсы'!$A$4:$A$46,0)) | G6: 0 | H6: 1 | K6: нет | L6: 0.015 | M6: 0.25 | N6: организатор (счёт после сеанса) | O6: Тариф старого сайта | P6: =(MIN(IF($J6="",1E+9,$J6),MAX(IF($I6="",0,$I6),$G6*P$3*$F6+$H6))+IF($K6="да",0,$L6*P$3*$F6+$M6))/$F6 | Q6: =(MIN(IF($J6="",1E+9,$J6),MAX(IF($I6="",0,$I6),$G6*Q$3*$F6+$H6))+IF($K6="да",0,$L6*Q$3*$F6+$M6))/$F6 | R6: =(MIN(IF($J6="",1E+9,$J6),MAX(IF($I6="",0,$I6),$G6*R$3*$F6+$H6))+IF($K6="да",0,$L6*R$3*$F6+$M6))/$F6 | S6: =(MIN(IF($J6="",1E+9,$J6),MAX(IF($I6="",0,$I6),$G6*S$3*$F6+$H6))+IF($K6="да",0,$L6*S$3*$F6+$M6))/$F6 | T6: =P6/P$3 | U6: =Q6/Q$3 | V6: =R6/R$3 | W6: =S6/S$3
A7: Direct merchant | B7: Arena Sold Out | C7: EU | D7: Вариант Б (Марина 08.10): без мест | E7: EUR | F7: =INDEX('Курсы'!$B$4:$B$46,MATCH($E7,'Курсы'!$A$4:$A$46,0)) | G7: 0 | H7: 1 | K7: нет | L7: 0.015 | M7: 0.25 | N7: организатор (счёт после сеанса) | O7: Предложение 08.10, не утверждено | P7: =(MIN(IF($J7="",1E+9,$J7),MAX(IF($I7="",0,$I7),$G7*P$3*$F7+$H7))+IF($K7="да",0,$L7*P$3*$F7+$M7))/$F7 | Q7: =(MIN(IF($J7="",1E+9,$J7),MAX(IF($I7="",0,$I7),$G7*Q$3*$F7+$H7))+IF($K7="да",0,$L7*Q$3*$F7+$M7))/$F7 | R7: =(MIN(IF($J7="",1E+9,$J7),MAX(IF($I7="",0,$I7),$G7*R$3*$F7+$H7))+IF($K7="да",0,$L7*R$3*$F7+$M7))/$F7 | S7: =(MIN(IF($J7="",1E+9,$J7),MAX(IF($I7="",0,$I7),$G7*S$3*$F7+$H7))+IF($K7="да",0,$L7*S$3*$F7+$M7))/$F7 | T7: =P7/P$3 | U7: =Q7/Q$3 | V7: =R7/R$3 | W7: =S7/S$3
A8: Direct merchant | B8: Arena Sold Out | C8: EU | D8: Вариант Б (Марина 08.10): с планом зала | E8: EUR | F8: =INDEX('Курсы'!$B$4:$B$46,MATCH($E8,'Курсы'!$A$4:$A$46,0)) | G8: 0 | H8: 1.5 | K8: нет | L8: 0.015 | M8: 0.25 | N8: организатор (счёт после сеанса) | O8: +0,50 за место, прочтение не подтверждено | P8: =(MIN(IF($J8="",1E+9,$J8),MAX(IF($I8="",0,$I8),$G8*P$3*$F8+$H8))+IF($K8="да",0,$L8*P$3*$F8+$M8))/$F8 | Q8: =(MIN(IF($J8="",1E+9,$J8),MAX(IF($I8="",0,$I8),$G8*Q$3*$F8+$H8))+IF($K8="да",0,$L8*Q$3*$F8+$M8))/$F8 | R8: =(MIN(IF($J8="",1E+9,$J8),MAX(IF($I8="",0,$I8),$G8*R$3*$F8+$H8))+IF($K8="да",0,$L8*R$3*$F8+$M8))/$F8 | S8: =(MIN(IF($J8="",1E+9,$J8),MAX(IF($I8="",0,$I8),$G8*S$3*$F8+$H8))+IF($K8="да",0,$L8*S$3*$F8+$M8))/$F8 | T8: =P8/P$3 | U8: =Q8/Q$3 | V8: =R8/R$3 | W8: =S8/S$3
A9: Direct merchant | B9: Arena Sold Out | C9: EU | D9: Постоянные площадки: 2 % | E9: EUR | F9: =INDEX('Курсы'!$B$4:$B$46,MATCH($E9,'Курсы'!$A$4:$A$46,0)) | G9: 0.02 | H9: 0 | K9: нет | L9: 0.015 | M9: 0.25 | N9: организатор | O9: Тариф старого сайта для площадок | P9: =(MIN(IF($J9="",1E+9,$J9),MAX(IF($I9="",0,$I9),$G9*P$3*$F9+$H9))+IF($K9="да",0,$L9*P$3*$F9+$M9))/$F9 | Q9: =(MIN(IF($J9="",1E+9,$J9),MAX(IF($I9="",0,$I9),$G9*Q$3*$F9+$H9))+IF($K9="да",0,$L9*Q$3*$F9+$M9))/$F9 | R9: =(MIN(IF($J9="",1E+9,$J9),MAX(IF($I9="",0,$I9),$G9*R$3*$F9+$H9))+IF($K9="да",0,$L9*R$3*$F9+$M9))/$F9 | S9: =(MIN(IF($J9="",1E+9,$J9),MAX(IF($I9="",0,$I9),$G9*S$3*$F9+$H9))+IF($K9="да",0,$L9*S$3*$F9+$M9))/$F9 | T9: =P9/P$3 | U9: =Q9/Q$3 | V9: =R9/R$3 | W9: =S9/S$3
A10: Direct merchant | B10: Ticket Tailor | C10: UK | D10: Pay as you sell, без мест | E10: GBP | F10: =INDEX('Курсы'!$B$4:$B$46,MATCH($E10,'Курсы'!$A$4:$A$46,0)) | G10: 0 | H10: 0.6 | K10: нет | L10: 0.015 | M10: 0.2 | N10: настраивается | O10: Цены без НДС (+20 %). Сбор не возвращается при возврате билета | P10: =(MIN(IF($J10="",1E+9,$J10),MAX(IF($I10="",0,$I10),$G10*P$3*$F10+$H10))+IF($K10="да",0,$L10*P$3*$F10+$M10))/$F10 | Q10: =(MIN(IF($J10="",1E+9,$J10),MAX(IF($I10="",0,$I10),$G10*Q$3*$F10+$H10))+IF($K10="да",0,$L10*Q$3*$F10+$M10))/$F10 | R10: =(MIN(IF($J10="",1E+9,$J10),MAX(IF($I10="",0,$I10),$G10*R$3*$F10+$H10))+IF($K10="да",0,$L10*R$3*$F10+$M10))/$F10 | S10: =(MIN(IF($J10="",1E+9,$J10),MAX(IF($I10="",0,$I10),$G10*S$3*$F10+$H10))+IF($K10="да",0,$L10*S$3*$F10+$M10))/$F10 | T10: =P10/P$3 | U10: =Q10/Q$3 | V10: =R10/R$3 | W10: =S10/S$3
A11: Direct merchant | B11: Ticket Tailor | C11: UK | D11: Pay as you sell, с местами (+1 кредит) | E11: GBP | F11: =INDEX('Курсы'!$B$4:$B$46,MATCH($E11,'Курсы'!$A$4:$A$46,0)) | G11: 0 | H11: 1.2 | K11: нет | L11: 0.015 | M11: 0.2 | N11: настраивается | O11: Место с рассадкой = 2 кредита | P11: =(MIN(IF($J11="",1E+9,$J11),MAX(IF($I11="",0,$I11),$G11*P$3*$F11+$H11))+IF($K11="да",0,$L11*P$3*$F11+$M11))/$F11 | Q11: =(MIN(IF($J11="",1E+9,$J11),MAX(IF($I11="",0,$I11),$G11*Q$3*$F11+$H11))+IF($K11="да",0,$L11*Q$3*$F11+$M11))/$F11 | R11: =(MIN(IF($J11="",1E+9,$J11),MAX(IF($I11="",0,$I11),$G11*R$3*$F11+$H11))+IF($K11="да",0,$L11*R$3*$F11+$M11))/$F11 | S11: =(MIN(IF($J11="",1E+9,$J11),MAX(IF($I11="",0,$I11),$G11*S$3*$F11+$H11))+IF($K11="да",0,$L11*S$3*$F11+$M11))/$F11 | T11: =P11/P$3 | U11: =Q11/Q$3 | V11: =R11/R$3 | W11: =S11/S$3
A12: Direct merchant | B12: Ticket Tailor | C12: UK | D12: Предоплата 500 кредитов | E12: GBP | F12: =INDEX('Курсы'!$B$4:$B$46,MATCH($E12,'Курсы'!$A$4:$A$46,0)) | G12: 0 | H12: 0.41 | K12: нет | L12: 0.015 | M12: 0.2 | N12: настраивается | O12: Кредиты не сгорают; крупнейшие пакеты от £0,22 | P12: =(MIN(IF($J12="",1E+9,$J12),MAX(IF($I12="",0,$I12),$G12*P$3*$F12+$H12))+IF($K12="да",0,$L12*P$3*$F12+$M12))/$F12 | Q12: =(MIN(IF($J12="",1E+9,$J12),MAX(IF($I12="",0,$I12),$G12*Q$3*$F12+$H12))+IF($K12="да",0,$L12*Q$3*$F12+$M12))/$F12 | R12: =(MIN(IF($J12="",1E+9,$J12),MAX(IF($I12="",0,$I12),$G12*R$3*$F12+$H12))+IF($K12="да",0,$L12*R$3*$F12+$M12))/$F12 | S12: =(MIN(IF($J12="",1E+9,$J12),MAX(IF($I12="",0,$I12),$G12*S$3*$F12+$H12))+IF($K12="да",0,$L12*S$3*$F12+$M12))/$F12 | T12: =P12/P$3 | U12: =Q12/Q$3 | V12: =R12/R$3 | W12: =S12/S$3
A13: Direct merchant | B13: Ticket Tailor | C13: Еврозона | D13: Pay as you sell, без мест | E13: EUR | F13: =INDEX('Курсы'!$B$4:$B$46,MATCH($E13,'Курсы'!$A$4:$A$46,0)) | G13: 0 | H13: 0.7 | K13: нет | L13: 0.015 | M13: 0.25 | N13: настраивается | O13: Цены без НДС | P13: =(MIN(IF($J13="",1E+9,$J13),MAX(IF($I13="",0,$I13),$G13*P$3*$F13+$H13))+IF($K13="да",0,$L13*P$3*$F13+$M13))/$F13 | Q13: =(MIN(IF($J13="",1E+9,$J13),MAX(IF($I13="",0,$I13),$G13*Q$3*$F13+$H13))+IF($K13="да",0,$L13*Q$3*$F13+$M13))/$F13 | R13: =(MIN(IF($J13="",1E+9,$J13),MAX(IF($I13="",0,$I13),$G13*R$3*$F13+$H13))+IF($K13="да",0,$L13*R$3*$F13+$M13))/$F13 | S13: =(MIN(IF($J13="",1E+9,$J13),MAX(IF($I13="",0,$I13),$G13*S$3*$F13+$H13))+IF($K13="да",0,$L13*S$3*$F13+$M13))/$F13 | T13: =P13/P$3 | U13: =Q13/Q$3 | V13: =R13/R$3 | W13: =S13/S$3
A14: Direct merchant | B14: Ticket Tailor | C14: Еврозона | D14: Предоплата (крупные пакеты, ~) | E14: EUR | F14: =INDEX('Курсы'!$B$4:$B$46,MATCH($E14,'Курсы'!$A$4:$A$46,0)) | G14: 0 | H14: 0.3 | K14: нет | L14: 0.015 | M14: 0.25 | N14: настраивается | O14: «около €0,30»; точная лестница пакетов в EUR не прочитана [snippet] | P14: =(MIN(IF($J14="",1E+9,$J14),MAX(IF($I14="",0,$I14),$G14*P$3*$F14+$H14))+IF($K14="да",0,$L14*P$3*$F14+$M14))/$F14 | Q14: =(MIN(IF($J14="",1E+9,$J14),MAX(IF($I14="",0,$I14),$G14*Q$3*$F14+$H14))+IF($K14="да",0,$L14*Q$3*$F14+$M14))/$F14 | R14: =(MIN(IF($J14="",1E+9,$J14),MAX(IF($I14="",0,$I14),$G14*R$3*$F14+$H14))+IF($K14="да",0,$L14*R$3*$F14+$M14))/$F14 | S14: =(MIN(IF($J14="",1E+9,$J14),MAX(IF($I14="",0,$I14),$G14*S$3*$F14+$H14))+IF($K14="да",0,$L14*S$3*$F14+$M14))/$F14 | T14: =P14/P$3 | U14: =Q14/Q$3 | V14: =R14/R$3 | W14: =S14/S$3
A15: Direct merchant | B15: Ticket Tailor | C15: США | D15: Pay as you sell | E15: USD | F15: =INDEX('Курсы'!$B$4:$B$46,MATCH($E15,'Курсы'!$A$4:$A$46,0)) | G15: 0 | H15: 0.85 | K15: нет | L15: 0.029 | M15: 0.3 | N15: настраивается | P15: =(MIN(IF($J15="",1E+9,$J15),MAX(IF($I15="",0,$I15),$G15*P$3*$F15+$H15))+IF($K15="да",0,$L15*P$3*$F15+$M15))/$F15 | Q15: =(MIN(IF($J15="",1E+9,$J15),MAX(IF($I15="",0,$I15),$G15*Q$3*$F15+$H15))+IF($K15="да",0,$L15*Q$3*$F15+$M15))/$F15 | R15: =(MIN(IF($J15="",1E+9,$J15),MAX(IF($I15="",0,$I15),$G15*R$3*$F15+$H15))+IF($K15="да",0,$L15*R$3*$F15+$M15))/$F15 | S15: =(MIN(IF($J15="",1E+9,$J15),MAX(IF($I15="",0,$I15),$G15*S$3*$F15+$H15))+IF($K15="да",0,$L15*S$3*$F15+$M15))/$F15 | T15: =P15/P$3 | U15: =Q15/Q$3 | V15: =R15/R$3 | W15: =S15/S$3
A16: Direct merchant | B16: Tito | C16: Глобально | D16: Standard | E16: EUR | F16: =INDEX('Курсы'!$B$4:$B$46,MATCH($E16,'Курсы'!$A$4:$A$46,0)) | G16: 0.03 | H16: 0 | J16: 25 | K16: нет | L16: 0.015 | M16: 0.25 | N16: организатор (перекладывать запрещено) | O16: Потолок €25 за билет | P16: =(MIN(IF($J16="",1E+9,$J16),MAX(IF($I16="",0,$I16),$G16*P$3*$F16+$H16))+IF($K16="да",0,$L16*P$3*$F16+$M16))/$F16 | Q16: =(MIN(IF($J16="",1E+9,$J16),MAX(IF($I16="",0,$I16),$G16*Q$3*$F16+$H16))+IF($K16="да",0,$L16*Q$3*$F16+$M16))/$F16 | R16: =(MIN(IF($J16="",1E+9,$J16),MAX(IF($I16="",0,$I16),$G16*R$3*$F16+$H16))+IF($K16="да",0,$L16*R$3*$F16+$M16))/$F16 | S16: =(MIN(IF($J16="",1E+9,$J16),MAX(IF($I16="",0,$I16),$G16*S$3*$F16+$H16))+IF($K16="да",0,$L16*S$3*$F16+$M16))/$F16 | T16: =P16/P$3 | U16: =Q16/Q$3 | V16: =R16/R$3 | W16: =S16/S$3
A17: Direct merchant | B17: pretix (hosted) | C17: Глобально | D17: Pay as you go | E17: EUR | F17: =INDEX('Курсы'!$B$4:$B$46,MATCH($E17,'Курсы'!$A$4:$A$46,0)) | G17: 0.025 | H17: 0 | J17: 15 | K17: нет | L17: 0.015 | M17: 0.25 | N17: организатор | O17: Потолок €15 за билет; некоммерческим 2 % | P17: =(MIN(IF($J17="",1E+9,$J17),MAX(IF($I17="",0,$I17),$G17*P$3*$F17+$H17))+IF($K17="да",0,$L17*P$3*$F17+$M17))/$F17 | Q17: =(MIN(IF($J17="",1E+9,$J17),MAX(IF($I17="",0,$I17),$G17*Q$3*$F17+$H17))+IF($K17="да",0,$L17*Q$3*$F17+$M17))/$F17 | R17: =(MIN(IF($J17="",1E+9,$J17),MAX(IF($I17="",0,$I17),$G17*R$3*$F17+$H17))+IF($K17="да",0,$L17*R$3*$F17+$M17))/$F17 | S17: =(MIN(IF($J17="",1E+9,$J17),MAX(IF($I17="",0,$I17),$G17*S$3*$F17+$H17))+IF($K17="да",0,$L17*S$3*$F17+$M17))/$F17 | T17: =P17/P$3 | U17: =Q17/Q$3 | V17: =R17/R$3 | W17: =S17/S$3
A18: Оба (показан direct) | B18: Humanitix | C18: Еврозона | D18: Standard (свой Stripe) | E18: EUR | F18: =INDEX('Курсы'!$B$4:$B$46,MATCH($E18,'Курсы'!$A$4:$A$46,0)) | G18: 0.021 | H18: 0.99 | K18: нет | L18: 0.015 | M18: 0.25 | N18: покупатель по умолчанию | O18: Прибыль идёт на благотворительность | P18: =(MIN(IF($J18="",1E+9,$J18),MAX(IF($I18="",0,$I18),$G18*P$3*$F18+$H18))+IF($K18="да",0,$L18*P$3*$F18+$M18))/$F18 | Q18: =(MIN(IF($J18="",1E+9,$J18),MAX(IF($I18="",0,$I18),$G18*Q$3*$F18+$H18))+IF($K18="да",0,$L18*Q$3*$F18+$M18))/$F18 | R18: =(MIN(IF($J18="",1E+9,$J18),MAX(IF($I18="",0,$I18),$G18*R$3*$F18+$H18))+IF($K18="да",0,$L18*R$3*$F18+$M18))/$F18 | S18: =(MIN(IF($J18="",1E+9,$J18),MAX(IF($I18="",0,$I18),$G18*S$3*$F18+$H18))+IF($K18="да",0,$L18*S$3*$F18+$M18))/$F18 | T18: =P18/P$3 | U18: =Q18/Q$3 | V18: =R18/R$3 | W18: =S18/S$3
A19: Direct merchant | B19: Luma | C19: Глобально | D19: Free | E19: USD | F19: =INDEX('Курсы'!$B$4:$B$46,MATCH($E19,'Курсы'!$A$4:$A$46,0)) | G19: 0.05 | H19: 0 | K19: нет | L19: 0.029 | M19: 0.3 | N19: организатор | O19: Luma Plus $69/мес = 0 % | P19: =(MIN(IF($J19="",1E+9,$J19),MAX(IF($I19="",0,$I19),$G19*P$3*$F19+$H19))+IF($K19="да",0,$L19*P$3*$F19+$M19))/$F19 | Q19: =(MIN(IF($J19="",1E+9,$J19),MAX(IF($I19="",0,$I19),$G19*Q$3*$F19+$H19))+IF($K19="да",0,$L19*Q$3*$F19+$M19))/$F19 | R19: =(MIN(IF($J19="",1E+9,$J19),MAX(IF($I19="",0,$I19),$G19*R$3*$F19+$H19))+IF($K19="да",0,$L19*R$3*$F19+$M19))/$F19 | S19: =(MIN(IF($J19="",1E+9,$J19),MAX(IF($I19="",0,$I19),$G19*S$3*$F19+$H19))+IF($K19="да",0,$L19*S$3*$F19+$M19))/$F19 | T19: =P19/P$3 | U19: =Q19/Q$3 | V19: =R19/R$3 | W19: =S19/S$3
A20: Оба (показан direct) | B20: TryBooking | C20: UK | D20: You handle payments (свой Stripe) | E20: GBP | F20: =INDEX('Курсы'!$B$4:$B$46,MATCH($E20,'Курсы'!$A$4:$A$46,0)) | G20: 0 | H20: 0.75 | K20: нет | L20: 0.015 | M20: 0.2 | N20: настраивается | O20: Платформа «никогда не держит» деньги | P20: =(MIN(IF($J20="",1E+9,$J20),MAX(IF($I20="",0,$I20),$G20*P$3*$F20+$H20))+IF($K20="да",0,$L20*P$3*$F20+$M20))/$F20 | Q20: =(MIN(IF($J20="",1E+9,$J20),MAX(IF($I20="",0,$I20),$G20*Q$3*$F20+$H20))+IF($K20="да",0,$L20*Q$3*$F20+$M20))/$F20 | R20: =(MIN(IF($J20="",1E+9,$J20),MAX(IF($I20="",0,$I20),$G20*R$3*$F20+$H20))+IF($K20="да",0,$L20*R$3*$F20+$M20))/$F20 | S20: =(MIN(IF($J20="",1E+9,$J20),MAX(IF($I20="",0,$I20),$G20*S$3*$F20+$H20))+IF($K20="да",0,$L20*S$3*$F20+$M20))/$F20 | T20: =P20/P$3 | U20: =Q20/Q$3 | V20: =R20/R$3 | W20: =S20/S$3
A21: Оба (показан direct) | B21: TryBooking | C21: Австралия | D21: Own Stripe account | E21: AUD | F21: =INDEX('Курсы'!$B$4:$B$46,MATCH($E21,'Курсы'!$A$4:$A$46,0)) | G21: 0.01 | H21: 0.5 | K21: нет | L21: 0.0165 | M21: 0.3 | N21: настраивается | P21: =(MIN(IF($J21="",1E+9,$J21),MAX(IF($I21="",0,$I21),$G21*P$3*$F21+$H21))+IF($K21="да",0,$L21*P$3*$F21+$M21))/$F21 | Q21: =(MIN(IF($J21="",1E+9,$J21),MAX(IF($I21="",0,$I21),$G21*Q$3*$F21+$H21))+IF($K21="да",0,$L21*Q$3*$F21+$M21))/$F21 | R21: =(MIN(IF($J21="",1E+9,$J21),MAX(IF($I21="",0,$I21),$G21*R$3*$F21+$H21))+IF($K21="да",0,$L21*R$3*$F21+$M21))/$F21 | S21: =(MIN(IF($J21="",1E+9,$J21),MAX(IF($I21="",0,$I21),$G21*S$3*$F21+$H21))+IF($K21="да",0,$L21*S$3*$F21+$M21))/$F21 | T21: =P21/P$3 | U21: =Q21/Q$3 | V21: =R21/R$3 | W21: =S21/S$3
A22: Оба (показан direct) | B22: TicketSource | C22: UK | D22: Свой Stripe | E22: GBP | F22: =INDEX('Курсы'!$B$4:$B$46,MATCH($E22,'Курсы'!$A$4:$A$46,0)) | G22: 0.045 | H22: 0 | K22: нет | L22: 0.015 | M22: 0.2 | N22: настраивается | O22: С заказа, а не с билета; +НДС | P22: =(MIN(IF($J22="",1E+9,$J22),MAX(IF($I22="",0,$I22),$G22*P$3*$F22+$H22))+IF($K22="да",0,$L22*P$3*$F22+$M22))/$F22 | Q22: =(MIN(IF($J22="",1E+9,$J22),MAX(IF($I22="",0,$I22),$G22*Q$3*$F22+$H22))+IF($K22="да",0,$L22*Q$3*$F22+$M22))/$F22 | R22: =(MIN(IF($J22="",1E+9,$J22),MAX(IF($I22="",0,$I22),$G22*R$3*$F22+$H22))+IF($K22="да",0,$L22*R$3*$F22+$M22))/$F22 | S22: =(MIN(IF($J22="",1E+9,$J22),MAX(IF($I22="",0,$I22),$G22*S$3*$F22+$H22))+IF($K22="да",0,$L22*S$3*$F22+$M22))/$F22 | T22: =P22/P$3 | U22: =Q22/Q$3 | V22: =R22/R$3 | W22: =S22/S$3
A23: Direct merchant | B23: SimpleTix | C23: Глобально | D23: Online | E23: USD | F23: =INDEX('Курсы'!$B$4:$B$46,MATCH($E23,'Курсы'!$A$4:$A$46,0)) | G23: 0.02 | H23: 0.79 | J23: 9.99 | K23: нет | L23: 0.029 | M23: 0.3 | N23: настраивается | O23: Удерживает внутри платежа Stripe/PayPal/Square | P23: =(MIN(IF($J23="",1E+9,$J23),MAX(IF($I23="",0,$I23),$G23*P$3*$F23+$H23))+IF($K23="да",0,$L23*P$3*$F23+$M23))/$F23 | Q23: =(MIN(IF($J23="",1E+9,$J23),MAX(IF($I23="",0,$I23),$G23*Q$3*$F23+$H23))+IF($K23="да",0,$L23*Q$3*$F23+$M23))/$F23 | R23: =(MIN(IF($J23="",1E+9,$J23),MAX(IF($I23="",0,$I23),$G23*R$3*$F23+$H23))+IF($K23="да",0,$L23*R$3*$F23+$M23))/$F23 | S23: =(MIN(IF($J23="",1E+9,$J23),MAX(IF($I23="",0,$I23),$G23*S$3*$F23+$H23))+IF($K23="да",0,$L23*S$3*$F23+$M23))/$F23 | T23: =P23/P$3 | U23: =Q23/Q$3 | V23: =R23/R$3 | W23: =S23/S$3
A24: Direct merchant | B24: Yapsody | C24: Глобально | D24: General seating | E24: USD | F24: =INDEX('Курсы'!$B$4:$B$46,MATCH($E24,'Курсы'!$A$4:$A$46,0)) | G24: 0.0175 | H24: 0.59 | K24: нет | L24: 0.029 | M24: 0.3 | N24: настраивается | O24: Счёт раз в месяц | P24: =(MIN(IF($J24="",1E+9,$J24),MAX(IF($I24="",0,$I24),$G24*P$3*$F24+$H24))+IF($K24="да",0,$L24*P$3*$F24+$M24))/$F24 | Q24: =(MIN(IF($J24="",1E+9,$J24),MAX(IF($I24="",0,$I24),$G24*Q$3*$F24+$H24))+IF($K24="да",0,$L24*Q$3*$F24+$M24))/$F24 | R24: =(MIN(IF($J24="",1E+9,$J24),MAX(IF($I24="",0,$I24),$G24*R$3*$F24+$H24))+IF($K24="да",0,$L24*R$3*$F24+$M24))/$F24 | S24: =(MIN(IF($J24="",1E+9,$J24),MAX(IF($I24="",0,$I24),$G24*S$3*$F24+$H24))+IF($K24="да",0,$L24*S$3*$F24+$M24))/$F24 | T24: =P24/P$3 | U24: =Q24/Q$3 | V24: =R24/R$3 | W24: =S24/S$3
A25: Direct merchant | B25: Yapsody | C25: Глобально | D25: Reserved seating | E25: USD | F25: =INDEX('Курсы'!$B$4:$B$46,MATCH($E25,'Курсы'!$A$4:$A$46,0)) | G25: 0.0249 | H25: 0.98 | K25: нет | L25: 0.029 | M25: 0.3 | N25: настраивается | P25: =(MIN(IF($J25="",1E+9,$J25),MAX(IF($I25="",0,$I25),$G25*P$3*$F25+$H25))+IF($K25="да",0,$L25*P$3*$F25+$M25))/$F25 | Q25: =(MIN(IF($J25="",1E+9,$J25),MAX(IF($I25="",0,$I25),$G25*Q$3*$F25+$H25))+IF($K25="да",0,$L25*Q$3*$F25+$M25))/$F25 | R25: =(MIN(IF($J25="",1E+9,$J25),MAX(IF($I25="",0,$I25),$G25*R$3*$F25+$H25))+IF($K25="да",0,$L25*R$3*$F25+$M25))/$F25 | S25: =(MIN(IF($J25="",1E+9,$J25),MAX(IF($I25="",0,$I25),$G25*S$3*$F25+$H25))+IF($K25="да",0,$L25*S$3*$F25+$M25))/$F25 | T25: =P25/P$3 | U25: =Q25/Q$3 | V25: =R25/R$3 | W25: =S25/S$3
A26: Direct merchant | B26: ThunderTix | C26: США | D26: General Admission | E26: USD | F26: =INDEX('Курсы'!$B$4:$B$46,MATCH($E26,'Курсы'!$A$4:$A$46,0)) | G26: 0 | H26: 1 | K26: нет | L26: 0.029 | M26: 0.3 | N26: — | O26: Плюс $20/мес (не учтено в сценарии) | P26: =(MIN(IF($J26="",1E+9,$J26),MAX(IF($I26="",0,$I26),$G26*P$3*$F26+$H26))+IF($K26="да",0,$L26*P$3*$F26+$M26))/$F26 | Q26: =(MIN(IF($J26="",1E+9,$J26),MAX(IF($I26="",0,$I26),$G26*Q$3*$F26+$H26))+IF($K26="да",0,$L26*Q$3*$F26+$M26))/$F26 | R26: =(MIN(IF($J26="",1E+9,$J26),MAX(IF($I26="",0,$I26),$G26*R$3*$F26+$H26))+IF($K26="да",0,$L26*R$3*$F26+$M26))/$F26 | S26: =(MIN(IF($J26="",1E+9,$J26),MAX(IF($I26="",0,$I26),$G26*S$3*$F26+$H26))+IF($K26="да",0,$L26*S$3*$F26+$M26))/$F26 | T26: =P26/P$3 | U26: =Q26/Q$3 | V26: =R26/R$3 | W26: =S26/S$3
A27: Direct merchant | B27: ThunderTix | C27: США | D27: Reserved Seating | E27: USD | F27: =INDEX('Курсы'!$B$4:$B$46,MATCH($E27,'Курсы'!$A$4:$A$46,0)) | G27: 0 | H27: 1.25 | K27: нет | L27: 0.029 | M27: 0.3 | N27: — | O27: Плюс $25/мес; схема $0,55 за место, мин. $250 | P27: =(MIN(IF($J27="",1E+9,$J27),MAX(IF($I27="",0,$I27),$G27*P$3*$F27+$H27))+IF($K27="да",0,$L27*P$3*$F27+$M27))/$F27 | Q27: =(MIN(IF($J27="",1E+9,$J27),MAX(IF($I27="",0,$I27),$G27*Q$3*$F27+$H27))+IF($K27="да",0,$L27*Q$3*$F27+$M27))/$F27 | R27: =(MIN(IF($J27="",1E+9,$J27),MAX(IF($I27="",0,$I27),$G27*R$3*$F27+$H27))+IF($K27="да",0,$L27*R$3*$F27+$M27))/$F27 | S27: =(MIN(IF($J27="",1E+9,$J27),MAX(IF($I27="",0,$I27),$G27*S$3*$F27+$H27))+IF($K27="да",0,$L27*S$3*$F27+$M27))/$F27 | T27: =P27/P$3 | U27: =Q27/Q$3 | V27: =R27/R$3 | W27: =S27/S$3
A28: Direct merchant | B28: Brushfire | C28: США | D28: Other events | E28: USD | F28: =INDEX('Курсы'!$B$4:$B$46,MATCH($E28,'Курсы'!$A$4:$A$46,0)) | G28: 0.01 | H28: 1.5 | K28: нет | L28: 0.029 | M28: 0.3 | N28: настраивается | P28: =(MIN(IF($J28="",1E+9,$J28),MAX(IF($I28="",0,$I28),$G28*P$3*$F28+$H28))+IF($K28="да",0,$L28*P$3*$F28+$M28))/$F28 | Q28: =(MIN(IF($J28="",1E+9,$J28),MAX(IF($I28="",0,$I28),$G28*Q$3*$F28+$H28))+IF($K28="да",0,$L28*Q$3*$F28+$M28))/$F28 | R28: =(MIN(IF($J28="",1E+9,$J28),MAX(IF($I28="",0,$I28),$G28*R$3*$F28+$H28))+IF($K28="да",0,$L28*R$3*$F28+$M28))/$F28 | S28: =(MIN(IF($J28="",1E+9,$J28),MAX(IF($I28="",0,$I28),$G28*S$3*$F28+$H28))+IF($K28="да",0,$L28*S$3*$F28+$M28))/$F28 | T28: =P28/P$3 | U28: =Q28/Q$3 | V28: =R28/R$3 | W28: =S28/S$3
A29: Direct merchant | B29: Ticketbud | C29: США | D29: Paid events | E29: USD | F29: =INDEX('Курсы'!$B$4:$B$46,MATCH($E29,'Курсы'!$A$4:$A$46,0)) | G29: 0.02 | H29: 0.99 | K29: нет | L29: 0.029 | M29: 0.3 | N29: покупатель | P29: =(MIN(IF($J29="",1E+9,$J29),MAX(IF($I29="",0,$I29),$G29*P$3*$F29+$H29))+IF($K29="да",0,$L29*P$3*$F29+$M29))/$F29 | Q29: =(MIN(IF($J29="",1E+9,$J29),MAX(IF($I29="",0,$I29),$G29*Q$3*$F29+$H29))+IF($K29="да",0,$L29*Q$3*$F29+$M29))/$F29 | R29: =(MIN(IF($J29="",1E+9,$J29),MAX(IF($I29="",0,$I29),$G29*R$3*$F29+$H29))+IF($K29="да",0,$L29*R$3*$F29+$M29))/$F29 | S29: =(MIN(IF($J29="",1E+9,$J29),MAX(IF($I29="",0,$I29),$G29*S$3*$F29+$H29))+IF($K29="да",0,$L29*S$3*$F29+$M29))/$F29 | T29: =P29/P$3 | U29: =Q29/Q$3 | V29: =R29/R$3 | W29: =S29/S$3
A30: Direct merchant | B30: BZUCO | C30: Чехия | D30: Základní (предоплаченный кредит) | E30: CZK | F30: =INDEX('Курсы'!$B$4:$B$46,MATCH($E30,'Курсы'!$A$4:$A$46,0)) | G30: 0.02 | H30: 0 | K30: нет | L30: 0.015 | M30: 6.5 | N30: настраивается | O30: Мин. годовой кредит 10–50 тыс. CZK | P30: =(MIN(IF($J30="",1E+9,$J30),MAX(IF($I30="",0,$I30),$G30*P$3*$F30+$H30))+IF($K30="да",0,$L30*P$3*$F30+$M30))/$F30 | Q30: =(MIN(IF($J30="",1E+9,$J30),MAX(IF($I30="",0,$I30),$G30*Q$3*$F30+$H30))+IF($K30="да",0,$L30*Q$3*$F30+$M30))/$F30 | R30: =(MIN(IF($J30="",1E+9,$J30),MAX(IF($I30="",0,$I30),$G30*R$3*$F30+$H30))+IF($K30="да",0,$L30*R$3*$F30+$M30))/$F30 | S30: =(MIN(IF($J30="",1E+9,$J30),MAX(IF($I30="",0,$I30),$G30*S$3*$F30+$H30))+IF($K30="да",0,$L30*S$3*$F30+$M30))/$F30 | T30: =P30/P$3 | U30: =Q30/Q$3 | V30: =R30/R$3 | W30: =S30/S$3
A31: Direct merchant | B31: Paysera Tickets | C31: Прибалтика | D31: Platform fee + Paysera Checkout | E31: EUR | F31: =INDEX('Курсы'!$B$4:$B$46,MATCH($E31,'Курсы'!$A$4:$A$46,0)) | G31: 0.02 | H31: 0 | I31: 0.15 | J31: 1 | K31: нет | L31: 0.009 | M31: 0.1 | N31: — | O31: Эквайринг Paysera 0,9 % (мин 0,10, макс 0,40) — потолок эквайринга в сценарии не учтён | P31: =(MIN(IF($J31="",1E+9,$J31),MAX(IF($I31="",0,$I31),$G31*P$3*$F31+$H31))+IF($K31="да",0,$L31*P$3*$F31+$M31))/$F31 | Q31: =(MIN(IF($J31="",1E+9,$J31),MAX(IF($I31="",0,$I31),$G31*Q$3*$F31+$H31))+IF($K31="да",0,$L31*Q$3*$F31+$M31))/$F31 | R31: =(MIN(IF($J31="",1E+9,$J31),MAX(IF($I31="",0,$I31),$G31*R$3*$F31+$H31))+IF($K31="да",0,$L31*R$3*$F31+$M31))/$F31 | S31: =(MIN(IF($J31="",1E+9,$J31),MAX(IF($I31="",0,$I31),$G31*S$3*$F31+$H31))+IF($K31="да",0,$L31*S$3*$F31+$M31))/$F31 | T31: =P31/P$3 | U31: =Q31/Q$3 | V31: =R31/R$3 | W31: =S31/S$3
A32: Direct merchant | B32: Shownet | C32: Литва | D32: System commission | E32: EUR | F32: =INDEX('Курсы'!$B$4:$B$46,MATCH($E32,'Курсы'!$A$4:$A$46,0)) | G32: 0.025 | H32: 0 | I32: 0.06 | K32: нет | L32: 0.015 | M32: 0.25 | N32: — | P32: =(MIN(IF($J32="",1E+9,$J32),MAX(IF($I32="",0,$I32),$G32*P$3*$F32+$H32))+IF($K32="да",0,$L32*P$3*$F32+$M32))/$F32 | Q32: =(MIN(IF($J32="",1E+9,$J32),MAX(IF($I32="",0,$I32),$G32*Q$3*$F32+$H32))+IF($K32="да",0,$L32*Q$3*$F32+$M32))/$F32 | R32: =(MIN(IF($J32="",1E+9,$J32),MAX(IF($I32="",0,$I32),$G32*R$3*$F32+$H32))+IF($K32="да",0,$L32*R$3*$F32+$M32))/$F32 | S32: =(MIN(IF($J32="",1E+9,$J32),MAX(IF($I32="",0,$I32),$G32*S$3*$F32+$H32))+IF($K32="да",0,$L32*S$3*$F32+$M32))/$F32 | T32: =P32/P$3 | U32: =Q32/Q$3 | V32: =R32/R$3 | W32: =S32/S$3
A33: Direct merchant | B33: eTichet.ro | C33: Румыния | D33: Standard | E33: RON | F33: =INDEX('Курсы'!$B$4:$B$46,MATCH($E33,'Курсы'!$A$4:$A$46,0)) | G33: 0.05 | H33: 0 | K33: нет | L33: 0.015 | M33: 1.34 | N33: организатор | P33: =(MIN(IF($J33="",1E+9,$J33),MAX(IF($I33="",0,$I33),$G33*P$3*$F33+$H33))+IF($K33="да",0,$L33*P$3*$F33+$M33))/$F33 | Q33: =(MIN(IF($J33="",1E+9,$J33),MAX(IF($I33="",0,$I33),$G33*Q$3*$F33+$H33))+IF($K33="да",0,$L33*Q$3*$F33+$M33))/$F33 | R33: =(MIN(IF($J33="",1E+9,$J33),MAX(IF($I33="",0,$I33),$G33*R$3*$F33+$H33))+IF($K33="да",0,$L33*R$3*$F33+$M33))/$F33 | S33: =(MIN(IF($J33="",1E+9,$J33),MAX(IF($I33="",0,$I33),$G33*S$3*$F33+$H33))+IF($K33="да",0,$L33*S$3*$F33+$M33))/$F33 | T33: =P33/P$3 | U33: =Q33/Q$3 | V33: =R33/R$3 | W33: =S33/S$3
A34: Direct merchant | B34: RegToEvent | C34: Украина / межд. | D34: Small events | E34: EUR | F34: =INDEX('Курсы'!$B$4:$B$46,MATCH($E34,'Курсы'!$A$4:$A$46,0)) | G34: 0.029 | H34: 0.39 | K34: нет | L34: 0.015 | M34: 0.25 | N34: настраивается | P34: =(MIN(IF($J34="",1E+9,$J34),MAX(IF($I34="",0,$I34),$G34*P$3*$F34+$H34))+IF($K34="да",0,$L34*P$3*$F34+$M34))/$F34 | Q34: =(MIN(IF($J34="",1E+9,$J34),MAX(IF($I34="",0,$I34),$G34*Q$3*$F34+$H34))+IF($K34="да",0,$L34*Q$3*$F34+$M34))/$F34 | R34: =(MIN(IF($J34="",1E+9,$J34),MAX(IF($I34="",0,$I34),$G34*R$3*$F34+$H34))+IF($K34="да",0,$L34*R$3*$F34+$M34))/$F34 | S34: =(MIN(IF($J34="",1E+9,$J34),MAX(IF($I34="",0,$I34),$G34*S$3*$F34+$H34))+IF($K34="да",0,$L34*S$3*$F34+$M34))/$F34 | T34: =P34/P$3 | U34: =Q34/Q$3 | V34: =R34/R$3 | W34: =S34/S$3
A35: Direct merchant | B35: RegToEvent | C35: Украина / межд. | D35: С местами (нижняя ставка) | E35: EUR | F35: =INDEX('Курсы'!$B$4:$B$46,MATCH($E35,'Курсы'!$A$4:$A$46,0)) | G35: 0.045 | H35: 0.3 | K35: нет | L35: 0.015 | M35: 0.25 | N35: настраивается | P35: =(MIN(IF($J35="",1E+9,$J35),MAX(IF($I35="",0,$I35),$G35*P$3*$F35+$H35))+IF($K35="да",0,$L35*P$3*$F35+$M35))/$F35 | Q35: =(MIN(IF($J35="",1E+9,$J35),MAX(IF($I35="",0,$I35),$G35*Q$3*$F35+$H35))+IF($K35="да",0,$L35*Q$3*$F35+$M35))/$F35 | R35: =(MIN(IF($J35="",1E+9,$J35),MAX(IF($I35="",0,$I35),$G35*R$3*$F35+$H35))+IF($K35="да",0,$L35*R$3*$F35+$M35))/$F35 | S35: =(MIN(IF($J35="",1E+9,$J35),MAX(IF($I35="",0,$I35),$G35*S$3*$F35+$H35))+IF($K35="да",0,$L35*S$3*$F35+$M35))/$F35 | T35: =P35/P$3 | U35: =Q35/Q$3 | V35: =R35/R$3 | W35: =S35/S$3
A36: Direct merchant | B36: Event.net.ua | C36: Украина | D36: Без мест | E36: UAH | F36: =INDEX('Курсы'!$B$4:$B$46,MATCH($E36,'Курсы'!$A$4:$A$46,0)) | G36: 0 | H36: 8 | K36: нет | L36: 0.013 | M36: 0 | N36: организатор | O36: Эквайринг monobank 1,3 % | P36: =(MIN(IF($J36="",1E+9,$J36),MAX(IF($I36="",0,$I36),$G36*P$3*$F36+$H36))+IF($K36="да",0,$L36*P$3*$F36+$M36))/$F36 | Q36: =(MIN(IF($J36="",1E+9,$J36),MAX(IF($I36="",0,$I36),$G36*Q$3*$F36+$H36))+IF($K36="да",0,$L36*Q$3*$F36+$M36))/$F36 | R36: =(MIN(IF($J36="",1E+9,$J36),MAX(IF($I36="",0,$I36),$G36*R$3*$F36+$H36))+IF($K36="да",0,$L36*R$3*$F36+$M36))/$F36 | S36: =(MIN(IF($J36="",1E+9,$J36),MAX(IF($I36="",0,$I36),$G36*S$3*$F36+$H36))+IF($K36="да",0,$L36*S$3*$F36+$M36))/$F36 | T36: =P36/P$3 | U36: =Q36/Q$3 | V36: =R36/R$3 | W36: =S36/S$3
A37: Direct merchant | B37: Tikzet | C37: Бразилия | D37: Предоплата 300 билетов | E37: BRL | F37: =INDEX('Курсы'!$B$4:$B$46,MATCH($E37,'Курсы'!$A$4:$A$46,0)) | G37: 0 | H37: 1.4 | K37: нет | L37: 0.0498 | M37: 0 | N37: организатор | O37: Эквайринг Mercado Pago BR 4,98 % (мгновенный) | P37: =(MIN(IF($J37="",1E+9,$J37),MAX(IF($I37="",0,$I37),$G37*P$3*$F37+$H37))+IF($K37="да",0,$L37*P$3*$F37+$M37))/$F37 | Q37: =(MIN(IF($J37="",1E+9,$J37),MAX(IF($I37="",0,$I37),$G37*Q$3*$F37+$H37))+IF($K37="да",0,$L37*Q$3*$F37+$M37))/$F37 | R37: =(MIN(IF($J37="",1E+9,$J37),MAX(IF($I37="",0,$I37),$G37*R$3*$F37+$H37))+IF($K37="да",0,$L37*R$3*$F37+$M37))/$F37 | S37: =(MIN(IF($J37="",1E+9,$J37),MAX(IF($I37="",0,$I37),$G37*S$3*$F37+$H37))+IF($K37="да",0,$L37*S$3*$F37+$M37))/$F37 | T37: =P37/P$3 | U37: =Q37/Q$3 | V37: =R37/R$3 | W37: =S37/S$3
A38: Direct merchant | B38: Tikzet | C38: Мексика | D38: Предоплата 300 билетов | E38: MXN | F38: =INDEX('Курсы'!$B$4:$B$46,MATCH($E38,'Курсы'!$A$4:$A$46,0)) | G38: 0 | H38: 4.8 | K38: нет | L38: 0.0405 | M38: 0 | N38: организатор | O38: Mercado Pago MX 3,49 % + IVA | P38: =(MIN(IF($J38="",1E+9,$J38),MAX(IF($I38="",0,$I38),$G38*P$3*$F38+$H38))+IF($K38="да",0,$L38*P$3*$F38+$M38))/$F38 | Q38: =(MIN(IF($J38="",1E+9,$J38),MAX(IF($I38="",0,$I38),$G38*Q$3*$F38+$H38))+IF($K38="да",0,$L38*Q$3*$F38+$M38))/$F38 | R38: =(MIN(IF($J38="",1E+9,$J38),MAX(IF($I38="",0,$I38),$G38*R$3*$F38+$H38))+IF($K38="да",0,$L38*R$3*$F38+$M38))/$F38 | S38: =(MIN(IF($J38="",1E+9,$J38),MAX(IF($I38="",0,$I38),$G38*S$3*$F38+$H38))+IF($K38="да",0,$L38*S$3*$F38+$M38))/$F38 | T38: =P38/P$3 | U38: =Q38/Q$3 | V38: =R38/R$3 | W38: =S38/S$3
A39: Direct merchant | B39: Enter.ar | C39: Аргентина | D39: Standard | E39: ARS | F39: =INDEX('Курсы'!$B$4:$B$46,MATCH($E39,'Курсы'!$A$4:$A$46,0)) | G39: 0.02 | H39: 0 | K39: нет | L39: 0.073 | M39: 0 | N39: организатор | O39: Mercado Pago AR ~6,29 % + IVA (мгновенно), неточно | P39: =(MIN(IF($J39="",1E+9,$J39),MAX(IF($I39="",0,$I39),$G39*P$3*$F39+$H39))+IF($K39="да",0,$L39*P$3*$F39+$M39))/$F39 | Q39: =(MIN(IF($J39="",1E+9,$J39),MAX(IF($I39="",0,$I39),$G39*Q$3*$F39+$H39))+IF($K39="да",0,$L39*Q$3*$F39+$M39))/$F39 | R39: =(MIN(IF($J39="",1E+9,$J39),MAX(IF($I39="",0,$I39),$G39*R$3*$F39+$H39))+IF($K39="да",0,$L39*R$3*$F39+$M39))/$F39 | S39: =(MIN(IF($J39="",1E+9,$J39),MAX(IF($I39="",0,$I39),$G39*S$3*$F39+$H39))+IF($K39="да",0,$L39*S$3*$F39+$M39))/$F39 | T39: =P39/P$3 | U39: =Q39/Q$3 | V39: =R39/R$3 | W39: =S39/S$3
A40: Direct merchant | B40: MaunaOne | C40: Мексика | D40: Inicia (бесплатный) | E40: MXN | F40: =INDEX('Курсы'!$B$4:$B$46,MATCH($E40,'Курсы'!$A$4:$A$46,0)) | G40: 0.05 | H40: 0 | K40: нет | L40: 0.042 | M40: 3.48 | N40: настраивается | O40: Stripe MX 3,6 % + 3 MXN + IVA | P40: =(MIN(IF($J40="",1E+9,$J40),MAX(IF($I40="",0,$I40),$G40*P$3*$F40+$H40))+IF($K40="да",0,$L40*P$3*$F40+$M40))/$F40 | Q40: =(MIN(IF($J40="",1E+9,$J40),MAX(IF($I40="",0,$I40),$G40*Q$3*$F40+$H40))+IF($K40="да",0,$L40*Q$3*$F40+$M40))/$F40 | R40: =(MIN(IF($J40="",1E+9,$J40),MAX(IF($I40="",0,$I40),$G40*R$3*$F40+$H40))+IF($K40="да",0,$L40*R$3*$F40+$M40))/$F40 | S40: =(MIN(IF($J40="",1E+9,$J40),MAX(IF($I40="",0,$I40),$G40*S$3*$F40+$H40))+IF($K40="да",0,$L40*S$3*$F40+$M40))/$F40 | T40: =P40/P$3 | U40: =Q40/Q$3 | V40: =R40/R$3 | W40: =S40/S$3
A41: Direct merchant | B41: Soundtix | C41: Испания | D41: Standard (билеты до €40) | E41: EUR | F41: =INDEX('Курсы'!$B$4:$B$46,MATCH($E41,'Курсы'!$A$4:$A$46,0)) | G41: 0.1 | H41: 0 | K41: да | L41: 0 | M41: 0 | N41: покупатель | O41: Stripe Connect; цифры на сайте противоречат друг другу | P41: =(MIN(IF($J41="",1E+9,$J41),MAX(IF($I41="",0,$I41),$G41*P$3*$F41+$H41))+IF($K41="да",0,$L41*P$3*$F41+$M41))/$F41 | Q41: =(MIN(IF($J41="",1E+9,$J41),MAX(IF($I41="",0,$I41),$G41*Q$3*$F41+$H41))+IF($K41="да",0,$L41*Q$3*$F41+$M41))/$F41 | R41: =(MIN(IF($J41="",1E+9,$J41),MAX(IF($I41="",0,$I41),$G41*R$3*$F41+$H41))+IF($K41="да",0,$L41*R$3*$F41+$M41))/$F41 | S41: =(MIN(IF($J41="",1E+9,$J41),MAX(IF($I41="",0,$I41),$G41*S$3*$F41+$H41))+IF($K41="да",0,$L41*S$3*$F41+$M41))/$F41 | T41: =P41/P$3 | U41: =Q41/Q$3 | V41: =R41/R$3 | W41: =S41/S$3
A42: Оба (показан direct) | B42: Cooltix | C42: ЕС (кроме HU) | D42: Online | E42: EUR | F42: =INDEX('Курсы'!$B$4:$B$46,MATCH($E42,'Курсы'!$A$4:$A$46,0)) | G42: 0.025 | H42: 0.25 | K42: нет | L42: 0.015 | M42: 0.25 | N42: покупатель (сбор до 10 %) | P42: =(MIN(IF($J42="",1E+9,$J42),MAX(IF($I42="",0,$I42),$G42*P$3*$F42+$H42))+IF($K42="да",0,$L42*P$3*$F42+$M42))/$F42 | Q42: =(MIN(IF($J42="",1E+9,$J42),MAX(IF($I42="",0,$I42),$G42*Q$3*$F42+$H42))+IF($K42="да",0,$L42*Q$3*$F42+$M42))/$F42 | R42: =(MIN(IF($J42="",1E+9,$J42),MAX(IF($I42="",0,$I42),$G42*R$3*$F42+$H42))+IF($K42="да",0,$L42*R$3*$F42+$M42))/$F42 | S42: =(MIN(IF($J42="",1E+9,$J42),MAX(IF($I42="",0,$I42),$G42*S$3*$F42+$H42))+IF($K42="да",0,$L42*S$3*$F42+$M42))/$F42 | T42: =P42/P$3 | U42: =Q42/Q$3 | V42: =R42/R$3 | W42: =S42/S$3
A43: Оба (показан direct) | B43: Cooltix | C43: ЕС (кроме HU) | D43: Seated | E43: EUR | F43: =INDEX('Курсы'!$B$4:$B$46,MATCH($E43,'Курсы'!$A$4:$A$46,0)) | G43: 0.03 | H43: 0.5 | K43: нет | L43: 0.015 | M43: 0.25 | N43: покупатель | P43: =(MIN(IF($J43="",1E+9,$J43),MAX(IF($I43="",0,$I43),$G43*P$3*$F43+$H43))+IF($K43="да",0,$L43*P$3*$F43+$M43))/$F43 | Q43: =(MIN(IF($J43="",1E+9,$J43),MAX(IF($I43="",0,$I43),$G43*Q$3*$F43+$H43))+IF($K43="да",0,$L43*Q$3*$F43+$M43))/$F43 | R43: =(MIN(IF($J43="",1E+9,$J43),MAX(IF($I43="",0,$I43),$G43*R$3*$F43+$H43))+IF($K43="да",0,$L43*R$3*$F43+$M43))/$F43 | S43: =(MIN(IF($J43="",1E+9,$J43),MAX(IF($I43="",0,$I43),$G43*S$3*$F43+$H43))+IF($K43="да",0,$L43*S$3*$F43+$M43))/$F43 | T43: =P43/P$3 | U43: =Q43/Q$3 | V43: =R43/R$3 | W43: =S43/S$3
A44: Оба (показан direct) | B44: Evenea | C44: Польша | D44: Commission | E44: PLN | F44: =INDEX('Курсы'!$B$4:$B$46,MATCH($E44,'Курсы'!$A$4:$A$46,0)) | G44: 0.029 | H44: 1 | K44: нет | L44: 0.015 | M44: 1 | N44: — | P44: =(MIN(IF($J44="",1E+9,$J44),MAX(IF($I44="",0,$I44),$G44*P$3*$F44+$H44))+IF($K44="да",0,$L44*P$3*$F44+$M44))/$F44 | Q44: =(MIN(IF($J44="",1E+9,$J44),MAX(IF($I44="",0,$I44),$G44*Q$3*$F44+$H44))+IF($K44="да",0,$L44*Q$3*$F44+$M44))/$F44 | R44: =(MIN(IF($J44="",1E+9,$J44),MAX(IF($I44="",0,$I44),$G44*R$3*$F44+$H44))+IF($K44="да",0,$L44*R$3*$F44+$M44))/$F44 | S44: =(MIN(IF($J44="",1E+9,$J44),MAX(IF($I44="",0,$I44),$G44*S$3*$F44+$H44))+IF($K44="да",0,$L44*S$3*$F44+$M44))/$F44 | T44: =P44/P$3 | U44: =Q44/Q$3 | V44: =R44/R$3 | W44: =S44/S$3
A45: Собирает на себя | B45: Eventbrite | C45: США | D45: Standard | E45: USD | F45: =INDEX('Курсы'!$B$4:$B$46,MATCH($E45,'Курсы'!$A$4:$A$46,0)) | G45: 0.037 | H45: 1.79 | K45: нет | L45: 0.029 | M45: 0 | N45: покупатель (настраивается) | O45: +2,9 % обработка платежа с заказа | P45: =(MIN(IF($J45="",1E+9,$J45),MAX(IF($I45="",0,$I45),$G45*P$3*$F45+$H45))+IF($K45="да",0,$L45*P$3*$F45+$M45))/$F45 | Q45: =(MIN(IF($J45="",1E+9,$J45),MAX(IF($I45="",0,$I45),$G45*Q$3*$F45+$H45))+IF($K45="да",0,$L45*Q$3*$F45+$M45))/$F45 | R45: =(MIN(IF($J45="",1E+9,$J45),MAX(IF($I45="",0,$I45),$G45*R$3*$F45+$H45))+IF($K45="да",0,$L45*R$3*$F45+$M45))/$F45 | S45: =(MIN(IF($J45="",1E+9,$J45),MAX(IF($I45="",0,$I45),$G45*S$3*$F45+$H45))+IF($K45="да",0,$L45*S$3*$F45+$M45))/$F45 | T45: =P45/P$3 | U45: =Q45/Q$3 | V45: =R45/R$3 | W45: =S45/S$3
A46: Собирает на себя | B46: Eventbrite | C46: UK | D46: Standard | E46: GBP | F46: =INDEX('Курсы'!$B$4:$B$46,MATCH($E46,'Курсы'!$A$4:$A$46,0)) | G46: 0.0695 | H46: 0.59 | K46: да | L46: 0 | M46: 0 | N46: покупатель (настраивается) | P46: =(MIN(IF($J46="",1E+9,$J46),MAX(IF($I46="",0,$I46),$G46*P$3*$F46+$H46))+IF($K46="да",0,$L46*P$3*$F46+$M46))/$F46 | Q46: =(MIN(IF($J46="",1E+9,$J46),MAX(IF($I46="",0,$I46),$G46*Q$3*$F46+$H46))+IF($K46="да",0,$L46*Q$3*$F46+$M46))/$F46 | R46: =(MIN(IF($J46="",1E+9,$J46),MAX(IF($I46="",0,$I46),$G46*R$3*$F46+$H46))+IF($K46="да",0,$L46*R$3*$F46+$M46))/$F46 | S46: =(MIN(IF($J46="",1E+9,$J46),MAX(IF($I46="",0,$I46),$G46*S$3*$F46+$H46))+IF($K46="да",0,$L46*S$3*$F46+$M46))/$F46 | T46: =P46/P$3 | U46: =Q46/Q$3 | V46: =R46/R$3 | W46: =S46/S$3
A47: Собирает на себя | B47: Eventbrite | C47: Ирландия | D47: Standard | E47: EUR | F47: =INDEX('Курсы'!$B$4:$B$46,MATCH($E47,'Курсы'!$A$4:$A$46,0)) | G47: 0.059 | H47: 0.79 | K47: да | L47: 0 | M47: 0 | N47: покупатель (настраивается) | P47: =(MIN(IF($J47="",1E+9,$J47),MAX(IF($I47="",0,$I47),$G47*P$3*$F47+$H47))+IF($K47="да",0,$L47*P$3*$F47+$M47))/$F47 | Q47: =(MIN(IF($J47="",1E+9,$J47),MAX(IF($I47="",0,$I47),$G47*Q$3*$F47+$H47))+IF($K47="да",0,$L47*Q$3*$F47+$M47))/$F47 | R47: =(MIN(IF($J47="",1E+9,$J47),MAX(IF($I47="",0,$I47),$G47*R$3*$F47+$H47))+IF($K47="да",0,$L47*R$3*$F47+$M47))/$F47 | S47: =(MIN(IF($J47="",1E+9,$J47),MAX(IF($I47="",0,$I47),$G47*S$3*$F47+$H47))+IF($K47="да",0,$L47*S$3*$F47+$M47))/$F47 | T47: =P47/P$3 | U47: =Q47/Q$3 | V47: =R47/R$3 | W47: =S47/S$3
A48: Собирает на себя | B48: Eventbrite | C48: Испания | D48: Essentials (старая таблица) | E48: EUR | F48: =INDEX('Курсы'!$B$4:$B$46,MATCH($E48,'Курсы'!$A$4:$A$46,0)) | G48: 0.06 | H48: 0 | K48: да | L48: 0 | M48: 0 | N48: покупатель (настраивается) | P48: =(MIN(IF($J48="",1E+9,$J48),MAX(IF($I48="",0,$I48),$G48*P$3*$F48+$H48))+IF($K48="да",0,$L48*P$3*$F48+$M48))/$F48 | Q48: =(MIN(IF($J48="",1E+9,$J48),MAX(IF($I48="",0,$I48),$G48*Q$3*$F48+$H48))+IF($K48="да",0,$L48*Q$3*$F48+$M48))/$F48 | R48: =(MIN(IF($J48="",1E+9,$J48),MAX(IF($I48="",0,$I48),$G48*R$3*$F48+$H48))+IF($K48="да",0,$L48*R$3*$F48+$M48))/$F48 | S48: =(MIN(IF($J48="",1E+9,$J48),MAX(IF($I48="",0,$I48),$G48*S$3*$F48+$H48))+IF($K48="да",0,$L48*S$3*$F48+$M48))/$F48 | T48: =P48/P$3 | U48: =Q48/Q$3 | V48: =R48/R$3 | W48: =S48/S$3
A49: Собирает на себя | B49: Eventbrite | C49: Германия | D49: Essentials (старая таблица) | E49: EUR | F49: =INDEX('Курсы'!$B$4:$B$46,MATCH($E49,'Курсы'!$A$4:$A$46,0)) | G49: 0.055 | H49: 0 | K49: да | L49: 0 | M49: 0 | N49: покупатель (настраивается) | P49: =(MIN(IF($J49="",1E+9,$J49),MAX(IF($I49="",0,$I49),$G49*P$3*$F49+$H49))+IF($K49="да",0,$L49*P$3*$F49+$M49))/$F49 | Q49: =(MIN(IF($J49="",1E+9,$J49),MAX(IF($I49="",0,$I49),$G49*Q$3*$F49+$H49))+IF($K49="да",0,$L49*Q$3*$F49+$M49))/$F49 | R49: =(MIN(IF($J49="",1E+9,$J49),MAX(IF($I49="",0,$I49),$G49*R$3*$F49+$H49))+IF($K49="да",0,$L49*R$3*$F49+$M49))/$F49 | S49: =(MIN(IF($J49="",1E+9,$J49),MAX(IF($I49="",0,$I49),$G49*S$3*$F49+$H49))+IF($K49="да",0,$L49*S$3*$F49+$M49))/$F49 | T49: =P49/P$3 | U49: =Q49/Q$3 | V49: =R49/R$3 | W49: =S49/S$3
A50: Собирает на себя | B50: Eventbrite | C50: Чехия | D50: Essentials (старая таблица) | E50: CZK | F50: =INDEX('Курсы'!$B$4:$B$46,MATCH($E50,'Курсы'!$A$4:$A$46,0)) | G50: 0.01 | H50: 19 | K50: да | L50: 0 | M50: 0 | N50: покупатель (настраивается) | O50: Включена ли обработка платежа — проверить | P50: =(MIN(IF($J50="",1E+9,$J50),MAX(IF($I50="",0,$I50),$G50*P$3*$F50+$H50))+IF($K50="да",0,$L50*P$3*$F50+$M50))/$F50 | Q50: =(MIN(IF($J50="",1E+9,$J50),MAX(IF($I50="",0,$I50),$G50*Q$3*$F50+$H50))+IF($K50="да",0,$L50*Q$3*$F50+$M50))/$F50 | R50: =(MIN(IF($J50="",1E+9,$J50),MAX(IF($I50="",0,$I50),$G50*R$3*$F50+$H50))+IF($K50="да",0,$L50*R$3*$F50+$M50))/$F50 | S50: =(MIN(IF($J50="",1E+9,$J50),MAX(IF($I50="",0,$I50),$G50*S$3*$F50+$H50))+IF($K50="да",0,$L50*S$3*$F50+$M50))/$F50 | T50: =P50/P$3 | U50: =Q50/Q$3 | V50: =R50/R$3 | W50: =S50/S$3
A51: Собирает на себя | B51: Eventim.Light | C51: Германия | D51: Свой магазин | E51: EUR | F51: =INDEX('Курсы'!$B$4:$B$46,MATCH($E51,'Курсы'!$A$4:$A$46,0)) | G51: 0.035 | H51: 0.49 | K51: да | L51: 0 | M51: 0 | N51: настраивается | O51: Сеть Eventim +10 % | P51: =(MIN(IF($J51="",1E+9,$J51),MAX(IF($I51="",0,$I51),$G51*P$3*$F51+$H51))+IF($K51="да",0,$L51*P$3*$F51+$M51))/$F51 | Q51: =(MIN(IF($J51="",1E+9,$J51),MAX(IF($I51="",0,$I51),$G51*Q$3*$F51+$H51))+IF($K51="да",0,$L51*Q$3*$F51+$M51))/$F51 | R51: =(MIN(IF($J51="",1E+9,$J51),MAX(IF($I51="",0,$I51),$G51*R$3*$F51+$H51))+IF($K51="да",0,$L51*R$3*$F51+$M51))/$F51 | S51: =(MIN(IF($J51="",1E+9,$J51),MAX(IF($I51="",0,$I51),$G51*S$3*$F51+$H51))+IF($K51="да",0,$L51*S$3*$F51+$M51))/$F51 | T51: =P51/P$3 | U51: =Q51/Q$3 | V51: =R51/R$3 | W51: =S51/S$3
A52: Собирает на себя | B52: Eventim.Light | C52: Испания | D52: Свой магазин | E52: EUR | F52: =INDEX('Курсы'!$B$4:$B$46,MATCH($E52,'Курсы'!$A$4:$A$46,0)) | G52: 0.035 | H52: 0.4 | K52: да | L52: 0 | M52: 0 | N52: настраивается | O52: Через entradas.com 9,5 % + 0,40 | P52: =(MIN(IF($J52="",1E+9,$J52),MAX(IF($I52="",0,$I52),$G52*P$3*$F52+$H52))+IF($K52="да",0,$L52*P$3*$F52+$M52))/$F52 | Q52: =(MIN(IF($J52="",1E+9,$J52),MAX(IF($I52="",0,$I52),$G52*Q$3*$F52+$H52))+IF($K52="да",0,$L52*Q$3*$F52+$M52))/$F52 | R52: =(MIN(IF($J52="",1E+9,$J52),MAX(IF($I52="",0,$I52),$G52*R$3*$F52+$H52))+IF($K52="да",0,$L52*R$3*$F52+$M52))/$F52 | S52: =(MIN(IF($J52="",1E+9,$J52),MAX(IF($I52="",0,$I52),$G52*S$3*$F52+$H52))+IF($K52="да",0,$L52*S$3*$F52+$M52))/$F52 | T52: =P52/P$3 | U52: =Q52/Q$3 | V52: =R52/R$3 | W52: =S52/S$3
A53: Собирает на себя | B53: Eventim.Light | C53: Нидерланды | D53: Свой магазин | E53: EUR | F53: =INDEX('Курсы'!$B$4:$B$46,MATCH($E53,'Курсы'!$A$4:$A$46,0)) | G53: 0.02 | H53: 0.49 | K53: да | L53: 0 | M53: 0 | N53: настраивается | P53: =(MIN(IF($J53="",1E+9,$J53),MAX(IF($I53="",0,$I53),$G53*P$3*$F53+$H53))+IF($K53="да",0,$L53*P$3*$F53+$M53))/$F53 | Q53: =(MIN(IF($J53="",1E+9,$J53),MAX(IF($I53="",0,$I53),$G53*Q$3*$F53+$H53))+IF($K53="да",0,$L53*Q$3*$F53+$M53))/$F53 | R53: =(MIN(IF($J53="",1E+9,$J53),MAX(IF($I53="",0,$I53),$G53*R$3*$F53+$H53))+IF($K53="да",0,$L53*R$3*$F53+$M53))/$F53 | S53: =(MIN(IF($J53="",1E+9,$J53),MAX(IF($I53="",0,$I53),$G53*S$3*$F53+$H53))+IF($K53="да",0,$L53*S$3*$F53+$M53))/$F53 | T53: =P53/P$3 | U53: =Q53/Q$3 | V53: =R53/R$3 | W53: =S53/S$3
A54: Собирает на себя | B54: Eventim.Light | C54: Австрия | D54: Свой магазин | E54: EUR | F54: =INDEX('Курсы'!$B$4:$B$46,MATCH($E54,'Курсы'!$A$4:$A$46,0)) | G54: 0.05 | H54: 0 | I54: 0.39 | K54: да | L54: 0 | M54: 0 | N54: настраивается | P54: =(MIN(IF($J54="",1E+9,$J54),MAX(IF($I54="",0,$I54),$G54*P$3*$F54+$H54))+IF($K54="да",0,$L54*P$3*$F54+$M54))/$F54 | Q54: =(MIN(IF($J54="",1E+9,$J54),MAX(IF($I54="",0,$I54),$G54*Q$3*$F54+$H54))+IF($K54="да",0,$L54*Q$3*$F54+$M54))/$F54 | R54: =(MIN(IF($J54="",1E+9,$J54),MAX(IF($I54="",0,$I54),$G54*R$3*$F54+$H54))+IF($K54="да",0,$L54*R$3*$F54+$M54))/$F54 | S54: =(MIN(IF($J54="",1E+9,$J54),MAX(IF($I54="",0,$I54),$G54*S$3*$F54+$H54))+IF($K54="да",0,$L54*S$3*$F54+$M54))/$F54 | T54: =P54/P$3 | U54: =Q54/Q$3 | V54: =R54/R$3 | W54: =S54/S$3
A55: Собирает на себя | B55: Eventim.Light | C55: Финляндия | D55: Standard | E55: EUR | F55: =INDEX('Курсы'!$B$4:$B$46,MATCH($E55,'Курсы'!$A$4:$A$46,0)) | G55: 0.12 | H55: 0 | K55: да | L55: 0 | M55: 0 | N55: настраивается | P55: =(MIN(IF($J55="",1E+9,$J55),MAX(IF($I55="",0,$I55),$G55*P$3*$F55+$H55))+IF($K55="да",0,$L55*P$3*$F55+$M55))/$F55 | Q55: =(MIN(IF($J55="",1E+9,$J55),MAX(IF($I55="",0,$I55),$G55*Q$3*$F55+$H55))+IF($K55="да",0,$L55*Q$3*$F55+$M55))/$F55 | R55: =(MIN(IF($J55="",1E+9,$J55),MAX(IF($I55="",0,$I55),$G55*R$3*$F55+$H55))+IF($K55="да",0,$L55*R$3*$F55+$M55))/$F55 | S55: =(MIN(IF($J55="",1E+9,$J55),MAX(IF($I55="",0,$I55),$G55*S$3*$F55+$H55))+IF($K55="да",0,$L55*S$3*$F55+$M55))/$F55 | T55: =P55/P$3 | U55: =Q55/Q$3 | V55: =R55/R$3 | W55: =S55/S$3
A56: Собирает на себя | B56: Ticketcorner.Light | C56: Швейцария | D56: Свой магазин | E56: CHF | F56: =INDEX('Курсы'!$B$4:$B$46,MATCH($E56,'Курсы'!$A$4:$A$46,0)) | G56: 0.04 | H56: 0.5 | K56: да | L56: 0 | M56: 0 | N56: настраивается | O56: Через сеть Ticketcorner 12 % + 0,50 | P56: =(MIN(IF($J56="",1E+9,$J56),MAX(IF($I56="",0,$I56),$G56*P$3*$F56+$H56))+IF($K56="да",0,$L56*P$3*$F56+$M56))/$F56 | Q56: =(MIN(IF($J56="",1E+9,$J56),MAX(IF($I56="",0,$I56),$G56*Q$3*$F56+$H56))+IF($K56="да",0,$L56*Q$3*$F56+$M56))/$F56 | R56: =(MIN(IF($J56="",1E+9,$J56),MAX(IF($I56="",0,$I56),$G56*R$3*$F56+$H56))+IF($K56="да",0,$L56*R$3*$F56+$M56))/$F56 | S56: =(MIN(IF($J56="",1E+9,$J56),MAX(IF($I56="",0,$I56),$G56*S$3*$F56+$H56))+IF($K56="да",0,$L56*S$3*$F56+$M56))/$F56 | T56: =P56/P$3 | U56: =Q56/Q$3 | V56: =R56/R$3 | W56: =S56/S$3
A57: Собирает на себя | B57: Eventfrog | C57: Швейцария | D57: Plus | E57: CHF | F57: =INDEX('Курсы'!$B$4:$B$46,MATCH($E57,'Курсы'!$A$4:$A$46,0)) | G57: 0.024 | H57: 0.49 | K57: да | L57: 0 | M57: 0 | N57: организатор | P57: =(MIN(IF($J57="",1E+9,$J57),MAX(IF($I57="",0,$I57),$G57*P$3*$F57+$H57))+IF($K57="да",0,$L57*P$3*$F57+$M57))/$F57 | Q57: =(MIN(IF($J57="",1E+9,$J57),MAX(IF($I57="",0,$I57),$G57*Q$3*$F57+$H57))+IF($K57="да",0,$L57*Q$3*$F57+$M57))/$F57 | R57: =(MIN(IF($J57="",1E+9,$J57),MAX(IF($I57="",0,$I57),$G57*R$3*$F57+$H57))+IF($K57="да",0,$L57*R$3*$F57+$M57))/$F57 | S57: =(MIN(IF($J57="",1E+9,$J57),MAX(IF($I57="",0,$I57),$G57*S$3*$F57+$H57))+IF($K57="да",0,$L57*S$3*$F57+$M57))/$F57 | T57: =P57/P$3 | U57: =Q57/Q$3 | V57: =R57/R$3 | W57: =S57/S$3
A58: Собирает на себя | B58: Weezevent | C58: Франция / EUR | D58: WeezTicket | E58: EUR | F58: =INDEX('Курсы'!$B$4:$B$46,MATCH($E58,'Курсы'!$A$4:$A$46,0)) | G58: 0.025 | H58: 0 | I58: 0.99 | K58: да | L58: 0 | M58: 0 | N58: — | P58: =(MIN(IF($J58="",1E+9,$J58),MAX(IF($I58="",0,$I58),$G58*P$3*$F58+$H58))+IF($K58="да",0,$L58*P$3*$F58+$M58))/$F58 | Q58: =(MIN(IF($J58="",1E+9,$J58),MAX(IF($I58="",0,$I58),$G58*Q$3*$F58+$H58))+IF($K58="да",0,$L58*Q$3*$F58+$M58))/$F58 | R58: =(MIN(IF($J58="",1E+9,$J58),MAX(IF($I58="",0,$I58),$G58*R$3*$F58+$H58))+IF($K58="да",0,$L58*R$3*$F58+$M58))/$F58 | S58: =(MIN(IF($J58="",1E+9,$J58),MAX(IF($I58="",0,$I58),$G58*S$3*$F58+$H58))+IF($K58="да",0,$L58*S$3*$F58+$M58))/$F58 | T58: =P58/P$3 | U58: =Q58/Q$3 | V58: =R58/R$3 | W58: =S58/S$3
A59: Собирает на себя | B59: Weezevent | C59: Швейцария | D59: WeezTicket | E59: CHF | F59: =INDEX('Курсы'!$B$4:$B$46,MATCH($E59,'Курсы'!$A$4:$A$46,0)) | G59: 0.025 | H59: 0.99 | K59: да | L59: 0 | M59: 0 | N59: — | P59: =(MIN(IF($J59="",1E+9,$J59),MAX(IF($I59="",0,$I59),$G59*P$3*$F59+$H59))+IF($K59="да",0,$L59*P$3*$F59+$M59))/$F59 | Q59: =(MIN(IF($J59="",1E+9,$J59),MAX(IF($I59="",0,$I59),$G59*Q$3*$F59+$H59))+IF($K59="да",0,$L59*Q$3*$F59+$M59))/$F59 | R59: =(MIN(IF($J59="",1E+9,$J59),MAX(IF($I59="",0,$I59),$G59*R$3*$F59+$H59))+IF($K59="да",0,$L59*R$3*$F59+$M59))/$F59 | S59: =(MIN(IF($J59="",1E+9,$J59),MAX(IF($I59="",0,$I59),$G59*S$3*$F59+$H59))+IF($K59="да",0,$L59*S$3*$F59+$M59))/$F59 | T59: =P59/P$3 | U59: =Q59/Q$3 | V59: =R59/R$3 | W59: =S59/S$3
A60: Собирает на себя | B60: Billetweb | C60: Франция | D60: Standard | E60: EUR | F60: =INDEX('Курсы'!$B$4:$B$46,MATCH($E60,'Курсы'!$A$4:$A$46,0)) | G60: 0.01 | H60: 0.29 | K60: да | L60: 0 | M60: 0 | N60: настраивается | P60: =(MIN(IF($J60="",1E+9,$J60),MAX(IF($I60="",0,$I60),$G60*P$3*$F60+$H60))+IF($K60="да",0,$L60*P$3*$F60+$M60))/$F60 | Q60: =(MIN(IF($J60="",1E+9,$J60),MAX(IF($I60="",0,$I60),$G60*Q$3*$F60+$H60))+IF($K60="да",0,$L60*Q$3*$F60+$M60))/$F60 | R60: =(MIN(IF($J60="",1E+9,$J60),MAX(IF($I60="",0,$I60),$G60*R$3*$F60+$H60))+IF($K60="да",0,$L60*R$3*$F60+$M60))/$F60 | S60: =(MIN(IF($J60="",1E+9,$J60),MAX(IF($I60="",0,$I60),$G60*S$3*$F60+$H60))+IF($K60="да",0,$L60*S$3*$F60+$M60))/$F60 | T60: =P60/P$3 | U60: =Q60/Q$3 | V60: =R60/R$3 | W60: =S60/S$3
A61: Собирает на себя | B61: Yurplan | C61: Франция | D61: Standard | E61: EUR | F61: =INDEX('Курсы'!$B$4:$B$46,MATCH($E61,'Курсы'!$A$4:$A$46,0)) | G61: 0.01 | H61: 0.39 | K61: да | L61: 0 | M61: 0 | N61: организатор | P61: =(MIN(IF($J61="",1E+9,$J61),MAX(IF($I61="",0,$I61),$G61*P$3*$F61+$H61))+IF($K61="да",0,$L61*P$3*$F61+$M61))/$F61 | Q61: =(MIN(IF($J61="",1E+9,$J61),MAX(IF($I61="",0,$I61),$G61*Q$3*$F61+$H61))+IF($K61="да",0,$L61*Q$3*$F61+$M61))/$F61 | R61: =(MIN(IF($J61="",1E+9,$J61),MAX(IF($I61="",0,$I61),$G61*R$3*$F61+$H61))+IF($K61="да",0,$L61*R$3*$F61+$M61))/$F61 | S61: =(MIN(IF($J61="",1E+9,$J61),MAX(IF($I61="",0,$I61),$G61*S$3*$F61+$H61))+IF($K61="да",0,$L61*S$3*$F61+$M61))/$F61 | T61: =P61/P$3 | U61: =Q61/Q$3 | V61: =R61/R$3 | W61: =S61/S$3
A62: Собирает на себя | B62: Fienta | C62: Глобально | D62: Paid tickets | E62: EUR | F62: =INDEX('Курсы'!$B$4:$B$46,MATCH($E62,'Курсы'!$A$4:$A$46,0)) | G62: 0.035 | H62: 0 | I62: 0.4 | K62: да | L62: 0 | M62: 0 | N62: организатор | O62: Страница отдала USD; EUR не подтверждён | P62: =(MIN(IF($J62="",1E+9,$J62),MAX(IF($I62="",0,$I62),$G62*P$3*$F62+$H62))+IF($K62="да",0,$L62*P$3*$F62+$M62))/$F62 | Q62: =(MIN(IF($J62="",1E+9,$J62),MAX(IF($I62="",0,$I62),$G62*Q$3*$F62+$H62))+IF($K62="да",0,$L62*Q$3*$F62+$M62))/$F62 | R62: =(MIN(IF($J62="",1E+9,$J62),MAX(IF($I62="",0,$I62),$G62*R$3*$F62+$H62))+IF($K62="да",0,$L62*R$3*$F62+$M62))/$F62 | S62: =(MIN(IF($J62="",1E+9,$J62),MAX(IF($I62="",0,$I62),$G62*S$3*$F62+$H62))+IF($K62="да",0,$L62*S$3*$F62+$M62))/$F62 | T62: =P62/P$3 | U62: =Q62/Q$3 | V62: =R62/R$3 | W62: =S62/S$3
A63: Собирает на себя | B63: Ticketkantoor | C63: Нидерланды | D63: All-in | E63: EUR | F63: =INDEX('Курсы'!$B$4:$B$46,MATCH($E63,'Курсы'!$A$4:$A$46,0)) | G63: 0 | H63: 0.8 | K63: да | L63: 0 | M63: 0 | N63: организатор | P63: =(MIN(IF($J63="",1E+9,$J63),MAX(IF($I63="",0,$I63),$G63*P$3*$F63+$H63))+IF($K63="да",0,$L63*P$3*$F63+$M63))/$F63 | Q63: =(MIN(IF($J63="",1E+9,$J63),MAX(IF($I63="",0,$I63),$G63*Q$3*$F63+$H63))+IF($K63="да",0,$L63*Q$3*$F63+$M63))/$F63 | R63: =(MIN(IF($J63="",1E+9,$J63),MAX(IF($I63="",0,$I63),$G63*R$3*$F63+$H63))+IF($K63="да",0,$L63*R$3*$F63+$M63))/$F63 | S63: =(MIN(IF($J63="",1E+9,$J63),MAX(IF($I63="",0,$I63),$G63*S$3*$F63+$H63))+IF($K63="да",0,$L63*S$3*$F63+$M63))/$F63 | T63: =P63/P$3 | U63: =Q63/Q$3 | V63: =R63/R$3 | W63: =S63/S$3
A64: Собирает на себя | B64: Billetto | C64: Европа | D64: Essential | E64: EUR | F64: =INDEX('Курсы'!$B$4:$B$46,MATCH($E64,'Курсы'!$A$4:$A$46,0)) | G64: 0.0399 | H64: 0.9 | K64: да | L64: 0 | M64: 0 | N64: покупатель | P64: =(MIN(IF($J64="",1E+9,$J64),MAX(IF($I64="",0,$I64),$G64*P$3*$F64+$H64))+IF($K64="да",0,$L64*P$3*$F64+$M64))/$F64 | Q64: =(MIN(IF($J64="",1E+9,$J64),MAX(IF($I64="",0,$I64),$G64*Q$3*$F64+$H64))+IF($K64="да",0,$L64*Q$3*$F64+$M64))/$F64 | R64: =(MIN(IF($J64="",1E+9,$J64),MAX(IF($I64="",0,$I64),$G64*R$3*$F64+$H64))+IF($K64="да",0,$L64*R$3*$F64+$M64))/$F64 | S64: =(MIN(IF($J64="",1E+9,$J64),MAX(IF($I64="",0,$I64),$G64*S$3*$F64+$H64))+IF($K64="да",0,$L64*S$3*$F64+$M64))/$F64 | T64: =P64/P$3 | U64: =Q64/Q$3 | V64: =R64/R$3 | W64: =S64/S$3
A65: Собирает на себя | B65: Weeztix (ex-Eventix) | C65: ЕС | D65: Стандарт | E65: EUR | F65: =INDEX('Курсы'!$B$4:$B$46,MATCH($E65,'Курсы'!$A$4:$A$46,0)) | G65: 0.0385 | H65: 0.67 | K65: да | L65: 0 | M65: 0 | N65: покупатель | O65: Держит ≥10 % выручки до события | P65: =(MIN(IF($J65="",1E+9,$J65),MAX(IF($I65="",0,$I65),$G65*P$3*$F65+$H65))+IF($K65="да",0,$L65*P$3*$F65+$M65))/$F65 | Q65: =(MIN(IF($J65="",1E+9,$J65),MAX(IF($I65="",0,$I65),$G65*Q$3*$F65+$H65))+IF($K65="да",0,$L65*Q$3*$F65+$M65))/$F65 | R65: =(MIN(IF($J65="",1E+9,$J65),MAX(IF($I65="",0,$I65),$G65*R$3*$F65+$H65))+IF($K65="да",0,$L65*R$3*$F65+$M65))/$F65 | S65: =(MIN(IF($J65="",1E+9,$J65),MAX(IF($I65="",0,$I65),$G65*S$3*$F65+$H65))+IF($K65="да",0,$L65*S$3*$F65+$M65))/$F65 | T65: =P65/P$3 | U65: =Q65/Q$3 | V65: =R65/R$3 | W65: =S65/S$3
A66: Собирает на себя | B66: DICE | C66: UK | D66: Self sign-up | E66: GBP | F66: =INDEX('Курсы'!$B$4:$B$46,MATCH($E66,'Курсы'!$A$4:$A$46,0)) | G66: 0.085 | H66: 0 | I66: 1 | K66: нет | L66: 0.025 | M66: 0 | N66: покупатель | O66: +2,5 % транзакция, +НДС; резерв 5 % на 6 мес. | P66: =(MIN(IF($J66="",1E+9,$J66),MAX(IF($I66="",0,$I66),$G66*P$3*$F66+$H66))+IF($K66="да",0,$L66*P$3*$F66+$M66))/$F66 | Q66: =(MIN(IF($J66="",1E+9,$J66),MAX(IF($I66="",0,$I66),$G66*Q$3*$F66+$H66))+IF($K66="да",0,$L66*Q$3*$F66+$M66))/$F66 | R66: =(MIN(IF($J66="",1E+9,$J66),MAX(IF($I66="",0,$I66),$G66*R$3*$F66+$H66))+IF($K66="да",0,$L66*R$3*$F66+$M66))/$F66 | S66: =(MIN(IF($J66="",1E+9,$J66),MAX(IF($I66="",0,$I66),$G66*S$3*$F66+$H66))+IF($K66="да",0,$L66*S$3*$F66+$M66))/$F66 | T66: =P66/P$3 | U66: =Q66/Q$3 | V66: =R66/R$3 | W66: =S66/S$3
A67: Собирает на себя | B67: TicketSource | C67: UK | D67: Свой эквайринг TicketSource | E67: GBP | F67: =INDEX('Курсы'!$B$4:$B$46,MATCH($E67,'Курсы'!$A$4:$A$46,0)) | G67: 0.07 | H67: 0 | I67: 0.25 | K67: да | L67: 0 | M67: 0 | N67: настраивается | O67: С заказа; +НДС | P67: =(MIN(IF($J67="",1E+9,$J67),MAX(IF($I67="",0,$I67),$G67*P$3*$F67+$H67))+IF($K67="да",0,$L67*P$3*$F67+$M67))/$F67 | Q67: =(MIN(IF($J67="",1E+9,$J67),MAX(IF($I67="",0,$I67),$G67*Q$3*$F67+$H67))+IF($K67="да",0,$L67*Q$3*$F67+$M67))/$F67 | R67: =(MIN(IF($J67="",1E+9,$J67),MAX(IF($I67="",0,$I67),$G67*R$3*$F67+$H67))+IF($K67="да",0,$L67*R$3*$F67+$M67))/$F67 | S67: =(MIN(IF($J67="",1E+9,$J67),MAX(IF($I67="",0,$I67),$G67*S$3*$F67+$H67))+IF($K67="да",0,$L67*S$3*$F67+$M67))/$F67 | T67: =P67/P$3 | U67: =Q67/Q$3 | V67: =R67/R$3 | W67: =S67/S$3
A68: Собирает на себя | B68: Humanitix | C68: UK | D68: Standard | E68: GBP | F68: =INDEX('Курсы'!$B$4:$B$46,MATCH($E68,'Курсы'!$A$4:$A$46,0)) | G68: 0.056 | H68: 0.55 | K68: да | L68: 0 | M68: 0 | N68: покупатель | P68: =(MIN(IF($J68="",1E+9,$J68),MAX(IF($I68="",0,$I68),$G68*P$3*$F68+$H68))+IF($K68="да",0,$L68*P$3*$F68+$M68))/$F68 | Q68: =(MIN(IF($J68="",1E+9,$J68),MAX(IF($I68="",0,$I68),$G68*Q$3*$F68+$H68))+IF($K68="да",0,$L68*Q$3*$F68+$M68))/$F68 | R68: =(MIN(IF($J68="",1E+9,$J68),MAX(IF($I68="",0,$I68),$G68*R$3*$F68+$H68))+IF($K68="да",0,$L68*R$3*$F68+$M68))/$F68 | S68: =(MIN(IF($J68="",1E+9,$J68),MAX(IF($I68="",0,$I68),$G68*S$3*$F68+$H68))+IF($K68="да",0,$L68*S$3*$F68+$M68))/$F68 | T68: =P68/P$3 | U68: =Q68/Q$3 | V68: =R68/R$3 | W68: =S68/S$3
A69: Собирает на себя | B69: Posh | C69: США | D69: Standard | E69: USD | F69: =INDEX('Курсы'!$B$4:$B$46,MATCH($E69,'Курсы'!$A$4:$A$46,0)) | G69: 0.1 | H69: 0.99 | K69: да | L69: 0 | M69: 0 | N69: покупатель | O69: [third_party] | P69: =(MIN(IF($J69="",1E+9,$J69),MAX(IF($I69="",0,$I69),$G69*P$3*$F69+$H69))+IF($K69="да",0,$L69*P$3*$F69+$M69))/$F69 | Q69: =(MIN(IF($J69="",1E+9,$J69),MAX(IF($I69="",0,$I69),$G69*Q$3*$F69+$H69))+IF($K69="да",0,$L69*Q$3*$F69+$M69))/$F69 | R69: =(MIN(IF($J69="",1E+9,$J69),MAX(IF($I69="",0,$I69),$G69*R$3*$F69+$H69))+IF($K69="да",0,$L69*R$3*$F69+$M69))/$F69 | S69: =(MIN(IF($J69="",1E+9,$J69),MAX(IF($I69="",0,$I69),$G69*S$3*$F69+$H69))+IF($K69="да",0,$L69*S$3*$F69+$M69))/$F69 | T69: =P69/P$3 | U69: =Q69/Q$3 | V69: =R69/R$3 | W69: =S69/S$3
A70: Собирает на себя | B70: Ludus | C70: США | D70: Standard | E70: USD | F70: =INDEX('Курсы'!$B$4:$B$46,MATCH($E70,'Курсы'!$A$4:$A$46,0)) | G70: 0.05 | H70: 0.75 | K70: да | L70: 0 | M70: 0 | N70: настраивается | O70: Рассадка бесплатно, чарджбэки на Ludus | P70: =(MIN(IF($J70="",1E+9,$J70),MAX(IF($I70="",0,$I70),$G70*P$3*$F70+$H70))+IF($K70="да",0,$L70*P$3*$F70+$M70))/$F70 | Q70: =(MIN(IF($J70="",1E+9,$J70),MAX(IF($I70="",0,$I70),$G70*Q$3*$F70+$H70))+IF($K70="да",0,$L70*Q$3*$F70+$M70))/$F70 | R70: =(MIN(IF($J70="",1E+9,$J70),MAX(IF($I70="",0,$I70),$G70*R$3*$F70+$H70))+IF($K70="да",0,$L70*R$3*$F70+$M70))/$F70 | S70: =(MIN(IF($J70="",1E+9,$J70),MAX(IF($I70="",0,$I70),$G70*S$3*$F70+$H70))+IF($K70="да",0,$L70*S$3*$F70+$M70))/$F70 | T70: =P70/P$3 | U70: =Q70/Q$3 | V70: =R70/R$3 | W70: =S70/S$3
A71: Собирает на себя | B71: Showpass | C71: Канада | D71: Essential | E71: CAD | F71: =INDEX('Курсы'!$B$4:$B$46,MATCH($E71,'Курсы'!$A$4:$A$46,0)) | G71: 0.01 | H71: 0.59 | K71: нет | L71: 0.029 | M71: 0.3 | N71: настраивается | O71: Схемы мест только на Professional | P71: =(MIN(IF($J71="",1E+9,$J71),MAX(IF($I71="",0,$I71),$G71*P$3*$F71+$H71))+IF($K71="да",0,$L71*P$3*$F71+$M71))/$F71 | Q71: =(MIN(IF($J71="",1E+9,$J71),MAX(IF($I71="",0,$I71),$G71*Q$3*$F71+$H71))+IF($K71="да",0,$L71*Q$3*$F71+$M71))/$F71 | R71: =(MIN(IF($J71="",1E+9,$J71),MAX(IF($I71="",0,$I71),$G71*R$3*$F71+$H71))+IF($K71="да",0,$L71*R$3*$F71+$M71))/$F71 | S71: =(MIN(IF($J71="",1E+9,$J71),MAX(IF($I71="",0,$I71),$G71*S$3*$F71+$H71))+IF($K71="да",0,$L71*S$3*$F71+$M71))/$F71 | T71: =P71/P$3 | U71: =Q71/Q$3 | V71: =R71/R$3 | W71: =S71/S$3
A72: Собирает на себя | B72: Showpass | C72: Канада | D72: Professional (с местами) | E72: CAD | F72: =INDEX('Курсы'!$B$4:$B$46,MATCH($E72,'Курсы'!$A$4:$A$46,0)) | G72: 0.025 | H72: 1.69 | K72: нет | L72: 0.029 | M72: 0.3 | N72: настраивается | P72: =(MIN(IF($J72="",1E+9,$J72),MAX(IF($I72="",0,$I72),$G72*P$3*$F72+$H72))+IF($K72="да",0,$L72*P$3*$F72+$M72))/$F72 | Q72: =(MIN(IF($J72="",1E+9,$J72),MAX(IF($I72="",0,$I72),$G72*Q$3*$F72+$H72))+IF($K72="да",0,$L72*Q$3*$F72+$M72))/$F72 | R72: =(MIN(IF($J72="",1E+9,$J72),MAX(IF($I72="",0,$I72),$G72*R$3*$F72+$H72))+IF($K72="да",0,$L72*R$3*$F72+$M72))/$F72 | S72: =(MIN(IF($J72="",1E+9,$J72),MAX(IF($I72="",0,$I72),$G72*S$3*$F72+$H72))+IF($K72="да",0,$L72*S$3*$F72+$M72))/$F72 | T72: =P72/P$3 | U72: =Q72/Q$3 | V72: =R72/R$3 | W72: =S72/S$3
A73: Собирает на себя | B73: Ticketleap | C73: США | D73: Standard | E73: USD | F73: =INDEX('Курсы'!$B$4:$B$46,MATCH($E73,'Курсы'!$A$4:$A$46,0)) | G73: 0.02 | H73: 1 | J73: 20 | K73: да | L73: 0 | M73: 0 | N73: настраивается | P73: =(MIN(IF($J73="",1E+9,$J73),MAX(IF($I73="",0,$I73),$G73*P$3*$F73+$H73))+IF($K73="да",0,$L73*P$3*$F73+$M73))/$F73 | Q73: =(MIN(IF($J73="",1E+9,$J73),MAX(IF($I73="",0,$I73),$G73*Q$3*$F73+$H73))+IF($K73="да",0,$L73*Q$3*$F73+$M73))/$F73 | R73: =(MIN(IF($J73="",1E+9,$J73),MAX(IF($I73="",0,$I73),$G73*R$3*$F73+$H73))+IF($K73="да",0,$L73*R$3*$F73+$M73))/$F73 | S73: =(MIN(IF($J73="",1E+9,$J73),MAX(IF($I73="",0,$I73),$G73*S$3*$F73+$H73))+IF($K73="да",0,$L73*S$3*$F73+$M73))/$F73 | T73: =P73/P$3 | U73: =Q73/Q$3 | V73: =R73/R$3 | W73: =S73/S$3
A74: Собирает на себя | B74: Entradium | C74: Испания | D74: Básico | E74: EUR | F74: =INDEX('Курсы'!$B$4:$B$46,MATCH($E74,'Курсы'!$A$4:$A$46,0)) | G74: 0.01 | H74: 0 | K74: да | L74: 0 | M74: 0 | N74: покупатель | O74: +IVA 21 % на сбор; в условиях покупателя ещё 2 % + IVA — один это сбор или два, не ясно | P74: =(MIN(IF($J74="",1E+9,$J74),MAX(IF($I74="",0,$I74),$G74*P$3*$F74+$H74))+IF($K74="да",0,$L74*P$3*$F74+$M74))/$F74 | Q74: =(MIN(IF($J74="",1E+9,$J74),MAX(IF($I74="",0,$I74),$G74*Q$3*$F74+$H74))+IF($K74="да",0,$L74*Q$3*$F74+$M74))/$F74 | R74: =(MIN(IF($J74="",1E+9,$J74),MAX(IF($I74="",0,$I74),$G74*R$3*$F74+$H74))+IF($K74="да",0,$L74*R$3*$F74+$M74))/$F74 | S74: =(MIN(IF($J74="",1E+9,$J74),MAX(IF($I74="",0,$I74),$G74*S$3*$F74+$H74))+IF($K74="да",0,$L74*S$3*$F74+$M74))/$F74 | T74: =P74/P$3 | U74: =Q74/Q$3 | V74: =R74/R$3 | W74: =S74/S$3
A75: Собирает на себя | B75: Vivetix | C75: Испания | D75: Tarifa base | E75: EUR | F75: =INDEX('Курсы'!$B$4:$B$46,MATCH($E75,'Курсы'!$A$4:$A$46,0)) | G75: 0.01 | H75: 0.1 | K75: да | L75: 0 | M75: 0 | N75: настраивается | O75: +IVA; ранняя выплата +10 % | P75: =(MIN(IF($J75="",1E+9,$J75),MAX(IF($I75="",0,$I75),$G75*P$3*$F75+$H75))+IF($K75="да",0,$L75*P$3*$F75+$M75))/$F75 | Q75: =(MIN(IF($J75="",1E+9,$J75),MAX(IF($I75="",0,$I75),$G75*Q$3*$F75+$H75))+IF($K75="да",0,$L75*Q$3*$F75+$M75))/$F75 | R75: =(MIN(IF($J75="",1E+9,$J75),MAX(IF($I75="",0,$I75),$G75*R$3*$F75+$H75))+IF($K75="да",0,$L75*R$3*$F75+$M75))/$F75 | S75: =(MIN(IF($J75="",1E+9,$J75),MAX(IF($I75="",0,$I75),$G75*S$3*$F75+$H75))+IF($K75="да",0,$L75*S$3*$F75+$M75))/$F75 | T75: =P75/P$3 | U75: =Q75/Q$3 | V75: =R75/R$3 | W75: =S75/S$3
A76: Собирает на себя | B76: Tuk Tuk | C76: Испания | D76: Basic | E76: EUR | F76: =INDEX('Курсы'!$B$4:$B$46,MATCH($E76,'Курсы'!$A$4:$A$46,0)) | G76: 0.08 | H76: 0 | K76: да | L76: 0 | M76: 0 | N76: настраивается | P76: =(MIN(IF($J76="",1E+9,$J76),MAX(IF($I76="",0,$I76),$G76*P$3*$F76+$H76))+IF($K76="да",0,$L76*P$3*$F76+$M76))/$F76 | Q76: =(MIN(IF($J76="",1E+9,$J76),MAX(IF($I76="",0,$I76),$G76*Q$3*$F76+$H76))+IF($K76="да",0,$L76*Q$3*$F76+$M76))/$F76 | R76: =(MIN(IF($J76="",1E+9,$J76),MAX(IF($I76="",0,$I76),$G76*R$3*$F76+$H76))+IF($K76="да",0,$L76*R$3*$F76+$M76))/$F76 | S76: =(MIN(IF($J76="",1E+9,$J76),MAX(IF($I76="",0,$I76),$G76*S$3*$F76+$H76))+IF($K76="да",0,$L76*S$3*$F76+$M76))/$F76 | T76: =P76/P$3 | U76: =Q76/Q$3 | V76: =R76/R$3 | W76: =S76/S$3
A77: Собирает на себя | B77: More.com | C77: Греция / Кипр | D77: Teller | E77: EUR | F77: =INDEX('Курсы'!$B$4:$B$46,MATCH($E77,'Курсы'!$A$4:$A$46,0)) | G77: 0 | H77: 0 | K77: нет | L77: 0.024 | M77: 0.24 | N77: — | O77: 0 % платформы, только банковские ~2,4 % + 0,24 | P77: =(MIN(IF($J77="",1E+9,$J77),MAX(IF($I77="",0,$I77),$G77*P$3*$F77+$H77))+IF($K77="да",0,$L77*P$3*$F77+$M77))/$F77 | Q77: =(MIN(IF($J77="",1E+9,$J77),MAX(IF($I77="",0,$I77),$G77*Q$3*$F77+$H77))+IF($K77="да",0,$L77*Q$3*$F77+$M77))/$F77 | R77: =(MIN(IF($J77="",1E+9,$J77),MAX(IF($I77="",0,$I77),$G77*R$3*$F77+$H77))+IF($K77="да",0,$L77*R$3*$F77+$M77))/$F77 | S77: =(MIN(IF($J77="",1E+9,$J77),MAX(IF($I77="",0,$I77),$G77*S$3*$F77+$H77))+IF($K77="да",0,$L77*S$3*$F77+$M77))/$F77 | T77: =P77/P$3 | U77: =Q77/Q$3 | V77: =R77/R$3 | W77: =S77/S$3
A78: Собирает на себя | B78: GoOut / Ticketportal (PLG) | C78: Чехия | D78: Типичный договор | E78: CZK | F78: =INDEX('Курсы'!$B$4:$B$46,MATCH($E78,'Курсы'!$A$4:$A$46,0)) | G78: 0.08 | H78: 0 | I78: 5 | K78: да | L78: 0 | M78: 0 | N78: организатор + покупатель | O78: +3,5 % с покупателя (мин 10, макс 500 CZK); цифры из прессы [third_party] | P78: =(MIN(IF($J78="",1E+9,$J78),MAX(IF($I78="",0,$I78),$G78*P$3*$F78+$H78))+IF($K78="да",0,$L78*P$3*$F78+$M78))/$F78 | Q78: =(MIN(IF($J78="",1E+9,$J78),MAX(IF($I78="",0,$I78),$G78*Q$3*$F78+$H78))+IF($K78="да",0,$L78*Q$3*$F78+$M78))/$F78 | R78: =(MIN(IF($J78="",1E+9,$J78),MAX(IF($I78="",0,$I78),$G78*R$3*$F78+$H78))+IF($K78="да",0,$L78*R$3*$F78+$M78))/$F78 | S78: =(MIN(IF($J78="",1E+9,$J78),MAX(IF($I78="",0,$I78),$G78*S$3*$F78+$H78))+IF($K78="да",0,$L78*S$3*$F78+$M78))/$F78 | T78: =P78/P$3 | U78: =Q78/Q$3 | V78: =R78/R$3 | W78: =S78/S$3
A79: Собирает на себя | B79: SMSticket | C79: Чехия | D79: Standard | E79: CZK | F79: =INDEX('Курсы'!$B$4:$B$46,MATCH($E79,'Курсы'!$A$4:$A$46,0)) | G79: 0.05 | H79: 0 | I79: 5 | K79: да | L79: 0 | M79: 0 | N79: организатор | O79: +10 CZK с заказа; выплата за 24 ч | P79: =(MIN(IF($J79="",1E+9,$J79),MAX(IF($I79="",0,$I79),$G79*P$3*$F79+$H79))+IF($K79="да",0,$L79*P$3*$F79+$M79))/$F79 | Q79: =(MIN(IF($J79="",1E+9,$J79),MAX(IF($I79="",0,$I79),$G79*Q$3*$F79+$H79))+IF($K79="да",0,$L79*Q$3*$F79+$M79))/$F79 | R79: =(MIN(IF($J79="",1E+9,$J79),MAX(IF($I79="",0,$I79),$G79*R$3*$F79+$H79))+IF($K79="да",0,$L79*R$3*$F79+$M79))/$F79 | S79: =(MIN(IF($J79="",1E+9,$J79),MAX(IF($I79="",0,$I79),$G79*S$3*$F79+$H79))+IF($K79="да",0,$L79*S$3*$F79+$M79))/$F79 | T79: =P79/P$3 | U79: =Q79/Q$3 | V79: =R79/R$3 | W79: =S79/S$3
A80: Собирает на себя | B80: Ticketstream | C80: Чехия | D80: По умолчанию | E80: CZK | F80: =INDEX('Курсы'!$B$4:$B$46,MATCH($E80,'Курсы'!$A$4:$A$46,0)) | G80: 0.1 | H80: 0 | K80: нет | L80: 0.015 | M80: 6.5 | N80: настраивается | O80: Условия 2022 г. | P80: =(MIN(IF($J80="",1E+9,$J80),MAX(IF($I80="",0,$I80),$G80*P$3*$F80+$H80))+IF($K80="да",0,$L80*P$3*$F80+$M80))/$F80 | Q80: =(MIN(IF($J80="",1E+9,$J80),MAX(IF($I80="",0,$I80),$G80*Q$3*$F80+$H80))+IF($K80="да",0,$L80*Q$3*$F80+$M80))/$F80 | R80: =(MIN(IF($J80="",1E+9,$J80),MAX(IF($I80="",0,$I80),$G80*R$3*$F80+$H80))+IF($K80="да",0,$L80*R$3*$F80+$M80))/$F80 | S80: =(MIN(IF($J80="",1E+9,$J80),MAX(IF($I80="",0,$I80),$G80*S$3*$F80+$H80))+IF($K80="да",0,$L80*S$3*$F80+$M80))/$F80 | T80: =P80/P$3 | U80: =Q80/Q$3 | V80: =R80/R$3 | W80: =S80/S$3
A81: Собирает на себя | B81: Inviton | C81: Словакия | D81: Standard | E81: EUR | F81: =INDEX('Курсы'!$B$4:$B$46,MATCH($E81,'Курсы'!$A$4:$A$46,0)) | G81: 0.05 | H81: 0 | I81: 0.6 | K81: да | L81: 0 | M81: 0 | N81: организатор | P81: =(MIN(IF($J81="",1E+9,$J81),MAX(IF($I81="",0,$I81),$G81*P$3*$F81+$H81))+IF($K81="да",0,$L81*P$3*$F81+$M81))/$F81 | Q81: =(MIN(IF($J81="",1E+9,$J81),MAX(IF($I81="",0,$I81),$G81*Q$3*$F81+$H81))+IF($K81="да",0,$L81*Q$3*$F81+$M81))/$F81 | R81: =(MIN(IF($J81="",1E+9,$J81),MAX(IF($I81="",0,$I81),$G81*R$3*$F81+$H81))+IF($K81="да",0,$L81*R$3*$F81+$M81))/$F81 | S81: =(MIN(IF($J81="",1E+9,$J81),MAX(IF($I81="",0,$I81),$G81*S$3*$F81+$H81))+IF($K81="да",0,$L81*S$3*$F81+$M81))/$F81 | T81: =P81/P$3 | U81: =Q81/Q$3 | V81: =R81/R$3 | W81: =S81/S$3
A82: Собирает на себя | B82: Going. | C82: Польша | D82: Тариф | E82: PLN | F82: =INDEX('Курсы'!$B$4:$B$46,MATCH($E82,'Курсы'!$A$4:$A$46,0)) | G82: 0.1 | H82: 0 | K82: нет | L82: 0.015 | M82: 1 | N82: покупатель + организатор | P82: =(MIN(IF($J82="",1E+9,$J82),MAX(IF($I82="",0,$I82),$G82*P$3*$F82+$H82))+IF($K82="да",0,$L82*P$3*$F82+$M82))/$F82 | Q82: =(MIN(IF($J82="",1E+9,$J82),MAX(IF($I82="",0,$I82),$G82*Q$3*$F82+$H82))+IF($K82="да",0,$L82*Q$3*$F82+$M82))/$F82 | R82: =(MIN(IF($J82="",1E+9,$J82),MAX(IF($I82="",0,$I82),$G82*R$3*$F82+$H82))+IF($K82="да",0,$L82*R$3*$F82+$M82))/$F82 | S82: =(MIN(IF($J82="",1E+9,$J82),MAX(IF($I82="",0,$I82),$G82*S$3*$F82+$H82))+IF($K82="да",0,$L82*S$3*$F82+$M82))/$F82 | T82: =P82/P$3 | U82: =Q82/Q$3 | V82: =R82/R$3 | W82: =S82/S$3
A83: Собирает на себя | B83: Bilet.bg | C83: Болгария | D83: Эксклюзив | E83: BGN | F83: =INDEX('Курсы'!$B$4:$B$46,MATCH($E83,'Курсы'!$A$4:$A$46,0)) | G83: 0.06 | H83: 0 | K83: нет | L83: 0.015 | M83: 0.49 | N83: организатор | P83: =(MIN(IF($J83="",1E+9,$J83),MAX(IF($I83="",0,$I83),$G83*P$3*$F83+$H83))+IF($K83="да",0,$L83*P$3*$F83+$M83))/$F83 | Q83: =(MIN(IF($J83="",1E+9,$J83),MAX(IF($I83="",0,$I83),$G83*Q$3*$F83+$H83))+IF($K83="да",0,$L83*Q$3*$F83+$M83))/$F83 | R83: =(MIN(IF($J83="",1E+9,$J83),MAX(IF($I83="",0,$I83),$G83*R$3*$F83+$H83))+IF($K83="да",0,$L83*R$3*$F83+$M83))/$F83 | S83: =(MIN(IF($J83="",1E+9,$J83),MAX(IF($I83="",0,$I83),$G83*S$3*$F83+$H83))+IF($K83="да",0,$L83*S$3*$F83+$M83))/$F83 | T83: =P83/P$3 | U83: =Q83/Q$3 | V83: =R83/R$3 | W83: =S83/S$3
A84: Собирает на себя | B84: Entrio | C84: Хорватия | D84: Стандарт | E84: EUR | F84: =INDEX('Курсы'!$B$4:$B$46,MATCH($E84,'Курсы'!$A$4:$A$46,0)) | G84: 0.085 | H84: 0 | K84: нет | L84: 0.015 | M84: 0.25 | N84: покупатель | O84: +НДС [snippet] | P84: =(MIN(IF($J84="",1E+9,$J84),MAX(IF($I84="",0,$I84),$G84*P$3*$F84+$H84))+IF($K84="да",0,$L84*P$3*$F84+$M84))/$F84 | Q84: =(MIN(IF($J84="",1E+9,$J84),MAX(IF($I84="",0,$I84),$G84*Q$3*$F84+$H84))+IF($K84="да",0,$L84*Q$3*$F84+$M84))/$F84 | R84: =(MIN(IF($J84="",1E+9,$J84),MAX(IF($I84="",0,$I84),$G84*R$3*$F84+$H84))+IF($K84="да",0,$L84*R$3*$F84+$M84))/$F84 | S84: =(MIN(IF($J84="",1E+9,$J84),MAX(IF($I84="",0,$I84),$G84*S$3*$F84+$H84))+IF($K84="да",0,$L84*S$3*$F84+$M84))/$F84 | T84: =P84/P$3 | U84: =Q84/Q$3 | V84: =R84/R$3 | W84: =S84/S$3
A85: Собирает на себя | B85: Adriaticket | C85: Хорватия | D85: Standard | E85: EUR | F85: =INDEX('Курсы'!$B$4:$B$46,MATCH($E85,'Курсы'!$A$4:$A$46,0)) | G85: 0.039 | H85: 0 | K85: да | L85: 0 | M85: 0 | N85: организатор | P85: =(MIN(IF($J85="",1E+9,$J85),MAX(IF($I85="",0,$I85),$G85*P$3*$F85+$H85))+IF($K85="да",0,$L85*P$3*$F85+$M85))/$F85 | Q85: =(MIN(IF($J85="",1E+9,$J85),MAX(IF($I85="",0,$I85),$G85*Q$3*$F85+$H85))+IF($K85="да",0,$L85*Q$3*$F85+$M85))/$F85 | R85: =(MIN(IF($J85="",1E+9,$J85),MAX(IF($I85="",0,$I85),$G85*R$3*$F85+$H85))+IF($K85="да",0,$L85*R$3*$F85+$M85))/$F85 | S85: =(MIN(IF($J85="",1E+9,$J85),MAX(IF($I85="",0,$I85),$G85*S$3*$F85+$H85))+IF($K85="да",0,$L85*S$3*$F85+$M85))/$F85 | T85: =P85/P$3 | U85: =Q85/Q$3 | V85: =R85/R$3 | W85: =S85/S$3
A86: Собирает на себя | B86: Типичный оператор Украины | C86: Украина | D86: Агент + сервисный сбор | E86: UAH | F86: =INDEX('Курсы'!$B$4:$B$46,MATCH($E86,'Курсы'!$A$4:$A$46,0)) | G86: 0.14 | H86: 0 | K86: да | L86: 0 | M86: 0 | N86: организатор 6–8 % + покупатель 5–9 % | O86: Оценка основателя Concert.ua, Delo.ua 05.10.2026 [third_party] | P86: =(MIN(IF($J86="",1E+9,$J86),MAX(IF($I86="",0,$I86),$G86*P$3*$F86+$H86))+IF($K86="да",0,$L86*P$3*$F86+$M86))/$F86 | Q86: =(MIN(IF($J86="",1E+9,$J86),MAX(IF($I86="",0,$I86),$G86*Q$3*$F86+$H86))+IF($K86="да",0,$L86*Q$3*$F86+$M86))/$F86 | R86: =(MIN(IF($J86="",1E+9,$J86),MAX(IF($I86="",0,$I86),$G86*R$3*$F86+$H86))+IF($K86="да",0,$L86*R$3*$F86+$M86))/$F86 | S86: =(MIN(IF($J86="",1E+9,$J86),MAX(IF($I86="",0,$I86),$G86*S$3*$F86+$H86))+IF($K86="да",0,$L86*S$3*$F86+$M86))/$F86 | T86: =P86/P$3 | U86: =Q86/Q$3 | V86: =R86/R$3 | W86: =S86/S$3
A87: Собирает на себя | B87: Sympla | C87: Бразилия | D87: Paid events | E87: BRL | F87: =INDEX('Курсы'!$B$4:$B$46,MATCH($E87,'Курсы'!$A$4:$A$46,0)) | G87: 0.1 | H87: 0 | I87: 3.99 | K87: нет | L87: 0.025 | M87: 0 | N87: настраивается | O87: Кто платит 2–2,5 % обработки — противоречиво | P87: =(MIN(IF($J87="",1E+9,$J87),MAX(IF($I87="",0,$I87),$G87*P$3*$F87+$H87))+IF($K87="да",0,$L87*P$3*$F87+$M87))/$F87 | Q87: =(MIN(IF($J87="",1E+9,$J87),MAX(IF($I87="",0,$I87),$G87*Q$3*$F87+$H87))+IF($K87="да",0,$L87*Q$3*$F87+$M87))/$F87 | R87: =(MIN(IF($J87="",1E+9,$J87),MAX(IF($I87="",0,$I87),$G87*R$3*$F87+$H87))+IF($K87="да",0,$L87*R$3*$F87+$M87))/$F87 | S87: =(MIN(IF($J87="",1E+9,$J87),MAX(IF($I87="",0,$I87),$G87*S$3*$F87+$H87))+IF($K87="да",0,$L87*S$3*$F87+$M87))/$F87 | T87: =P87/P$3 | U87: =Q87/Q$3 | V87: =R87/R$3 | W87: =S87/S$3
A88: Собирает на себя | B88: Boletia | C88: Мексика | D88: Online | E88: MXN | F88: =INDEX('Курсы'!$B$4:$B$46,MATCH($E88,'Курсы'!$A$4:$A$46,0)) | G88: 0.1 | H88: 10 | K88: да | L88: 0 | M88: 0 | N88: настраивается | O88: Рассрочка 7,5–24 % на организаторе | P88: =(MIN(IF($J88="",1E+9,$J88),MAX(IF($I88="",0,$I88),$G88*P$3*$F88+$H88))+IF($K88="да",0,$L88*P$3*$F88+$M88))/$F88 | Q88: =(MIN(IF($J88="",1E+9,$J88),MAX(IF($I88="",0,$I88),$G88*Q$3*$F88+$H88))+IF($K88="да",0,$L88*Q$3*$F88+$M88))/$F88 | R88: =(MIN(IF($J88="",1E+9,$J88),MAX(IF($I88="",0,$I88),$G88*R$3*$F88+$H88))+IF($K88="да",0,$L88*R$3*$F88+$M88))/$F88 | S88: =(MIN(IF($J88="",1E+9,$J88),MAX(IF($I88="",0,$I88),$G88*S$3*$F88+$H88))+IF($K88="да",0,$L88*S$3*$F88+$M88))/$F88 | T88: =P88/P$3 | U88: =Q88/Q$3 | V88: =R88/R$3 | W88: =S88/S$3
A89: Собирает на себя | B89: Welcu | C89: Чили | D89: Standard | E89: CLP | F89: =INDEX('Курсы'!$B$4:$B$46,MATCH($E89,'Курсы'!$A$4:$A$46,0)) | G89: 0.1 | H89: 0 | K89: да | L89: 0 | M89: 0 | N89: организатор | P89: =(MIN(IF($J89="",1E+9,$J89),MAX(IF($I89="",0,$I89),$G89*P$3*$F89+$H89))+IF($K89="да",0,$L89*P$3*$F89+$M89))/$F89 | Q89: =(MIN(IF($J89="",1E+9,$J89),MAX(IF($I89="",0,$I89),$G89*Q$3*$F89+$H89))+IF($K89="да",0,$L89*Q$3*$F89+$M89))/$F89 | R89: =(MIN(IF($J89="",1E+9,$J89),MAX(IF($I89="",0,$I89),$G89*R$3*$F89+$H89))+IF($K89="да",0,$L89*R$3*$F89+$M89))/$F89 | S89: =(MIN(IF($J89="",1E+9,$J89),MAX(IF($I89="",0,$I89),$G89*S$3*$F89+$H89))+IF($K89="да",0,$L89*S$3*$F89+$M89))/$F89 | T89: =P89/P$3 | U89: =Q89/Q$3 | V89: =R89/R$3 | W89: =S89/S$3
A90: Собирает на себя | B90: Passline | C90: Латинская Америка | D90: Producer agreement | E90: CLP | F90: =INDEX('Курсы'!$B$4:$B$46,MATCH($E90,'Курсы'!$A$4:$A$46,0)) | G90: 0.15 | H90: 0 | K90: да | L90: 0 | M90: 0 | N90: покупатель | P90: =(MIN(IF($J90="",1E+9,$J90),MAX(IF($I90="",0,$I90),$G90*P$3*$F90+$H90))+IF($K90="да",0,$L90*P$3*$F90+$M90))/$F90 | Q90: =(MIN(IF($J90="",1E+9,$J90),MAX(IF($I90="",0,$I90),$G90*Q$3*$F90+$H90))+IF($K90="да",0,$L90*Q$3*$F90+$M90))/$F90 | R90: =(MIN(IF($J90="",1E+9,$J90),MAX(IF($I90="",0,$I90),$G90*R$3*$F90+$H90))+IF($K90="да",0,$L90*R$3*$F90+$M90))/$F90 | S90: =(MIN(IF($J90="",1E+9,$J90),MAX(IF($I90="",0,$I90),$G90*S$3*$F90+$H90))+IF($K90="да",0,$L90*S$3*$F90+$M90))/$F90 | T90: =P90/P$3 | U90: =Q90/Q$3 | V90: =R90/R$3 | W90: =S90/S$3
A91: Собирает на себя | B91: Alpogo | C91: Аргентина | D91: Producer terms | E91: ARS | F91: =INDEX('Курсы'!$B$4:$B$46,MATCH($E91,'Курсы'!$A$4:$A$46,0)) | G91: 0.175 | H91: 0 | K91: да | L91: 0 | M91: 0 | N91: организатор | O91: Может держать 30 % 90 дней | P91: =(MIN(IF($J91="",1E+9,$J91),MAX(IF($I91="",0,$I91),$G91*P$3*$F91+$H91))+IF($K91="да",0,$L91*P$3*$F91+$M91))/$F91 | Q91: =(MIN(IF($J91="",1E+9,$J91),MAX(IF($I91="",0,$I91),$G91*Q$3*$F91+$H91))+IF($K91="да",0,$L91*Q$3*$F91+$M91))/$F91 | R91: =(MIN(IF($J91="",1E+9,$J91),MAX(IF($I91="",0,$I91),$G91*R$3*$F91+$H91))+IF($K91="да",0,$L91*R$3*$F91+$M91))/$F91 | S91: =(MIN(IF($J91="",1E+9,$J91),MAX(IF($I91="",0,$I91),$G91*S$3*$F91+$H91))+IF($K91="да",0,$L91*S$3*$F91+$M91))/$F91 | T91: =P91/P$3 | U91: =Q91/Q$3 | V91: =R91/R$3 | W91: =S91/S$3
A92: Собирает на себя | B92: Peatix | C92: Европа | D92: Ticketing fee | E92: EUR | F92: =INDEX('Курсы'!$B$4:$B$46,MATCH($E92,'Курсы'!$A$4:$A$46,0)) | G92: 0.049 | H92: 0.99 | K92: да | L92: 0 | M92: 0 | N92: организатор | P92: =(MIN(IF($J92="",1E+9,$J92),MAX(IF($I92="",0,$I92),$G92*P$3*$F92+$H92))+IF($K92="да",0,$L92*P$3*$F92+$M92))/$F92 | Q92: =(MIN(IF($J92="",1E+9,$J92),MAX(IF($I92="",0,$I92),$G92*Q$3*$F92+$H92))+IF($K92="да",0,$L92*Q$3*$F92+$M92))/$F92 | R92: =(MIN(IF($J92="",1E+9,$J92),MAX(IF($I92="",0,$I92),$G92*R$3*$F92+$H92))+IF($K92="да",0,$L92*R$3*$F92+$M92))/$F92 | S92: =(MIN(IF($J92="",1E+9,$J92),MAX(IF($I92="",0,$I92),$G92*S$3*$F92+$H92))+IF($K92="да",0,$L92*S$3*$F92+$M92))/$F92 | T92: =P92/P$3 | U92: =Q92/Q$3 | V92: =R92/R$3 | W92: =S92/S$3
A93: Собирает на себя | B93: Peatix | C93: Япония | D93: Ticketing fee | E93: JPY | F93: =INDEX('Курсы'!$B$4:$B$46,MATCH($E93,'Курсы'!$A$4:$A$46,0)) | G93: 0.049 | H93: 99 | K93: да | L93: 0 | M93: 0 | N93: организатор | P93: =(MIN(IF($J93="",1E+9,$J93),MAX(IF($I93="",0,$I93),$G93*P$3*$F93+$H93))+IF($K93="да",0,$L93*P$3*$F93+$M93))/$F93 | Q93: =(MIN(IF($J93="",1E+9,$J93),MAX(IF($I93="",0,$I93),$G93*Q$3*$F93+$H93))+IF($K93="да",0,$L93*Q$3*$F93+$M93))/$F93 | R93: =(MIN(IF($J93="",1E+9,$J93),MAX(IF($I93="",0,$I93),$G93*R$3*$F93+$H93))+IF($K93="да",0,$L93*R$3*$F93+$M93))/$F93 | S93: =(MIN(IF($J93="",1E+9,$J93),MAX(IF($I93="",0,$I93),$G93*S$3*$F93+$H93))+IF($K93="да",0,$L93*S$3*$F93+$M93))/$F93 | T93: =P93/P$3 | U93: =Q93/Q$3 | V93: =R93/R$3 | W93: =S93/S$3
A94: Собирает на себя | B94: TryBooking | C94: Австралия | D94: Standard | E94: AUD | F94: =INDEX('Курсы'!$B$4:$B$46,MATCH($E94,'Курсы'!$A$4:$A$46,0)) | G94: 0.025 | H94: 0.5 | K94: да | L94: 0 | M94: 0 | N94: настраивается | P94: =(MIN(IF($J94="",1E+9,$J94),MAX(IF($I94="",0,$I94),$G94*P$3*$F94+$H94))+IF($K94="да",0,$L94*P$3*$F94+$M94))/$F94 | Q94: =(MIN(IF($J94="",1E+9,$J94),MAX(IF($I94="",0,$I94),$G94*Q$3*$F94+$H94))+IF($K94="да",0,$L94*Q$3*$F94+$M94))/$F94 | R94: =(MIN(IF($J94="",1E+9,$J94),MAX(IF($I94="",0,$I94),$G94*R$3*$F94+$H94))+IF($K94="да",0,$L94*R$3*$F94+$M94))/$F94 | S94: =(MIN(IF($J94="",1E+9,$J94),MAX(IF($I94="",0,$I94),$G94*S$3*$F94+$H94))+IF($K94="да",0,$L94*S$3*$F94+$M94))/$F94 | T94: =P94/P$3 | U94: =Q94/Q$3 | V94: =R94/R$3 | W94: =S94/S$3
A95: Собирает на себя | B95: teket | C95: Япония | D95: Без мест | E95: JPY | F95: =INDEX('Курсы'!$B$4:$B$46,MATCH($E95,'Курсы'!$A$4:$A$46,0)) | G95: 0.08 | H95: 0 | K95: да | L95: 0 | M95: 0 | N95: организатор | P95: =(MIN(IF($J95="",1E+9,$J95),MAX(IF($I95="",0,$I95),$G95*P$3*$F95+$H95))+IF($K95="да",0,$L95*P$3*$F95+$M95))/$F95 | Q95: =(MIN(IF($J95="",1E+9,$J95),MAX(IF($I95="",0,$I95),$G95*Q$3*$F95+$H95))+IF($K95="да",0,$L95*Q$3*$F95+$M95))/$F95 | R95: =(MIN(IF($J95="",1E+9,$J95),MAX(IF($I95="",0,$I95),$G95*R$3*$F95+$H95))+IF($K95="да",0,$L95*R$3*$F95+$M95))/$F95 | S95: =(MIN(IF($J95="",1E+9,$J95),MAX(IF($I95="",0,$I95),$G95*S$3*$F95+$H95))+IF($K95="да",0,$L95*S$3*$F95+$M95))/$F95 | T95: =P95/P$3 | U95: =Q95/Q$3 | V95: =R95/R$3 | W95: =S95/S$3
A96: Собирает на себя | B96: LivePocket | C96: Япония | D96: Sales fee | E96: JPY | F96: =INDEX('Курсы'!$B$4:$B$46,MATCH($E96,'Курсы'!$A$4:$A$46,0)) | G96: 0.05 | H96: 0 | K96: да | L96: 0 | M96: 0 | N96: настраивается | P96: =(MIN(IF($J96="",1E+9,$J96),MAX(IF($I96="",0,$I96),$G96*P$3*$F96+$H96))+IF($K96="да",0,$L96*P$3*$F96+$M96))/$F96 | Q96: =(MIN(IF($J96="",1E+9,$J96),MAX(IF($I96="",0,$I96),$G96*Q$3*$F96+$H96))+IF($K96="да",0,$L96*Q$3*$F96+$M96))/$F96 | R96: =(MIN(IF($J96="",1E+9,$J96),MAX(IF($I96="",0,$I96),$G96*R$3*$F96+$H96))+IF($K96="да",0,$L96*R$3*$F96+$M96))/$F96 | S96: =(MIN(IF($J96="",1E+9,$J96),MAX(IF($I96="",0,$I96),$G96*S$3*$F96+$H96))+IF($K96="да",0,$L96*S$3*$F96+$M96))/$F96 | T96: =P96/P$3 | U96: =Q96/Q$3 | V96: =R96/R$3 | W96: =S96/S$3
A97: Собирает на себя | B97: Ticket2U | C97: Малайзия | D97: Standard | E97: MYR | F97: =INDEX('Курсы'!$B$4:$B$46,MATCH($E97,'Курсы'!$A$4:$A$46,0)) | G97: 0.05 | H97: 0 | I97: 2 | K97: да | L97: 0 | M97: 0 | N97: настраивается | O97: Прочтение 5 % vs 6 % под вопросом [snippet] | P97: =(MIN(IF($J97="",1E+9,$J97),MAX(IF($I97="",0,$I97),$G97*P$3*$F97+$H97))+IF($K97="да",0,$L97*P$3*$F97+$M97))/$F97 | Q97: =(MIN(IF($J97="",1E+9,$J97),MAX(IF($I97="",0,$I97),$G97*Q$3*$F97+$H97))+IF($K97="да",0,$L97*Q$3*$F97+$M97))/$F97 | R97: =(MIN(IF($J97="",1E+9,$J97),MAX(IF($I97="",0,$I97),$G97*R$3*$F97+$H97))+IF($K97="да",0,$L97*R$3*$F97+$M97))/$F97 | S97: =(MIN(IF($J97="",1E+9,$J97),MAX(IF($I97="",0,$I97),$G97*S$3*$F97+$H97))+IF($K97="да",0,$L97*S$3*$F97+$M97))/$F97 | T97: =P97/P$3 | U97: =Q97/Q$3 | V97: =R97/R$3 | W97: =S97/S$3
A98: Собирает на себя | B98: Accupass | C98: Тайвань | D98: Paid tickets | E98: TWD | F98: =INDEX('Курсы'!$B$4:$B$46,MATCH($E98,'Курсы'!$A$4:$A$46,0)) | G98: 0.05 | H98: 10 | K98: да | L98: 0 | M98: 0 | N98: организатор | P98: =(MIN(IF($J98="",1E+9,$J98),MAX(IF($I98="",0,$I98),$G98*P$3*$F98+$H98))+IF($K98="да",0,$L98*P$3*$F98+$M98))/$F98 | Q98: =(MIN(IF($J98="",1E+9,$J98),MAX(IF($I98="",0,$I98),$G98*Q$3*$F98+$H98))+IF($K98="да",0,$L98*Q$3*$F98+$M98))/$F98 | R98: =(MIN(IF($J98="",1E+9,$J98),MAX(IF($I98="",0,$I98),$G98*R$3*$F98+$H98))+IF($K98="да",0,$L98*R$3*$F98+$M98))/$F98 | S98: =(MIN(IF($J98="",1E+9,$J98),MAX(IF($I98="",0,$I98),$G98*S$3*$F98+$H98))+IF($K98="да",0,$L98*S$3*$F98+$M98))/$F98 | T98: =P98/P$3 | U98: =Q98/Q$3 | V98: =R98/R$3 | W98: =S98/S$3
A99: Собирает на себя | B99: BiletiniYap | C99: Турция | D99: Flat | E99: TRY | F99: =INDEX('Курсы'!$B$4:$B$46,MATCH($E99,'Курсы'!$A$4:$A$46,0)) | G99: 0.08 | H99: 0 | K99: да | L99: 0 | M99: 0 | N99: организатор | P99: =(MIN(IF($J99="",1E+9,$J99),MAX(IF($I99="",0,$I99),$G99*P$3*$F99+$H99))+IF($K99="да",0,$L99*P$3*$F99+$M99))/$F99 | Q99: =(MIN(IF($J99="",1E+9,$J99),MAX(IF($I99="",0,$I99),$G99*Q$3*$F99+$H99))+IF($K99="да",0,$L99*Q$3*$F99+$M99))/$F99 | R99: =(MIN(IF($J99="",1E+9,$J99),MAX(IF($I99="",0,$I99),$G99*R$3*$F99+$H99))+IF($K99="да",0,$L99*R$3*$F99+$M99))/$F99 | S99: =(MIN(IF($J99="",1E+9,$J99),MAX(IF($I99="",0,$I99),$G99*S$3*$F99+$H99))+IF($K99="да",0,$L99*S$3*$F99+$M99))/$F99 | T99: =P99/P$3 | U99: =Q99/Q$3 | V99: =R99/R$3 | W99: =S99/S$3
A100: Собирает на себя | B100: Biletino | C100: Турция | D100: Paid events | E100: TRY | F100: =INDEX('Курсы'!$B$4:$B$46,MATCH($E100,'Курсы'!$A$4:$A$46,0)) | G100: 0.136 | H100: 0 | K100: да | L100: 0 | M100: 0 | N100: организатор | P100: =(MIN(IF($J100="",1E+9,$J100),MAX(IF($I100="",0,$I100),$G100*P$3*$F100+$H100))+IF($K100="да",0,$L100*P$3*$F100+$M100))/$F100 | Q100: =(MIN(IF($J100="",1E+9,$J100),MAX(IF($I100="",0,$I100),$G100*Q$3*$F100+$H100))+IF($K100="да",0,$L100*Q$3*$F100+$M100))/$F100 | R100: =(MIN(IF($J100="",1E+9,$J100),MAX(IF($I100="",0,$I100),$G100*R$3*$F100+$H100))+IF($K100="да",0,$L100*R$3*$F100+$M100))/$F100 | S100: =(MIN(IF($J100="",1E+9,$J100),MAX(IF($I100="",0,$I100),$G100*S$3*$F100+$H100))+IF($K100="да",0,$L100*S$3*$F100+$M100))/$F100 | T100: =P100/P$3 | U100: =Q100/Q$3 | V100: =R100/R$3 | W100: =S100/S$3
...

Sheet Курсы
A1: Курсы валют: единиц валюты за 1 EUR, 09.10.2026
A3: Валюта | B3: За 1 EUR | C3: Источник
A4: EUR | B4: 1 | C4: ECB reference rate 09.10.2026 (api.frankfurter.dev)
A5: AUD | B5: 1.6052 | C5: ECB reference rate 09.10.2026 (api.frankfurter.dev)
A6: BRL | B6: 5.6086 | C6: ECB reference rate 09.10.2026 (api.frankfurter.dev)
A7: CAD | B7: 1.5942 | C7: ECB reference rate 09.10.2026 (api.frankfurter.dev)
A8: CHF | B8: 0.9313 | C8: ECB reference rate 09.10.2026 (api.frankfurter.dev)
A9: CZK | B9: 24.369 | C9: ECB reference rate 09.10.2026 (api.frankfurter.dev)
A10: DKK | B10: 7.4751 | C10: ECB reference rate 09.10.2026 (api.frankfurter.dev)
A11: GBP | B11: 0.84763 | C11: ECB reference rate 09.10.2026 (api.frankfurter.dev)
A12: HKD | B12: 8.794 | C12: ECB reference rate 09.10.2026 (api.frankfurter.dev)
A13: HUF | B13: 365.08 | C13: ECB reference rate 09.10.2026 (api.frankfurter.dev)
A14: IDR | B14: 20036.94 | C14: ECB reference rate 09.10.2026 (api.frankfurter.dev)
A15: ILS | B15: 3.426 | C15: ECB reference rate 09.10.2026 (api.frankfurter.dev)
... A46: TWD | B46: 35.782058 | C46: open.er-api.com, обновлено 09.10.2026 00:02 UTC (ECB эту валюту не публикует)

Sheet Direct merchant
A1: Регион | B1: Платформа | C1: Сайт | D1: Рынок | E1: Валюта | F1: Движение денег | G1: Как берёт деньги / выплаты | H1: Модель | I1: Тарифы и сбор за билет | J1: Предоплата | K1: Эквайринг | L1: Кто платит | M1: Бесплатные билеты | N1: Рассадка | O1: Выплаты | P1: Возвраты и чарджбэки | Q1: НДС | R1: Мелкий шрифт (звёздочки) | S1: Доп. услуги | T1: Enterprise / по запросу | U1: Сегмент | V1: Уверенность | W1: Источники
A2: Глобальные self-serve | B2: Ticket Tailor | C2: https://www.tickettailor.com | D2: UK | E2: GBP | F2: direct merchant | G2: Direct merchant: buyer pays straight into the organizer's own Stripe/PayPal/Square account (revenue appears almost immediately, bank transfer takes about a week); TT never holds the money. TT fee collection: Pre-pay = card charged immediately when credits are bought (optional auto top-up monthly or when <=25 credits left). PAYG on Stripe = fee deducted automatically at the point of sale; PAYG on PayPal/Square/offline = TT charges the organizer's card on file monthly, or every 50 usage units, or 2 days after the last event ends. | H2: flat_per_ticket | I2: • Free (free tickets): +0.0 — Up to 5,000 free tickets/year, no fee — First 5 paid sales also free • Pay as you go (PAYG): +0.6 — All features, flat fee per usage, no subscription — Stripe: deducted at sale; PayPal/Square: billed to card • Pre-pay credits: — Same features; lower unit price when credits are bought in advance — See prepaid bundles; credits never expire; running out falls back to PAYG automatically; minimum bundle 100 credits | J2: • 500 credits: 0.41 (срок: none; возврат: None) • largest bundles: 0.22 (срок: none; возврат: None) | K2: включён: False; свой процессинг: True; Stripe, PayPal, Square; Stripe UK 1.5% + GBP 0.20 (example) | L2: configurable (organizer adds own booking/transaction fee; default is organizer absorbs) | M2: Free tickets are free up to 5,000/year; first 5 paid tickets free. | N2: Seat reservation costs 1 extra usage per seated ticket: PAYG +GBP 0.60 (a paid seated ticket = GBP 1.20); pre-pay: +1 credit. A free seated ticket still costs 1 usage. Charity discount applies; marking seats not-for-sale is free. | O2: Immediate into organizer's Stripe/PayPal/Square; no payout by TT. | P2: No refund of TT fee/credit on refund or cancel; processor fees usually not returned either. No TT chargeback fee found on pages read. | Q2: TT fees shown excl. VAT; VAT/sales tax added where applicable | R2: • Charged per 'usage', not on ticket price: paid ticket = 1 usage; seated paid ticket = 2; free ticket = 0; free seated ticket = 1; product sale = 1; ticket issued via API (even free) = 1; imported ticket (even free) = 1; every ticket in a paid bundle = 1; a voucher-covered order is still charged. • First 5 ticket sales are free; the standard rate starts from the sixth paid ticket (pricing page FAQ). • Free tickets free within fair usage: the pricing page says 5,000 free tickets/year but its FAQ also mentions 'more than 2,000' in another answer; above fair usage TT gives a per-free-ticket quote via support. • Fees are not refunded when a ticket is refunded or cancelled (credits/PAYG fee kept); order transfer is free. • Discounts (apply via billing page, at TT's discretion): 50% for registered charities (forever), 20% for B Corps/PTAs/CICs/non-profits/BBN, half-usage for tickets under 5 incl. booking fees (a seated 5 ticket = 1.5 usage), 50% for Music Venue Trust members, 50% for Round Tables, 6 months free for Art Tickets users. Only one discount at a time; none applies to white-label/custom-domain prices or processor fees. • Refund protection: buyers can add it for 8% of ticket price; organizer keeps 10% of that fee, rest goes to TT (collected via PAYG). • SMS/WhatsApp reminders: TT charges 0.10 per event per order (GBP/USD) for buyers who opt in; organizer keeps any excess of the suggested fee. • TT does not touch the payment: Stripe, PayPal, Square or offline needed; TT fees are on top of processor fees; credits do not cover processing. • VAT and sales tax charged on TT fees where applicable; TT prices are shown excl. VAT. • No subscription, no contract; credits never expire; credits can be transferred between the organizer's box offices. • Pass-on of fees is manual: organizer adds a booking fee (per ticket) and/or transaction fee (per order, % and/or fixed); no automatic 'pass all fees' toggle. TT warns US sellers about the FTC junk-fees rule. • GBP bundle table: only the 500-credit (GBP 0.41) and 'from GBP 0.22' figures were readable. | S2: • {"name": "White label (logo removal + custom domain)", "price": "GBP 39/month; custom domain alone GBP 7/month"} • {"name": "HubSpot/ActiveCampaign/Constant Contact integrations", "price": "monthly fee shown in account (amount not public)"} • {"name": "Free check-in app", "price": "free"} | T2: Very large free events / above fair usage: ask support for a quote; 'Book a demo' for larger organizers (no public enterprise price) | U2: self-serve, small/mid organizers (shows, workshops, venues, charities); flat fee per ticket, bring-your-own processor | V2: page | W2: https://www.tickettailor.com/pricing (pricing page + FAQ) https://help.tickettailor.com/en/articles/6731528-how-much-does-ticket-tailor-cost-and-how-will-i-be-charged (help centre: how much does TT cost) https://help.tickettailor.com/en/articles/4096561-what-are-the-fees-for-using-seating-charts (help centre: seating chart fees) https://help.tickettailor.com/en/articles/4725866-how-do-pre-pay-ticket-credits-work (help centre: pre-pay credits) https://help.tickettailor.com/en/articles/8687492-what-discounts-do-we-offer (help centre: discounts) https://help.tickettailor.com/en/articles/5210356-how-to-pass-fees-onto-your-ticket-buyers (help centre: passing fees on)
A3: Глобальные self-serve | B3: Ticket Tailor | C3: https://www.tickettailor.com | D3: US | E3: USD | F3: direct merchant | G3: Direct merchant: buyer pays straight into the organizer's own Stripe/PayPal/Square account (revenue appears almost immediately, bank transfer takes about a week); TT never holds the money. TT fee collection: Pre-pay = card charged immediately when credits are bought (optional auto top-up monthly or when <=25 credits left). PAYG on Stripe = fee deducted automatically at the point of sale; PAYG on PayPal/Square/offline = TT charges the organizer's card on file monthly, or every 50 usage units, or 2 days after the last event ends. | H3: flat_per_ticket | I3: • Free (free tickets): +0.0 — Up to 5,000 free tickets/year, no fee — First 5 paid sales also free • Pay as you go (PAYG): +0.85 — All features, flat fee per usage, no subscription — Stripe: deducted at sale; PayPal/Square: billed to card • Pre-pay credits: — Same features; lower unit price when credits are bought in advance — See prepaid bundles; credits never expire; running out falls back to PAYG automatically; minimum bundle 100 credits | J3: • 100 credits: 0.7 (срок: none; возврат: None) • 500 credits: 0.6 (срок: none; возврат: None) • 1,000 credits: 0.52 (срок: none; возврат: None) • 5,000 credits: 0.43 (срок: none; возврат: None) • 10,000 credits: 0.39 (срок: none; возврат: None) • 20,000+ credits: 0.34 (срок: none; возврат: None) | K3: включён: False; свой процессинг: True; Stripe, PayPal, Square; Stripe US 2.9% + $0.30 (example) | L3: configurable (organizer adds own booking/transaction fee; default is organizer absorbs) | M3: Free tickets are free up to 5,000/year; first 5 paid tickets free. | N3: Seat reservation: PAYG +$0.85 per seated ticket (paid seated ticket = $1.70); pre-pay: +1 credit. | O3: Immediate into organizer's Stripe/PayPal/Square; no payout by TT. | P3: No refund of TT fee/credit on refund or cancel; processor fees usually not returned either. No TT chargeback fee found on pages read. | Q3: TT fees shown excl. VAT; VAT/sales tax added where applicable | R3: • Charged per 'usage', not on ticket price: paid ticket = 1 usage; seated paid ticket = 2; free ticket = 0; free seated ticket = 1; product sale = 1; ticket issued via API (even free) = 1; imported ticket (even free) = 1; every ticket in a paid bundle = 1; a voucher-covered order is still charged. • First 5 ticket sales are free; the standard rate starts from the sixth paid ticket (pricing page FAQ). • Free tickets free within fair usage: the pricing page says 5,000 free tickets/year but its FAQ also mentions 'more than 2,000' in another answer; above fair usage TT gives a per-free-ticket quote via support. • Fees are not refunded when a ticket is refunded or cancelled (credits/PAYG fee kept); order transfer is free. • Discounts (apply via billing page, at TT's discretion): 50% for registered charities (forever), 20% for B Corps/PTAs/CICs/non-profits/BBN, half-usage for tickets under 5 incl. booking fees (a seated 5 ticket = 1.5 usage), 50% for Music Venue Trust members, 50% for Round Tables, 6 months free for Art Tickets users. Only one discount at a time; none applies to white-label/custom-domain prices or processor fees. • Refund protection: buyers can add it for 8% of ticket price; organizer keeps 10% of that fee, rest goes to TT (collected via PAYG). • SMS/WhatsApp reminders: TT charges 0.10 per event per order (GBP/USD) for buyers who opt in; organizer keeps any excess of the suggested fee. • TT does not touch the payment: Stripe, PayPal, Square or offline needed; TT fees are on top of processor fees; credits do not cover processing. • VAT and sales tax charged on TT fees where applicable; TT prices are shown excl. VAT. • No subscription, no contract; credits never expire; credits can be transferred between the organizer's box offices. • Pass-on of fees is manual: organizer adds a booking fee (per ticket) and/or transaction fee (per order, % and/or fixed); no automatic 'pass all fees' toggle. TT warns US sellers about the FTC junk-fees rule. • US credit tiers come from a competitor's (TixFox) reading of TT's USD calculator on 2026-10-08, not from a statically rendered TT page; TT's own headline says credits start 'from $0.30'. | S3: • {"name": "White label (logo removal + custom domain)", "price": "$49/month; custom domain alone $8/month"} • {"name": "HubSpot/ActiveCampaign/Constant Contact integrations", "price": "monthly fee shown in account (amount not public)"} • {"name": "Free check-in app", "price": "free"} | T3: Very large free events / above fair usage: ask support for a quote; 'Book a demo' for larger organizers (no public enterprise price) | U3: self-serve, small/mid organizers (shows, workshops, venues, charities); flat fee per ticket, bring-your-own processor | V3: third_party | W3: https://www.tickettailor.com/pricing (pricing page + FAQ) https://help.tickettailor.com/en/articles/6731528-how-much-does-ticket-tailor-cost-and-how-will-i-be-charged (help centre: how much does TT cost) https://help.tickettailor.com/en/articles/4096561-what-are-the-fees-for-using-seating-charts (help centre: seating chart fees) https://help.tickettailor.com/en/articles/4725866-how-do-pre-pay-ticket-credits-work (help centre: pre-pay credits) https://help.tickettailor.com/en/articles/8687492-what-discounts-do-we-offer (help centre: discounts) https://help.tickettailor.com/en/articles/5210356-how-to-pass-fees-onto-your-ticket-buyers (help centre: passing fees on) https://tixfox.co/blog/ticket-tailor-fees (third-party (TixFox) read of US credit tiers)
A4: Глобальные self-serve | B4: Ticket Tailor | C4: https://www.tickettailor.com | D4: Eurozone | E4: EUR | F4: direct merchant | G4: Direct merchant: buyer pays straight into the organizer's own Stripe/PayPal/Square account (revenue appears almost immediately, bank transfer takes about a week); TT never holds the money. TT fee collection: Pre-pay = card charged immediately when credits are bought (optional auto top-up monthly or when <=25 credits left). PAYG on Stripe = fee deducted automatically at the point of sale; PAYG on PayPal/Square/offline = TT charges the organizer's card on file monthly, or every 50 usage units, or 2 days after the last event ends. | H4: flat_per_ticket | I4: • Free (free tickets): +0.0 — Up to 5,000 free tickets/year, no fee — First 5 paid sales also free • Pay as you go (PAYG): +0.7 — All features, flat fee per usage, no subscription — Stripe: deducted at sale; PayPal/Square: billed to card • Pre-pay credits: — Same features; lower unit price when credits are bought in advance — See prepaid bundles; credits never expire; running out falls back to PAYG automatically; minimum bundle 100 credits | J4: • credit bundles: 0.3 (срок: none; возврат: None) | K4: включён: False; свой процессинг: True; Stripe, PayPal, Square; Stripe Eurozone 1.5% + EUR 0.25 (example) | L4: configurable (organizer adds own booking/transaction fee; default is organizer absorbs) | M4: Free tickets are free up to 5,000/year; first 5 paid tickets free. | N4: Seat reservation: PAYG +EUR 0.70 per seated ticket; pre-pay: +1 credit. | O4: Immediate into organizer's Stripe/PayPal/Square; no payout by TT. | P4: No refund of TT fee/credit on refund or cancel; processor fees usually not returned either. No TT chargeback fee found on pages read. | Q4: TT fees shown excl. VAT; VAT/sales tax added where applicable | R4: • Charged per 'usage', not on ticket price: paid ticket = 1 usage; seated paid ticket = 2; free ticket = 0; free seated ticket = 1; product sale = 1; ticket issued via API (even free) = 1; imported ticket (even free) = 1; every ticket in a paid bundle = 1; a voucher-covered order is still charged. • First 5 ticket sales are free; the standard rate starts from the sixth paid ticket (pricing page FAQ). • Free tickets free within fair usage: the pricing page says 5,000 free tickets/year but its FAQ also mentions 'more than 2,000' in another answer; above fair usage TT gives a per-free-ticket quote via support. • Fees are not refunded when a ticket is refunded or cancelled (credits/PAYG fee kept); order transfer is free. • Discounts (apply via billing page, at TT's discretion): 50% for registered charities (forever), 20% for B Corps/PTAs/CICs/non-profits/BBN, half-usage for tickets under 5 incl. booking fees (a seated 5 ticket = 1.5 usage), 50% for Music Venue Trust members, 50% for Round Tables, 6 months free for Art Tickets users. Only one discount at a time; none applies to white-label/custom-domain prices or processor fees. • Refund protection: buyers can add it for 8% of ticket price; organizer keeps 10% of that fee, rest goes to TT (collected via PAYG). • SMS/WhatsApp reminders: TT charges 0.10 per event per order (GBP/USD) for buyers who opt in; organizer keeps any excess of the suggested fee. • TT does not touch the payment: Stripe, PayPal, Square or offline needed; TT fees are on top of processor fees; credits do not cover processing. • VAT and sales tax charged on TT fees where applicable; TT prices are shown excl. VAT. • No subscription, no contract; credits never expire; credits can be transferred between the organizer's box offices. • Pass-on of fees is manual: organizer adds a booking fee (per ticket) and/or transaction fee (per order, % and/or fixed); no automatic 'pass all fees' toggle. TT warns US sellers about the FTC junk-fees rule. | S4: • {"name": "White label (logo removal + custom domain)", "price": "EUR 45/month; custom domain alone EUR 8/month"} • {"name": "HubSpot/ActiveCampaign/Constant Contact integrations", "price": "monthly fee shown in account (amount not public)"} • {"name": "Free check-in app", "price": "free"} | T4: Very large free events / above fair usage: ask support for a quote; 'Book a demo' for larger organizers (no public enterprise price) | U4: self-serve, small/mid organizers (shows, workshops, venues, charities); flat fee per ticket, bring-your-own processor | V4: page | W4: https://www.tickettailor.com/pricing (pricing page + FAQ) https://help.tickettailor.com/en/articles/6731528-how-much-does-ticket-tailor-cost-and-how-will-i-be-charged (help centre: how much does TT cost) https://help.tickettailor.com/en/articles/4096561-what-are-the-fees-for-using-seating-charts (help centre: seating chart fees) https://help.tickettailor.com/en/articles/4725866-how-do-pre-pay-ticket-credits-work (help centre: pre-pay credits) https://help.tickettailor.com/en/articles/8687492-what-discounts-do-we-offer (help centre: discounts) https://help.tickettailor.com/en/articles/5210356-how-to-pass-fees-onto-your-ticket-buyers (help centre: passing fees on)
A5: Глобальные self-serve | B5: Ticket Tailor | C5: https://www.tickettailor.com | D5: Australia | E5: AUD | F5: direct merchant | G5: Direct merchant: buyer pays straight into the organizer's own Stripe/PayPal/Square account (revenue appears almost immediately, bank transfer takes about a week); TT never holds the money. TT fee collection: Pre-pay = card charged immediately when credits are bought (optional auto top-up monthly or when <=25 credits left). PAYG on Stripe = fee deducted automatically at the point of sale; PAYG on PayPal/Square/offline = TT charges the organizer's card on file monthly, or every 50 usage units, or 2 days after the last event ends. | H5: flat_per_ticket | I5: • Free (free tickets): +0.0 — Up to 5,000 free tickets/year, no fee — First 5 paid sales also free • Pay as you go (PAYG): +1.1 — All features, flat fee per usage, no subscription — Stripe: deducted at sale; PayPal/Square: billed to card • Pre-pay credits: — Same features; lower unit price when credits are bought in advance — See prepaid bundles; credits never expire; running out falls back to PAYG automatically; minimum bundle 100 credits | J5: • credit bundles: None (срок: none; возврат: None) | K5: включён: False; свой процессинг: True; Stripe, PayPal, Square; Stripe AU 1.75% + A$0.30 (example) | L5: configurable (organizer adds own booking/transaction fee; default is organizer absorbs) | M5: Free tickets are free up to 5,000/year; first 5 paid tickets free. | N5: Seat reservation: PAYG +A$1.10 per seated ticket; pre-pay: +1 credit. | O5: Immediate into organizer's Stripe/PayPal/Square; no payout by TT. | P5: No refund of TT fee/credit on refund or cancel; processor fees usually not returned either. No TT chargeback fee found on pages read. | Q5: TT fees shown excl. VAT; VAT/sales tax added where applicable | R5: • Charged per 'usage', not on ticket price: paid ticket = 1 usage; seated paid ticket = 2; free ticket = 0; free seated ticket = 1; product sale = 1; ticket issued via API (even free) = 1; imported ticket (even free) = 1; every ticket in a paid bundle = 1; a voucher-covered order is still charged. • First 5 ticket sales are free; the standard rate starts from the sixth paid ticket (pricing page FAQ). • Free tickets free within fair usage: the pricing page says 5,000 free tickets/year but its FAQ also mentions 'more than 2,000' in another answer; above fair usage TT gives a per-free-ticket quote via support. • Fees are not refunded when a ticket is refunded or cancelled (credits/PAYG fee kept); order transfer is free. • Discounts (apply via billing page, at TT's discretion): 50% for registered charities (forever), 20% for B Corps/PTAs/CICs/non-profits/BBN, half-usage for tickets under 5 incl. booking fees (a seated 5 ticket = 1.5 usage), 50% for Music Venue Trust members, 50% for Round Tables, 6 months free for Art Tickets users. Only one discount at a time; none applies to white-label/custom-domain prices or processor fees. • Refund protection: buyers can add it for 8% of ticket price; organizer keeps 10% of that fee, rest goes to TT (collected via PAYG). • SMS/WhatsApp reminders: TT charges 0.10 per event per order (GBP/USD) for buyers who opt in; organizer keeps any excess of the suggested fee. • TT does not touch the payment: Stripe, PayPal, Square or offline needed; TT fees are on top of processor fees; credits do not cover processing. • VAT and sales tax charged on TT fees where applicable; TT prices are shown excl. VAT. • No subscription, no contract; credits never expire; credits can be transferred between the organizer's box offices. • Pass-on of fees is manual: organizer adds a booking fee (per ticket) and/or transaction fee (per order, % and/or fixed); no automatic 'pass all fees' toggle. TT warns US sellers about the FTC junk-fees rule. | S5: • {"name": "White label (logo removal + custom domain)", "price": "A$69/month; custom domain alone A$12/month"} • {"name": "HubSpot/ActiveCampaign/Constant Contact integrations", "price": "monthly fee shown in account (amount not public)"} • {"name": "Free check-in app", "price": "free"} | T5: Very large free events / above fair usage: ask support for a quote; 'Book a demo' for larger organizers (no public enterprise price) | U5: self-serve, small/mid organizers (shows, workshops, venues, charities); flat fee per ticket, bring-your-own processor | V5: page | W5: https://www.tickettailor.com/pricing (pricing page + FAQ) https://help.tickettailor.com/en/articles/6731528-how-much-does-ticket-tailor-cost-and-how-will-i-be-charged (help centre: how much does TT cost) https://help.tickettailor.com/en/articles/4096561-what-are-the-fees-for-using-seating-charts (help centre: seating chart fees) https://help.tickettailor.com/en/articles/4725866-how-do-pre-pay-ticket-credits-work (help centre: pre-pay credits) https://help.tickettailor.com/en/articles/8687492-what-discounts-do-we-offer (help centre: discounts) https://help.tickettailor.com/en/articles/5210356-how-to-pass-fees-onto-your-ticket-buyers (help centre: passing fees on)
A6: Глобальные self-serve | B6: Ticket Tailor | C6: https://www.tickettailor.com | D6: Canada | E6: CAD | F6: direct merchant | G6: Direct merchant: buyer pays straight into the organizer's own Stripe/PayPal/Square account (revenue appears almost immediately, bank transfer takes about a week); TT never holds the money. TT fee collection: Pre-pay = card charged immediately when credits are bought (optional auto top-up monthly or when <=25 credits left). PAYG on Stripe = fee deducted automatically at the point of sale; PAYG on PayPal/Square/offline = TT charges the organizer's card on file monthly, or every 50 usage units, or 2 days after the last event ends. | H6: flat_per_ticket | I6: • Free (free tickets): +0.0 — Up to 5,000 free tickets/year, no fee — First 5 paid sales also free • Pay as you go (PAYG): +1.0 — All features, flat fee per usage, no subscription — Stripe: deducted at sale; PayPal/Square: billed to card • Pre-pay credits: — Same features; lower unit price when credits are bought in advance — See prepaid bundles; credits never expire; running out falls back to PAYG automatically; minimum bundle 100 credits | J6: • credit bundles: None (срок: none; возврат: None) | K6: включён: False; свой процессинг: True; Stripe, PayPal, Square; Stripe CA 2.9% + C$0.30 (example) | L6: configurable (organizer adds own booking/transaction fee; default is organizer absorbs) | M6: Free tickets are free up to 5,000/year; first 5 paid tickets free. | N6: Seat reservation: PAYG +C$1.00 per seated ticket; pre-pay: +1 credit. | O6: Immediate into organizer's Stripe/PayPal/Square; no payout by TT. | P6: No refund of TT fee/credit on refund or cancel; processor fees usually not returned either. No TT chargeback fee found on pages read. | Q6: TT fees shown excl. VAT; VAT/sales tax added where applicable | R6: • Charged per 'usage', not on ticket price: paid ticket = 1 usage; seated paid ticket = 2; free ticket = 0; free seated ticket = 1; product sale = 1; ticket issued via API (even free) = 1; imported ticket (even free) = 1; every ticket in a paid bundle = 1; a voucher-covered order is still charged. • First 5 ticket sales are free; the standard rate starts from the sixth paid ticket (pricing page FAQ). • Free tickets free within fair usage: the pricing page says 5,000 free tickets/year but its FAQ also mentions 'more than 2,000' in another answer; above fair usage TT gives a per-free-ticket quote via support. • Fees are not refunded when a ticket is refunded or cancelled (credits/PAYG fee kept); order transfer is free. • Discounts (apply via billing page, at TT's discretion): 50% for registered charities (forever), 20% for B Corps/PTAs/CICs/non-profits/BBN, half-usage for tickets under 5 incl. booking fees (a seated 5 ticket = 1.5 usage), 50% for Music Venue Trust members, 50% for Round Tables, 6 months free for Art Tickets users. Only one discount at a time; none applies to white-label/custom-domain prices or processor fees. • Refund protection: buyers can add it for 8% of ticket price; organizer keeps 10% of that fee, rest goes to TT (collected via PAYG). • SMS/WhatsApp reminders: TT charges 0.10 per event per order (GBP/USD) for buyers who opt in; organizer keeps any excess of the suggested fee. • TT does not touch the payment: Stripe, PayPal, Square or offline needed; TT fees are on top of processor fees; credits do not cover processing. • VAT and sales tax charged on TT fees where applicable; TT prices are shown excl. VAT. • No subscription, no contract; credits never expire; credits can be transferred between the organizer's box offices. • Pass-on of fees is manual: organizer adds a booking fee (per ticket) and/or transaction fee (per order, % and/or fixed); no automatic 'pass all fees' toggle. TT warns US sellers about the FTC junk-fees rule. | S6: • {"name": "White label (logo removal + custom domain)", "price": "C$69/month; custom domain alone C$10/month"} • {"name": "HubSpot/ActiveCampaign/Constant Contact integrations", "price": "monthly fee shown in account (amount not public)"} • {"name": "Free check-in app", "price": "free"} | T6: Very large free events / above fair usage: ask support for a quote; 'Book a demo' for larger organizers (no public enterprise price) | U6: self-serve, small/mid organizers (shows, workshops, venues, charities); flat fee per ticket, bring-your-own processor | V6: page | W6: https://www.tickettailor.com/pricing (pricing page + FAQ) https://help.tickettailor.com/en/articles/6731528-how-much-does-ticket-tailor-cost-and-how-will-i-be-charged (help centre: how much does TT cost) https://help.tickettailor.com/en/articles/4096561-what-are-the-fees-for-using-seating-charts (help centre: seating chart fees) https://help.tickettailor.com/en/articles/4725866-how-do-pre-pay-ticket-credits-work (help centre: pre-pay credits) https://help.tickettailor.com/en/articles/8687492-what-discounts-do-we-offer (help centre: discounts) https://help.tickettailor.com/en/articles/5210356-how-to-pass-fees-onto-your-ticket-buyers (help centre: passing fees on)
A7: Глобальные self-serve | B7: Tito (ti.to) | C7: https://ti.to | D7: Global (EUR shown on pricing page) | E7: EUR (139 currencies supported) | F7: direct merchant | G7: Organizer connects Stripe or PayPal; buyer money goes straight to the organizer's account ('Tito can never hold or delay your money'). Tito's fee is deducted automatically at transaction time through the Stripe/PayPal integration; a card on file is needed only when 'pay by invoice' is used (fees on those then charged monthly). | H7: percent | I7: • Standard: 3.0% потолок 25.0 — All features, no setup, no subscription — Cap EUR 25 per ticket on paid plans (tickets above EUR 833.33 pay flat EUR 25) • Charity / community / non-profit (apply): 2.5% потолок 25.0 — Same features — no commercial affiliation • Free events: 0.0% — Free events are free | K7: включён: False; свой процессинг: True; Stripe, PayPal; Stripe example on page: European cards 1.4% + EUR 0.25, non-European cards 2.9% + EUR 0.25; UK 1.4% + 20p / 2.9% + 20p; US 2.9% + 30c; Canada 2.9% + C$0.30 | L7: organizer (Tito deliberately does NOT allow passing booking fees to buyers; price shown is price paid) | M7: Free events free. | N7: not mentioned on pricing page (null) | O7: Direct from Stripe/PayPal rolling payouts (Stripe 2-7 days). | P7: Tito and gateway fees are charged at the transaction and NOT reversed on refund; no extra fee to process a refund. | Q7: Fee computed on ticket price excl. tax; Tito charges VAT on its own fee: EU VAT-registered = reverse charge, EU non-registered pay local VAT (MOSS), non-EU none | R7: • Tito Pro (pro.tito.io) is a separate next-gen product for professional invitation-only events; its pricing was not on the page read. • Cannot add booking fees on top - must fold fees into the ticket price. • No setup fee, no monthly subscription, no extra fee for premium features. • Usable in any country where Stripe or PayPal is available. | U7: conferences, workshops, tech/community events; Tito Pro is separate for invitation-only pro events; simple 3% model | V7: page | W7: https://ti.to/pricing (pricing page) https://help.tito.io/en/articles/3673403-does-vat-apply-to-tito-fees (help: VAT on fees) https://help.tito.io/en/articles/3766799-does-tito-refund-fees-on-cancelled-tickets (help: refunds) https://help.tito.io/en/articles/2038071-do-i-need-to-add-a-credit-card-to-make-my-event-live (help: how fees are charged) https://help.tito.io/en/articles/2006154-can-i-pass-booking-fees-along-to-attendees (help: pass booking fees)
A8: Глобальные self-serve | B8: Humanitix | C8: https://humanitix.com | D8: Australia | E8: AUD | F8: оба варианта | G8: Default: Humanitix gateway collects (payout ~5 business days after event); optional own Stripe account (same booking fee plus Stripe's charges). | H8: percent_plus_fixed | I8: • Standard: 4.0% +0.99 — All features, unlimited ticket types, reserved seating, scheduled payouts, scanning app — plus 10% GST • NFP / charity / school: 2.5% +0.5 — Same features — GST exempt • Free events: 0.0% +0.0 | K8: включён: True; свой процессинг: True; Humanitix gateway (cards, Apple/Google Pay, PayPal in some currencies), Stripe (alternative); Fee includes processing on the default gateway; with own Stripe the processor fee is added on top | L8: buyer by default (booking fee added on top); organizer can absorb or split | M8: No fees for free tickets/events. | N8: Reserved seating included in all plans (listed feature); no separate seating surcharge published. | O8: Default gateway: within about 5 business days after the event; earlier by request; Stripe: Stripe schedule. | P8: Refunds can be processed through the platform while the event has not been paid out; fee refund policy not captured; Stripe fees non-refundable. | Q8: fee quoted excl. GST; 10% GST added (NFP rate GST-exempt) | R8: • Not-for-profit; all profits go to charity; fees are called 'booking fees'. • No subscription, sign-up or admin fees; all features on all plans; no fees for free tickets, imported tickets or manual orders. • Registered NFP/charity/school/university rate is discounted (see plans). • Booking fees cannot be invoiced separately: they are deducted at purchase before payout. • Box-office (in-person) rate: 3% + 1 (local currency) per paid ticket; no fee for cash sales. • Organizer can absorb the fee (buyer pays face value, fee debited before payout) or split it with buyers. • On the default gateway AMEX and PayPal carry surcharges always paid by the buyer; PayPal not yet available for GBP. • Afterpay/Zip BNPL available for some currencies; those sales are paid out post-event only and cannot go to a connected Stripe account. • Custom pricing for big events or big-ticket items: contact sales. | U8: not-for-profit ticketing (profits to children's charities); events from community to festivals in AU/NZ/UK/US; fee paid by buyer by default | V8: page | W8: https://help.humanitix.com/en/articles/12292391-what-are-the-humanitix-booking-fees (help centre: booking fees (primary)) https://help.humanitix.com/en/articles/9760527-how-much-does-humanitix-cost (help centre: how much does Humanitix cost) https://help.humanitix.com/en/articles/8889188-payment-processing-options-for-your-humanitix-event (help centre: payment processing options) https://humanitix.com/pricing (US pricing page) https://humanitix.com/au/pricing (AU pricing page)
A9: Глобальные self-serve | B9: Humanitix | C9: https://humanitix.com | D9: New Zealand | E9: NZD | F9: оба варианта | G9: Default Humanitix gateway; optional own Stripe. | H9: percent_plus_fixed | I9: • Standard: 5.0% +0.49 — All features, unlimited ticket types, reserved seating, scheduled payouts, scanning app — plus 15% GST • NFP / charity / school: 3.0% +0.3 — Same features — GST exempt • Free events: 0.0% +0.0 | K9: включён: True; свой процессинг: True; Humanitix gateway (cards, Apple/Google Pay, PayPal in some currencies), Stripe (alternative); Fee includes processing on the default gateway; with own Stripe the processor fee is added on top | L9: buyer by default (booking fee added on top); organizer can absorb or split | M9: No fees for free tickets/events. | N9: Reserved seating included in all plans (listed feature); no separate seating surcharge published. | O9: Default gateway: within about 5 business days after the event; earlier by request; Stripe: Stripe schedule. | P9: Refunds can be processed through the platform while the event has not been paid out; fee refund policy not captured; Stripe fees non-refundable. | Q9: plus 15% GST on standard rate | R9: • Not-for-profit; all profits go to charity; fees are called 'booking fees'. • No subscription, sign-up or admin fees; all features on all plans; no fees for free tickets, imported tickets or manual orders. • Registered NFP/charity/school/university rate is discounted (see plans). • Booking fees cannot be invoiced separately: they are deducted at purchase before payout. • Box-office (in-person) rate: 3% + 1 (local currency) per paid ticket; no fee for cash sales. • Organizer can absorb the fee (buyer pays face value, fee debited before payout) or split it with buyers. • On the default gateway AMEX and PayPal carry surcharges always paid by the buyer; PayPal not yet available for GBP. • Afterpay/Zip BNPL available for some currencies; those sales are paid out post-event only and cannot go to a connected Stripe account. • Custom pricing for big events or big-ticket items: contact sales. | U9: not-for-profit ticketing (profits to children's charities); events from community to festivals in AU/NZ/UK/US; fee paid by buyer by default | V9: page | W9: https://help.humanitix.com/en/articles/12292391-what-are-the-humanitix-booking-fees (help centre: booking fees (primary)) https://help.humanitix.com/en/articles/9760527-how-much-does-humanitix-cost (help centre: how much does Humanitix cost) https://help.humanitix.com/en/articles/8889188-payment-processing-options-for-your-humanitix-event (help centre: payment processing options) https://humanitix.com/pricing (US pricing page) https://humanitix.com/au/pricing (AU pricing page)
A10: Глобальные self-serve | B10: Humanitix | C10: https://humanitix.com | D10: United States | E10: USD | F10: оба варианта | G10: Default Humanitix gateway for USD events. NOTE: the US pricing page (humanitix.com/pricing, read 2026-10-09) instead shows Standard 2.1% + $0.99 and Charities 1% + $0.99 with 'payment processing 2.9% + $0.30' - this matches the Stripe-connected rate (EUR/CAD tier). Reconciled: default gateway 5% + $1.29 all-in vs Stripe-connected 2.1% + $0.99 + Stripe 2.9% + $0.30. | H10: percent_plus_fixed | I10: • Standard: 5.0% +1.29 — All features, unlimited ticket types, reserved seating, scheduled payouts, scanning app — help centre; excl. tax; default-gateway rate with processing included • NFP / charity / school: 3.9% +1.29 — Same features — tax exempt • Free events: 0.0% +0.0 | K10: включён: True; свой процессинг: True; Humanitix gateway (cards, Apple/Google Pay, PayPal in some currencies), Stripe (alternative); Fee includes processing on the default gateway; with own Stripe the processor fee is added on top | L10: buyer by default (booking fee added on top); organizer can absorb or split | M10: No fees for free tickets/events. | N10: Reserved seating included in all plans (listed feature); no separate seating surcharge published. | O10: Default gateway: within about 5 business days after the event; earlier by request; Stripe: Stripe schedule. | P10: Refunds can be processed through the platform while the event has not been paid out; fee refund policy not captured; Stripe fees non-refundable. | Q10: fee quoted excl. taxes (sales tax applied where applicable) | R10: • Not-for-profit; all profits go to charity; fees are called 'booking fees'. • No subscription, sign-up or admin fees; all features on all plans; no fees for free tickets, imported tickets or manual orders. • Registered NFP/charity/school/university rate is discounted (see plans). • Booking fees cannot be invoiced separately: they are deducted at purchase before payout. • Box-office (in-person) rate: 3% + 1 (local currency) per paid ticket; no fee for cash sales. • Organizer can absorb the fee (buyer pays face value, fee debited before payout) or split it with buyers. • On the default gateway AMEX and PayPal carry surcharges always paid by the buyer; PayPal not yet available for GBP. • Afterpay/Zip BNPL available for some currencies; those sales are paid out post-event only and cannot go to a connected Stripe account. • Custom pricing for big events or big-ticket items: contact sales. • US page 2.1% + $0.99 (+ Stripe 2.9% + $0.30) vs help centre 5% + $1.29 all-in; both recorded. | U10: not-for-profit ticketing (profits to children's charities); events from community to festivals in AU/NZ/UK/US; fee paid by buyer by default | V10: page | W10: https://help.humanitix.com/en/articles/12292391-what-are-the-humanitix-booking-fees (help centre: booking fees (primary)) https://help.humanitix.com/en/articles/9760527-how-much-does-humanitix-cost (help centre: how much does Humanitix cost) https://help.humanitix.com/en/articles/8889188-payment-processing-options-for-your-humanitix-event (help centre: payment processing options) https://humanitix.com/pricing (US pricing page) https://humanitix.com/au/pricing (AU pricing page)
A11: Глобальные self-serve | B11: Humanitix | C11: https://humanitix.com | D11: United Kingdom | E11: GBP | F11: оба варианта | G11: Default Humanitix gateway for GBP events (PayPal not yet available for GBP); payout after event (third-party ticketingfees.co.uk: after the event by default, earlier on request). | H11: percent_plus_fixed | I11: • Standard: 5.6% +0.55 — All features, unlimited ticket types, reserved seating, scheduled payouts, scanning app — incl. VAT • NFP / charity / school: 4.0% +0.3 — Same features — incl. VAT • Free events: 0.0% +0.0 | K11: включён: True; свой процессинг: True; Humanitix gateway (cards, Apple/Google Pay, PayPal in some currencies), Stripe (alternative); Fee includes processing on the default gateway; with own Stripe the processor fee is added on top | L11: buyer by default (booking fee added on top); organizer can absorb or split | M11: No fees for free tickets/events. | N11: Reserved seating included in all plans (listed feature); no separate seating surcharge published. | O11: Default gateway: within about 5 business days after the event; earlier by request; Stripe: Stripe schedule. | P11: Refunds can be processed through the platform while the event has not been paid out; fee refund policy not captured; Stripe fees non-refundable. | Q11: fee quoted INCLUDING VAT (third-party: 4.67% + 46p excl. VAT; charity 3.33% + 25p excl. VAT) | R11: • Not-for-profit; all profits go to charity; fees are called 'booking fees'. • No subscription, sign-up or admin fees; all features on all plans; no fees for free tickets, imported tickets or manual orders. • Registered NFP/charity/school/university rate is discounted (see plans). • Booking fees cannot be invoiced separately: they are deducted at purchase before payout. • Box-office (in-person) rate: 3% + 1 (local currency) per paid ticket; no fee for cash sales. • Organizer can absorb the fee (buyer pays face value, fee debited before payout) or split it with buyers. • On the default gateway AMEX and PayPal carry surcharges always paid by the buyer; PayPal not yet available for GBP. • Afterpay/Zip BNPL available for some currencies; those sales are paid out post-event only and cannot go to a connected Stripe account. • Custom pricing for big events or big-ticket items: contact sales. • ticketingfees.co.uk (a competitor's site) quotes 4.67% + 46p excl. VAT, equal to 5.6% + 55p incl. VAT. | U11: not-for-profit ticketing (profits to children's charities); events from community to festivals in AU/NZ/UK/US; fee paid by buyer by default | V11: page | W11: https://help.humanitix.com/en/articles/12292391-what-are-the-humanitix-booking-fees (help centre: booking fees (primary)) https://help.humanitix.com/en/articles/9760527-how-much-does-humanitix-cost (help centre: how much does Humanitix cost) https://help.humanitix.com/en/articles/8889188-payment-processing-options-for-your-humanitix-event (help centre: payment processing options) https://humanitix.com/pricing (US pricing page) https://humanitix.com/au/pricing (AU pricing page)
A12: Глобальные self-serve | B12: Humanitix | C12: https://humanitix.com | D12: Eurozone (EUR) / Canada / Mexico / Fiji | E12: EUR (and CAD, MXN, FJD) | F12: direct merchant | G12: EUR, CAD, MXN and FJD events MUST connect their own Stripe account (Humanitix gateway not available): money goes straight to the organizer's Stripe; Humanitix fee deducted plus Stripe's own fees. | H12: percent_plus_fixed | I12: • Standard: 2.1% +0.99 — All features, unlimited ticket types, reserved seating, scheduled payouts, scanning app — + credit card fees charged by Stripe; same 2.1% + 0.99 for CAD/FJD/MXN • NFP / charity / school: 1.0% +0.99 — Same features — + Stripe fees • Free events: 0.0% +0.0 | K12: включён: False; свой процессинг: True; Stripe (mandatory); Stripe fees charged by Stripe on top of the booking fee | L12: buyer by default (booking fee added on top); organizer can absorb or split | M12: No fees for free tickets/events. | N12: Reserved seating included in all plans (listed feature); no separate seating surcharge published. | O12: Default gateway: within about 5 business days after the event; earlier by request; Stripe: Stripe schedule. | P12: Refunds can be processed through the platform while the event has not been paid out; fee refund policy not captured; Stripe fees non-refundable. | Q12: EUR: fee + Stripe's card fees; VAT treatment not stated | R12: • Not-for-profit; all profits go to charity; fees are called 'booking fees'. • No subscription, sign-up or admin fees; all features on all plans; no fees for free tickets, imported tickets or manual orders. • Registered NFP/charity/school/university rate is discounted (see plans). • Booking fees cannot be invoiced separately: they are deducted at purchase before payout. • Box-office (in-person) rate: 3% + 1 (local currency) per paid ticket; no fee for cash sales. • Organizer can absorb the fee (buyer pays face value, fee debited before payout) or split it with buyers. • On the default gateway AMEX and PayPal carry surcharges always paid by the buyer; PayPal not yet available for GBP. • Afterpay/Zip BNPL available for some currencies; those sales are paid out post-event only and cannot go to a connected Stripe account. • Custom pricing for big events or big-ticket items: contact sales. • Box-office rate not available ('NA') for these currencies. | U12: not-for-profit ticketing (profits to children's charities); events from community to festivals in AU/NZ/UK/US; fee paid by buyer by default | V12: page | W12: https://help.humanitix.com/en/articles/12292391-what-are-the-humanitix-booking-fees (help centre: booking fees (primary)) https://help.humanitix.com/en/articles/9760527-how-much-does-humanitix-cost (help centre: how much does Humanitix cost) https://help.humanitix.com/en/articles/8889188-payment-processing-options-for-your-humanitix-event (help centre: payment processing options) https://humanitix.com/pricing (US pricing page) https://humanitix.com/au/pricing (AU pricing page)
A13: Глобальные self-serve | B13: Luma (lu.ma) | C13: https://luma.com | D13: Global (USD) | E13: USD | F13: direct merchant | G13: Organizer connects own Stripe account; cards settle into the organizer's Stripe as tickets sell. Luma's platform fee is taken as an application fee on each transaction (luma_application_fee in the Sales History CSV) together with Stripe's processing fee. | H13: percent | I13: • Free: 5.0% — Unlimited events and guests, 500 invites/newsletters per week, 3 calendar admins, regional payment methods (iDEAL, Konbini, PayNow), coupons, ticket types — 5% platform fee on paid events; no tax collection • Luma Plus: 0.0% 69.0/мес 708.0/год — 0% platform fee, 5,000 sends/week, tax collection, API/Zapier, custom URLs, check-in manager, priority support, 5 admins — $59/month billed annually (save 14%, = $708/yr); $69/month month-to-month (Luma help comparison pages); per calendar, not per account; fees on earlier sales not refunded after upgrade • Enterprise: — Organization accounts, SSO, advanced integrations, custom features — Contact sales; price not public | K13: включён: False; свой процессинг: False; Stripe; Stripe typically 2.9% + 30c on top of the platform fee; доп. сбор: none; Stripe is the only processor | L13: organizer (third-party Hi.Events says the fee cannot be passed on; Luma pages show no pass-through toggle) | M13: Free events free; unlimited guests on free plan. | N13: No seating charts; tables modelled as limited-quantity high-price ticket tiers (Luma's own comparison page) | O13: Rolling payouts per organizer's Stripe schedule (typically next business day / 2 days in the US); Stripe Instant Payouts possible. | P13: Refunds via Stripe/Luma sales history; Luma platform-fee refund policy not captured; Stripe fees not returned. | Q13: prices in US dollars; Luma Plus can collect sales tax for ticket sales (free plan cannot); Luma fee invoices available for VAT bookkeeping | R13: • Extra calendar admin seat: $12/month ($9/month billed annually). • Weekly send add-ons for Plus: 10,000 $50/mo; 25,000 $200/mo; 50,000 $400/mo; 75,000 $600/mo; 100,000 $800/mo (billed annually, save up to 11%). • Plus is bought per calendar and cannot be moved to another calendar. • Calendar must be verified to unlock higher send limits even on Plus. • On a $20 ticket: Free plan fees $1.88 total; Plus $0.88 (Luma's own comparison page). | S13: • {"name": "Extra admin seat", "price": "$12/mo or $9/mo annual"} • {"name": "Weekly send tiers", "price": "$50-$800/mo"} | T13: Enterprise plan: contact sales (no public price) | U13: community/professional events, meetups, workshops, dinners; free-first with calendars/newsletters; strong with tech/creator communities | V13: page | W13: https://luma.com/pricing (pricing page) https://help.luma.com/p/luma-plus (help centre: Luma Plus overview) https://help.luma.com/p/understanding-payouts-and-event-proceeds (help centre: payouts and fees) https://help.luma.com/p/luma-vs-posh (Luma comparison page (vendor), includes Posh fee)
A14: Глобальные self-serve | B14: TicketSpice (Webconnex) | C14: https://www.ticketspice.com | D14: US | E14: USD | F14: оба варианта | G14: Default: in-house Webconnex Payments processor (platform collects, pays out WEEKLY by direct deposit, fees deducted before payout). Alternative: use own gateway (Stripe, Authorize.net, NMI, Paya, Cybersource, Payflow Pro, SecureNet) for an extra 1% + 25c per transaction charged by TicketSpice in USD - then money goes to the organizer's own gateway. | H14: flat_per_ticket | I14: • Standard: +0.99 — No platform/setup/support fees; page builder, reserved seating, box office app, scanning, API, weekly payouts — Plus card processing 2.9% + 30c (can be passed on); tickets of $5 or less: $0.49 • Box office app sales: +0.49 — On-site sales via the box office app — $0.49 per paid ticket on site • Free events: +0.0 — Free if the organizer also runs paid events; otherwise 99c/ticket | K14: включён: False; свой процессинг: True; Webconnex Payments (default), Stripe, Authorize.net, NMI, Paya, Cybersource; 2.9% + 30c standard processing; third-party gateways +1% + 25c per transaction | L14: configurable (organizer may absorb or pass on fees, and add own convenience fee and keep 100% of it) | M14: Free events free for organizers who also run paid events; else 99c/ticket. | N14: Reserved seating (charts, layouts, pods) included in the 99c; no surcharge stated. | O14: Weekly payouts by direct deposit (not after the event). | P14: Not captured on pricing page (fraud monitoring and purchase-protection options mentioned). | Q14: prices excl. tax | R14: • Optional upgrades: email marketing automation $9/mo + 2c per recipient; text message platform $19/mo + 2c per recipient (carrier activation fee applies); 3rd-party data enrichment $9/mo + 10c per record; cashless on-site payments 25c per transaction; white-label domain $150/year. • Using a non-default payment gateway costs 1% + 25c per transaction on top of 99c. • 'Your rates may be even lower' - volume pricing negotiable. | S14: • {"name": "Email marketing automation", "price": "$9/month + 2c/recipient"} • {"name": "Text message platform", "price": "$19/month + 2c/recipient"} • {"name": "White-label domain", "price": "$150/year"} • {"name": "Cashless on-site payments", "price": "25c/transaction"} | T14: 'Contact sales' for volume; no public price | U14: US events and attractions (festivals, haunts, theaters, waterparks); flat per-ticket fee plus in-house payments; box office and weekly payouts | V14: page | W14: https://www.ticketspice.com/pricing (pricing page + FAQ)
A15: Глобальные self-serve | B15: Universe (Live Nation) | C15: https://www.universe.com | D15: US | E15: USD | F15: оба варианта | G15: Default: Universe Payments collects and pays AFTER the event (48 hours after it ends, third-party); processing included but Universe Payments adds 3% in the US (third-party). Alternative: connect own Stripe (Stripe Connect, 'advanced payouts'): money goes to the organizer's Stripe on its schedule, Stripe charges processing separately and the Universe service fee is collected on top. | H15: percent_plus_fixed | I15: • Starter: 2.0% +0.59 — Unlimited ticket types/add-ons, checkout questions, box office app, API, Stripe Connect payouts, email support — US pricing page (read 2026-10-09) shows 2% + $0.59; a Google snippet of the same page and Hi.Events say 2% + $0.79 capped at $19.95 per ticket - the page seems to have changed. • Standard: 2.0% +0.59 — Starter + team permissions, cardholder presales, payment plans, tiered ticketing, priority email support — Page shows the same 2% + $0.59; third-party says Standard is 2.5% + $1.99 US (5.5% + GBP 0.99 UK); Capterra snippet 'starts at $19.95 one time' unverified. • Pro: — Custom a-la-carte plan: Ticketmaster sales, dedicated account manager, dynamic pricing, RFID — Custom pricing | K15: включён: True; свой процессинг: True; Universe Payments (default), Stripe Connect; Universe Payments: processing included by default (US adds 3%, UK/AU 2% per third-party); with own Stripe: Stripe's fee, not passed on as a Universe fee | L15: configurable (organizer can absorb or pass on service fee + processing; outside the USA the service+processing fee is shown as one all-in price) | M15: Free events: no fees at all. | N15: No separate seating line; no surcharge stated on page (null). | O15: Universe Payments: after the event (48 h after, third-party); Stripe Connect: your Stripe schedule. | P15: Standard chargeback support included (Universe submits evidence on Universe Payments disputes); extended support only in Pro. | Q15: 'Excludes VAT and processing fees' per pricing page | R15: • Fees vary by currency/location; VAT may apply; all-in pricing is shown as one number in every country except the USA. • Nonprofit/charity special pricing on request via a referral code that must be entered on every event page. • No free trial; no setup or termination fees; upgrade/downgrade/cancel any time. • Payment plans unavailable in Europe; fee cannot be passed to buyers in eight European countries (third-party). | U15: independent organizers worldwide (NA, UK, EU, AU/NZ); owned by Live Nation; Pro tier can sell on Ticketmaster | V15: page | W15: https://www.universe.com/pricing (pricing page (US view)) https://hi.events/fees/universe (third-party: Hi.Events fee page (a competitor))
A16: Глобальные self-serve | B16: Universe (Live Nation) | C16: https://www.universe.com | D16: Europe / UK / Australia | E16: EUR / GBP / AUD | F16: оба варианта | G16: As US (Universe Payments after event, or own Stripe). | H16: percent_plus_fixed | I16: • Starter (third-party): 2.0% +0.99 потолок 9.95 — UK: 2% + GBP 0.99; AU: 2% + A$0.99; service-fee cap GBP 9.95 — EUR varies by country from 1% + EUR 0.50 (France) to 5% + EUR 0.50 (Ireland) per Hi.Events | K16: включён: True; свой процессинг: True; Universe Payments, Stripe Connect; UK/AU: Universe Payments adds 2% (third-party) | L16: configurable except in 8 European countries | M16: Free events free. | O16: As US. | Q16: fees shown all-in (VAT where applicable) | R16: • Not read from Universe's own country pages (country selector not rendered in the scrape). | U16: independent organizers worldwide (NA, UK, EU, AU/NZ); owned by Live Nation; Pro tier can sell on Ticketmaster | V16: third_party | W16: https://hi.events/fees/universe (third-party Hi.Events fee page)
A17: Глобальные self-serve | B17: TicketSource | C17: https://www.ticketsource.co.uk | D17: United Kingdom | E17: GBP | F17: оба варианта | G17: Default: TicketSource payment processing (platform collects card payments, emails a fee breakdown after the event and pays out the MONDAY after the event, arriving by Wednesday). Alternative: connect own Stripe - payments go straight to the organizer's bank via Stripe and the fee drops to 4.5% + VAT because the organizer pays Stripe's fees. | H17: percent | I17: • TicketSource payment processing: 7.0% мин 0.25 — All features, seating plans, phone/email/live-chat support; includes card processing — 7% + VAT per PAID BOOKING (order), minimum GBP 0.25 + VAT per paid booking; GBP 10 booking = GBP 0.84 incl. VAT • Own Stripe account: 4.5% — Same features; Stripe fees charged separately by Stripe — 4.5% + VAT per paid booking • Registered charity: — Reduced booking fees on both options + Gift Aid and donation add-on — Discount amount not on page | K17: включён: True; свой процессинг: True; TicketSource processing, Stripe (own account); With TicketSource processing the card cost is included in 7%; with own Stripe Stripe's rate is paid to Stripe | L17: configurable (include in the price or pass on to the customer) | M17: No fees for in-person bookings or free events. | N17: Full access to the seating-plan designer on all accounts; no surcharge stated | O17: Monday after the event (arrives Wed/Thu); with Stripe: as sales happen on Stripe's schedule. | P17: Full refund guarantee: if the event is cancelled/postponed the customer is refunded ticket + booking fee with no extra charge (TicketSource bears the fee). | Q17: fee quoted + VAT: VAT is added (GBP 0.70 + VAT = GBP 0.84 on a GBP 10 booking in the page calculator) | R17: • Fee is per BOOKING (order), not per ticket: a booking of many tickets pays one 7% fee. • Card donations: 5% admin fee deducted; no fee for cash/cheque donations. • ticketingfees.co.uk (competitor) quotes 7% INCLUDING VAT, contradicting the page calculator that adds VAT on top. • No contracts, hidden fees or access tiers; telephone/live-chat support on all accounts. | U17: UK theatres, venues, community groups, charities; no contracts, no tiers; one booking fee; all features for all | V17: page | W17: https://www.ticketsource.co.uk/pricing (pricing page) https://www.tickettailor.com/blog/a-guide-to-pricing-for-online-ticketing (competitor (Ticket Tailor) blog: '7% per order')
A18: Глобальные self-serve | B18: Ticketbud | C18: https://www.ticketbud.com | D18: US | E18: USD | F18: direct merchant | G18: Organizer connects own Stripe or PayPal account (Ticketbud helps set up); processor fee 2.9% + 30c goes to the processor. Ticketbud's 2% + $0.99 per ticket is paid by attendees as a service fee unless the organizer absorbs it (collection mechanism not stated on the page). Help centre snippet (2023): Stripe payments have a 7-day rolling payout. | H18: percent_plus_fixed | I18: • Paid events: 2.0% +0.99 — All features, unlimited events and tickets, support; no tiers, no subscription, no credit card to start — Attendees pay 2% + $0.99 per ticket by default; organizer may absorb • Non-profit & schools: 1.75% +0.99 — Same — Attendee-paid by default • Free events: 0.0% +0.0 — Free events completely free | K18: включён: False; свой процессинг: True; Stripe, PayPal; Stripe/PayPal 2.9% + 30c per transaction (page wording: 'per ticket') | L18: buyer (attendees pay unless organizer absorbs) | M18: Free events free. | N18: Reserved seating feature exists (feature page); surcharge not stated | O18: Direct from Stripe/PayPal; 7-day rolling payouts on Stripe (help snippet 2023-09). | P18: Not captured. | Q18: prices excl. tax | R18: • Discounted rate for tickets under $10 available on request (contact): amount not published. • Custom & white-label: contact sales. • Rentable event hardware sold separately via shop.ticketbud.com (prices not captured). | T18: Custom & white label: 'let's chat' | U18: US small/mid events, hospitality, reunions, non-profits/schools; fee mostly paid by attendees; hardware rental and RFID options | V18: page | W18: https://www.ticketbud.com/pricing/ (pricing page) https://help.ticketbud.com/hc/en-us/articles/216675507-Payment-processor-options (help snippet (not opened))
A19: Театры и рассадка | B19: ThunderTix | C19: https://www.thundertix.com | D19: US (page also offers USD/CAD/GBP/AUD/NZD display toggle; non-USD amounts not captured) | E19: USD | F19: direct merchant | G19: Organizer connects own gateway (Stripe, Square, Authorize.net, Beanstream, Moneris, Elavon, Braintree); revenue goes to organizer's bank, typically nightly. ThunderTix bills its monthly plan + per-ticket overage on an invoice; billing cycle starts the day the gateway is connected and card payments go live. | H19: mixed | I19: • General Admission: 0% +1.0 20/мес — includes first 20 tickets per month — $1 per ticket beyond the 20; no % of sales • Reserved Seating (Most Popular): 0% +1.25 25/мес — includes first 20 tickets/month; custom interactive seating charts, tables/boxes/balconies, ADA linking — seating chart built by ThunderTix for a one-time fee, see seating • White Glove: 0% +1.95 195/мес — first 100 tickets/month; free seating chart + account setup, ticket templates and event pages built for you, branded subdomain, Meta CAPI, thermal ticket printing • K12 Schools (new for 2026): 3.5% +0.65 — reserved + GA seating, district season passes — 3.5% is all-in and includes Stripe card fees; requires the school's own Stripe account; verified K-12 schools/districts/edu nonprofits only | K19: включён: False; свой процессинг: True; Stripe, Square, Authorize.net, Beanstream, Moneris, Elavon, Braintree; Organizer pays its gateway directly (FAQ cites Stripe ~2.9%+30c, Square in-person from ~2.6%+15c); no extra ThunderTix fee for using own gateway; K12 plan is the exception (3.5% all-in) | M19: Only manually comped $0 tickets on single events and fully-free events are excluded from billing; tickets discounted to $0 by coupon/flex pass or comped inside a package DO count toward monthly ticket totals | N19: Custom chart built by ThunderTix: one-time $0.55 per seat (minimum $250); nonprofit rate $0.40 per seat (minimum $175); free with White Glove plan. Reserved plan costs $0.25/ticket and $5/mo more than GA | O19: Nightly deposits directly into the organizer's own gateway/bank account; no holding until after the event | P19: Not stated on pricing/FAQ; refund-to-gift-card feature; unlimited exchanges | Q19: not stated; US sales-tax context | R19: • No contract or minimum term; cancel anytime, no fee; 14-day free trial, can be extended • Billing begins when payment gateway goes live • Donations 2% credit-card fee, free by check; gift cards, merchandise sales and memberships 2% • Flexible Ticket Upgrade (CFAR): patron pays 10% to cancel for any reason, organizer keeps 65% of each upgrade • Nonprofit discounts 'available - just ask' (only the seating-chart discount is quantified) • Hardware (Zebra TC21/Chainway C90 scanners, card readers) sold separately, prices not published | S19: • {"name": "Email branding / mass email", "price": "$10/mo incl. 4,000 emails; $0.002 each beyond"} • {"name": "Thermal ticket printing setup", "price": "$199 one-time (included in White Glove)"} • {"name": "Meta Conversions API", "price": "$20/mo, needs branded subdomain (included in White Glove)"} • {"name": "Branded subdomain", "price": "included only in White Glove (price otherwise not shown)"} | T19: No public enterprise tier; White Glove is the top tier | U19: performing arts venues, theatres, music venues, schools; subscription + flat per-ticket fee, no % of sales | V19: page | W19: https://www.thundertix.com/online-ticketing-software-pricing/ (pricing page) https://www.thundertix.com/frequently-asked-questions/ (FAQ: setup fee, gateway, billing, comps)
A20: Театры и рассадка | B20: AudienceView Professional (incl. OvationTix) | C20: https://www.audienceview.com | D20: Global (NA focus) | F20: оба варианта | G20: Pricing page lists 'Merchant account and payment gateway connection' as included (organizer's own merchant account). A separate AV Payments product exists (page not read). Third party (TicketPeak, a competitor) says AudienceView pays after the event and only on manual request. | H20: negotiated | I20: • Subscription pricing: — unlimited users, support 24/7/365, CRM, shopping-cart branding, seating charts, comps 1:1 with paid, donations/memberships/merch/gift cards, implementation and data migration — no price published • Per-ticket pricing: — no price published; same feature set | K20: включён: None; свой процессинг: True | M20: Complimentary tickets included at a 1:1 ratio with paid tickets | N20: Reserved seating charts 'tailored to venue'; footnote says additional seating charts may incur a fee (amount not given) | O20: third_party (ticketpeak.com): paid after the show closes, must be requested | R20: • Claims 'transparent pricing with no hidden fees' but gives no numbers • Quote form asks annual ticket bands: 0-2,999 / 3,000-4,999 / 5,000-14,999 / 15,000-49,999 / 50,000-199,999 / 200,000+ and annual ticket revenue • Other products: AudienceView Unlimited (enterprise), Campus (higher ed) | T20: Contact sales only; no third-party number found | U20: mid/large performing arts, live music, museums, higher ed; quote-based subscription or per-ticket | V20: page | W20: https://www.audienceview.com/professional/pricing/ (pricing page (request form)) https://ticketpeak.com/when-do-ticketing-platforms-pay/ (third-party payout claim)
A21: Театры и рассадка | B21: Brushfire | C21: https://www.brushfire.com | D21: US | E21: USD | F21: direct merchant | G21: Payments run on the organizer's own Square or Stripe account at those processors' standard rates, no Brushfire markup; funds deposited quickly ('instantly' per FAQ). How Brushfire's own fee is collected (application fee vs invoice) is not stated. | H21: mixed | I21: • Attractions: +0.75 — season pass, group ticketing, mobile box office app, hardware credit when switching — no charge for free tickets • Education: +0.75 — dedicated Customer Success Manager, season pass, group, box office app — no charge for free tickets • Churches & ministries under 1,500 weekly attendance: 299/мес — ticketing, registration, ChMS integrations — plus card processing • Churches & ministries over 1,500 weekly attendance: 1.0% +1.0 — calculator example: $275 ticket x1,000 -> Brushfire fee $3.75/ticket • Other events: 1.0% +1.5 — dedicated CSM, season pass, group, box office app, hardware credit — free-ticket treatment not stated for this tier | K21: включён: False; свой процессинг: True; Square, Stripe; Square 2.6%+$0.15 in person, 2.9%+$0.30 online, 3.5%+$0.15 keyed; Stripe 2.7%+$0.05 in person, 2.9%+$0.30 online, 3.4%+$0.30 keyed; 'Stripe partnership rates' 2.9%+$0.30 online, 2.6%+$0.10 chip/PIN, 3.5%+$0.15 keyed | L21: configurable | M21: No charge for free tickets on Attractions/Education tiers | N21: No seating surcharge stated on pricing page | O21: Deposited quickly after transactions (FAQ says 'instantly'); direct to organizer's processor account | Q21: not stated | R21: • No setup fees, no monthly costs (except church plan), no contracts • Pass fees to attendees / absorb / custom fee structure • Display prices include required fees where applicable • Hardware credit when switching from another provider | T21: Demo-driven; no enterprise price shown | U21: attractions, farms, haunts, festivals, schools, churches; pay-as-you-go per ticket, vertical-specific rates | V21: page | W21: https://www.brushfire.com/pricing (pricing page + FAQ)
A22: Театры и рассадка | B22: Yapsody | C22: https://www.yapsody.com | D22: Global (currency selector USD/GBP/CAD/AUD and ~160 more) | E22: USD | F22: direct merchant | G22: Organizer links own gateway (Stripe, PayPal, 14+ gateways); 'payout directly to your account', 'zero holding of funds'. Yapsody bills its fee afterwards (monthly invoices/autopay, 'pay us later'); the 50% non-profit rebate is applied on monthly invoices. | H22: percent_plus_fixed | I22: • General seating: 1.75% +0.59 — all features, unlimited events, onboarding support — per ticket sold • Reserved seating: 2.49% +0.98 — interactive seat-map tool, VIP sections — per ticket sold | K22: включён: False; свой процессинг: True; Stripe, PayPal, 14+ other gateways; Organizer pays gateway; Yapsody calculator example: $100 ticket general seating -> $2.34 Yapsody fee | L22: configurable | M22: Free events: all features free | N22: Reserved seating costs +$0.39 and +0.74 pts over general seating; no chart setup fee stated | O22: Paid directly by organizer's own processor; no funds held by Yapsody | Q22: not stated | R22: • 50% rebate on fees for non-profit/NGO events (applied on monthly invoices) • Zero setup cost, no hidden charges • Ability to pass on fees or use fee-inclusive pricing • Site shows $ for calculator even with other currencies; per-currency fee amounts not published | T22: Custom feature development and managed services for strategic clients; no prices | U22: events, casinos/hospitality, theatres; lowest-headline-fee positioning; monthly invoiced, organizer keeps cash | V22: page | W22: https://www.yapsody.com/ticketing/pricing/ (pricing page)
A23: Театры и рассадка | B23: SimpleTix | C23: https://www.simpletix.com | D23: Global (account country list incl. Czech Republic, Spain, Portugal, Poland, UK, EU states; calculator offers USD/GBP/CAD/AUD/EUR) | E23: USD | F23: direct merchant | G23: Organizer connects own Square, Stripe, PayPal or Authorize.net; 'immediate payouts to your merchant account'. With Stripe, PayPal and Square US the SimpleTix fee is deducted inside the transaction (application-fee style); for other processors and offline sales SimpleTix charges the organizer's card on the 1st of the following month. | H23: percent_plus_fixed | I23: • Online sales: 2.0% +0.79 потолок 9.99 — all features, no tiers — cap $9.99 per ticket • In-person / box office: +0.25 — Square/Stripe readers, tap to pay, cash/comp support • Season tickets: 2.0% +0.79 — charged on total pass value; GA or reserved • Tickets $5 or less: +0.25 • Non-profit (501c3): 2.0% +0.71 — FAQ describes 10% off the platform fee, not the card fee | K23: включён: False; свой процессинг: True; Square, Stripe, PayPal, Authorize.net; Calculator assumes 2.9% + 30c; actual per processor/country | L23: configurable | M23: GA and Flex Pass free tickets $0; reserved-seat free tickets 25c each | N23: Reserved seating supported; seating charts built free; reserved free tickets 25c | O23: Immediate to organizer's merchant account | Q23: not stated; 'All prices shown in USD' | R23: • No setup, monthly or contract fees • Three fee options: pass all, custom service fee added on top (100% to organizer), absorb all • Square Canada/UK/Australia and non-Stripe processors: fee billed to card on file monthly | T23: none published | U23: small/mid organizers incl. theatres and comedy clubs worldwide; per-ticket fee with cap, no tiers | V23: page | W23: https://www.simpletix.com/pricing/ (pricing page + FAQ)
A24: Сев.-Зап. Европа и Швейцария | B24: pretix (pretix.eu hosted + self-hosted Community/Enterprise) | C24: https://pretix.eu | D24: Hosted (pretix.eu), all countries (business customers only) | E24: EUR | F24: direct merchant | G24: Buyer pays into the organizer's own bank / PayPal / Stripe / Mollie etc. (pretix integrates providers; organizer picks). pretix bills its fee by monthly invoice (SEPA debit, card or bank transfer). No payout from pretix. | H24: percent | I24: • pretix Hosted (pay as you sell): 2.5% потолок 15.0 — all features: shop, access control, point-of-sale, unlimited users, email+phone support, API; seating plugin included on hosted — 2.5% of net ticket price (also applied to non-ticket products), capped at EUR 15 per ticket (reached at ~EUR 600 tickets); for other currencies a cap of roughly EUR 15 equivalent; only successfully paid orders are charged; no minimum term • pretix Hosted for non-profits: 2.0% потолок 15.0 — same as above — applied for after account creation, decided case-by-case by pretix independent of legal charity status; free-ticket price EUR 0.10 and free quota 2,500/yr | K24: включён: False; свой процессинг: True; bank transfer, PayPal, Stripe, Mollie, others via plugins; organizer pays provider fees directly to the provider (pretix links special Mollie conditions) | L24: organizer (pretix invoices organizer); organizer can add a service fee to buyer price via plugin/settings | M24: first 500 free tickets per calendar year are free; quota grows by 1 for every paid ticket sold; beyond that EUR 0.50 per free ticket (non-profit: 2,500 free quota, EUR 0.10) | N24: Seating plugin is a proprietary plugin (3 license points on Enterprise); on Hosted it is included in the standard price (page says price includes almost all features) | O24: N/A - money goes directly to organizer's payment account | P24: no cancellation fee; fees already paid on cancelled orders are NOT refunded but credited against the next invoice | Q24: prices exclude VAT; German-resident organizers (and EU without VAT ID) get 19% VAT added on pretix's invoice; fee is computed on the net ticket price | R24: • only for businesses/associations/non-profits, not consumers • Peppol / Italy / Portugal e-invoicing add-on EUR 0.20 per invoice • lead scanning add-on EUR 25 per exhibitor that scanned at least one lead • discounts for large customers on request • invoice monthly | S24: • {"name": "Lead scanning (pretixLEAD)", "price": "EUR 25 per exhibitor"} • {"name": "Peppol / e-invoicing", "price": "EUR 0.20 per invoice"} • {"name": "pretixPOS / SCAN / KIOSK apps and hardware rental", "price": "included in %, hardware rental price not captured"} | T24: volume discounts on request via sales | U24: conferences, festivals, theatres, exhibitions; self-serve SaaS or self-hosted open source; non-profit friendly | V24: page | W24: https://pretix.eu/about/en/pricing (hosted pricing + FAQ) https://pretix.eu/about/en/pricing?nonprofit=true (non-profit pricing)
A25: Сев.-Зап. Европа и Швейцария | B25: pretix (pretix.eu hosted + self-hosted Community/Enterprise) | C25: https://pretix.eu | D25: Self-hosted / on-premise licence (global) | E25: EUR | F25: direct merchant | G25: Software is run by the organizer; no per-ticket fee to pretix; payments go to organizer's own providers. | H25: subscription | I25: • Community: 0% +0 — open source AGPLv3, unlimited volume, open-source plugins, community support only — needs Linux server admin skills; no proprietary plugins (seating, POS, etc.) • Enterprise Starter: 499 (<=10k orders and <=30k revenue) / 900 (<=20k orders, <=60k rev) / 2000 (<=50k, <=150k) / 3600 (<=100k, <=300k) / 8100 (<=250k, <=750k) / 14500 (<=500k, <=1.5M) / 26100 (<=1M, <=3M) / 44000 (>1M orders, >3M)/год — pretix Enterprise licence, 3 plugin license points, email support next business day — tier chosen by orders per year and turnover excl. VAT; volume reported at licence-year end and retroactively upgraded if exceeded; auto-renews yearly, 4 weeks notice; payment upfront for the year • Enterprise Professional: 750 / 1300 / 2900 / 5200 / 11700 / 21000 / 37800 / 62000 (same 8 volume steps)/год — 10 license points, phone support subject to availability — see Starter for steps • Enterprise Ultimate: 950 / 1700 / 3800 / 6800 / 15300 / 27500 / 49500 / 85000 (same 8 volume steps)/год — 20 license points, contact sales — see Starter for steps | K25: включён: False; свой процессинг: True; any supported plugin; organizer deals with providers directly | L25: organizer | M25: unlimited (volume counts every order incl. free ones) | N25: Seating plugin costs 3 license points | O25: N/A | P25: N/A (no per-ticket fee) | Q25: VAT or other taxes added depending on location | R25: • plugin license points: Seating 3, Exhibitors/Lead scanning 3, pretixPOS 2, Resellers 2, Shipping 2, TICKeos 2, HubSpot 2, most others 1 • default Enterprise licence does NOT allow running the software for third-party organizers (reselling as a service needs an individual offer) • one production server per licence; multi-server by offer • custom development billed by hour or negotiated contribution share | T25: multi-tenant / white-label for third parties: individual offer | U25: conferences, festivals, theatres, exhibitions; self-serve SaaS or self-hosted open source; non-profit friendly | V25: page | W25: https://pretix.eu/about/en/pricing/selfhosted (self-hosted licence table + FAQ)
A26: Южная Европа | B26: Tuk Tuk | C26: https://tuktuk.cat | D26: Spain | E26: EUR | F26: оба варианта | G26: Default: platform collects and transfers sales to the organiser's bank account after the event (with invoice for the fee). ENTERPRISE: direct payment gateway to the organiser's own account. The page does not give a payout day count. | H26: percent | I26: • FREE: 0.0% — Free (0 EUR) tickets only, up to 3 events and 500 tickets per event; QR validation, named tickets, capacity control, email delivery, Google Wallet • BASIC: 8.0% — Unlimited events and tickets, ticket types, named tickets, stats, card and Bizum, WhatsApp + email delivery, basic support — Fee includes IVA and card/Bizum payment costs. EUR 12 ticket -> EUR 0.96 fee • PROFESSIONAL: 9.0% — Basic + group tickets, season passes, seat map for theatres, VIP table map, invitations, discount codes, Meta Pixel, priority support • ENTERPRISE: — Professional + white label, own domain and email domain, DIRECT payment gateway into the organiser's bank account, Verifactu-compatible invoicing, webhooks, onboarding — Contact sales | K26: включён: True; свой процессинг: None; Card, Bizum; included in the % fee | L26: configurable: fee added on top of the ticket (buyer pays, default/most common) or included in the price and deducted from proceeds (organiser pays ~11 EUR on a 12 EUR ticket) | M26: FREE plan: no commission for 0 EUR tickets, capped at 3 events / 500 tickets per event | N26: Seat map only on PROFESSIONAL (9%) and above | O26: After the event, direct to bank account, with invoice for the fee (no day count stated). | P26: Fee is not refundable if the organiser cancels the event. | Q26: 'El IVA ya esta incluido' - the percentage is VAT-inclusive | R26: • 8%/9% are gross incl. IVA and payment costs, so net of 21% IVA the platform keeps about 6.6% / 7.4% before card costs (arithmetic, not a quoted figure) | T26: ENTERPRISE: contact sales | U26: Catalan/Spanish self-serve ticketing for small concerts, theatres, town festivals, free events | V26: page | W26: https://tuktuk.cat/es/precios (pricing: FREE / BASIC 8% / PROFESSIONAL 9% / ENTERPRISE, VAT included) https://tuktuk.cat/es/blog/12/cuanto-cuesta-vender-entradas-online/ (own blog: who pays, example 300 x 12 EUR, payout at end of event with invoice)
A27: Южная Европа | B27: Soundtix | C27: https://soundtix.com | D27: Spain | E27: EUR | F27: direct merchant | G27: Stripe Connect: each organiser has their own Stripe account and the money goes straight to it at the moment of purchase; Soundtix never holds it. Fee is added on top of the base price paid by the buyer (application-fee style split). | H27: percent | I27: • Standard (ticket base price < 40 EUR): 10.0% — Stripe processing, ticketing platform, 100% white label, Apple Pay/Google Pay, no-registration checkout, QR access control, embeddable widget, Meta Ads + Mailchimp integrations, support 24/7, virtual queue, seat selection — Pricing page: 'ronda el 10%' added to the base price and split into Stripe commission + Soundtix commission (example 15 EUR ticket: buyer pays 16.41; Stripe 0.42; Soundtix 0.99). The blog states, for a 40 EUR ticket, buyer pays 42 EUR: Stripe 0.88 + Soundtix 1.12 incl IVA (= 2.8% platform fee). The two descriptions are not the same schedule - scale not reconciled. • Tickets > 40 EUR or high volume: — Custom proposal — No public number | K27: включён: True; свой процессинг: True; Stripe (Stripe Connect); Stripe ES standard ~1.5% + 0.15 EUR (as quoted by Soundtix); Soundtix absorbs Stripe changes | L27: buyer (fee added to the base price; organiser receives the base price in full) | M27: Free events cost nothing | N27: Seat selection included (no surcharge stated) | O27: Instant, direct to the organiser's Stripe account. | P27: If the event is cancelled Soundtix returns its fee and also covers Stripe's non-refundable part for the first 100 EUR of Stripe costs for new promoters. | Q27: Fee amounts are shown INCLUDING IVA (comparison article: 'todos los precios con IVA incluido'; example: Soundtix 1.12 EUR 'IVA incluido') | R27: • No monthly fee, no setup, no minimum, no contract • Real-world example on the pricing page: 201 tickets at 15 EUR average | T27: Custom for >40 EUR tickets / large volume | U27: Spanish white-label ticketing for venues/promoters/bands, built on Stripe Connect with instant payouts to the organiser's own Stripe | V27: page | W27: https://soundtix.com/precios-comisiones-venta-entradas (official pricing page) https://soundtix.com/blog/comparativa-ticketeras-espana-2026 (own comparison article, 2026-08-23: 2.8% example, cancellation cover)
A28: Южная Европа | B28: Trackage Scheme (Malta) | C28: https://trackagescheme.com | D28: Malta | E28: EUR | F28: direct merchant | G28: Funds settle directly into the organiser's own Stripe account; Trackage says it does not hold the money. Stripe standard schedule 'typically 2-7 days for Maltese accounts'. Fee collected as a booking fee. | H28: mixed | I28: • Per-ticket booking fee: — Charged only when a ticket sells; no subscriptions, no setup fees — Rate not published: 'contact us for specific pricing based on event size and type' | K28: включён: False; свой процессинг: True; Stripe; Stripe's own rate, not stated | O28: Stripe standard payout, 2-7 days for Maltese accounts | Q28: Not stated | T28: Event-size based quote | U28: Maltese music-event ticketing with payouts into the organiser's own Stripe account | V28: page | W28: https://trackagescheme.com/tickets (organiser page (via fetch summarizer))
A29: Центр. и Вост. Европа, Балканы, Прибалтика | B29: BZUCO (bezticketingovky.cz) | C29: https://bezticketingovky.cz | D29: Czechia | E29: CZK | F29: direct merchant | G29: Buyers pay via organizer's own gateway (GoPay, Comgate) or by bank transfer to the organizer's account (Fio banka matching), money goes straight to the organizer. Platform fee is drawn automatically from a prepaid annual credit on each ticket sold. | H29: prepaid_credits | I29: • Zakladni (Basic): 2% — smaller events; one-time setup 5,000 CZK; minimum annual credit 10,000 CZK — Commission deducted from credit • Premium: 3% — more features, larger events; no setup fee; minimum annual credit 50,000 CZK — Commission deducted from credit | J29: • min annual credit 10,000 CZK (Basic): None (срок: not stated; возврат: None) • min annual credit 50,000 CZK (Premium): None (срок: not stated; возврат: None) | K29: включён: False; свой процессинг: True; GoPay, Comgate, bank transfer; Gateway typically charges 'up to 1%' to the organizer | L29: configurable: optional per-ticket buyer fee paid to the ORGANIZER (e.g. 20 CZK on 500 CZK) to cover the 2-3% plus gateway | O29: Not applicable (money goes directly to the organizer immediately) | Q29: not stated | R29: • Site says 'no monthly fees' and 'no commitments' yet requires a minimum annual credit - internally inconsistent • Marketing comparison on 500,000 CZK turnover: BZUCO 2% = 10,000 CZK; 3% = 15,000; SMSTicket 5% = 25,000; GoOut 7% = 35,000; Ticketportal 8% = 40,000 (competitor rates are the vendor's claims) • Currencies: CZK, EUR, PLN | U29: Czech 'ticketing without a ticketing company': organizer uses own payment gateway/bank account, pays 2-3% from prepaid credit; closest structural analogue to Arena in the Czech market | V29: page | W29: https://bezticketingovky.cz/ (pricing and money-flow page)
A30: Центр. и Вост. Европа, Балканы, Прибалтика | B30: Colosseum / ColosseumTicket (Perfect System s.r.o.) | C30: https://colosseum.eu | D30: Czechia | E30: CZK | F30: оба варианта | G30: Colosseum SOFTWARE is the organizer's own system (organizer owns data and payments, licence/rental/cloud fee, 'no commission'); the ColosseumTicket.cz marketplace collects buyer payments and passes the organizer its share ('odvedeme jim v odpovidajicim pomeru'). | H30: mixed | I30: • Colosseum software - three business models: 0% — up-front purchase with no per-sale fees, OR fixed monthly rental, OR one-off purchase plus monthly cloud operation fee; self-hosted option; hardware (printers, scanners, kiosks) and implementation extra — FAQ: 'What cut does Colosseum take? Nothing - no commission'. Price list page ('Cenik') says 'coming soon', offers a tailored quote. No numbers anywhere. | K30: включён: False; свой процессинг: True; online card, Google Pay, Apple Pay, transfer, Twisto, meal vouchers (software supports them) | L30: buyer pays small per-order handling fees on the marketplace; organizer pays licence | N30: Hall/seating editor included in software | P30: Marketplace: payment-type fees (benefit cards) and postage not refunded on cancelled events | R30: • ColosseumTicket buyer-side price list (section 10 of T&Cs): e-ticket delivery 20 CZK, registered mail 129 CZK, bulk order (10+) or pay-by-invoice 30 CZK, Gallery Beta card 5% of purchase value, Pluxee/Benefit Plus/Benefity 10% of purchase value, optional ticket insurance 39-1,980 CZK per ticket • ColosseumTicket organizer commission not published: T&Cs say the portal's service fee 'is usually a percentage of the purchase value' • Hospodarske noviny 2026-04-13 (paywalled snippet) notes a Colosseum Ticket buyer paying an extra fee on an 899 CZK theatre ticket; fee amount not retrievable | S30: • {"name": "hardware, implementation, marketing, festival service", "price": "quote only"} | T30: Quote on request; price list 'in preparation' | U30: Reservation SOFTWARE for theatres, museums, castles, stadiums (600+ organizers in CZ/SK, National Theatre) plus the consumer portal ColosseumTicket.cz/.sk | V30: page | W30: https://colosseum.eu/ (software homepage incl. FAQ 'no commission') https://colosseum.eu/cenik (price list placeholder) https://colosseumticket.cz/cs/obchodni-podminky (marketplace T&Cs with buyer fee list)
A31: Центр. и Вост. Европа, Балканы, Прибалтика | B31: Evenea | C31: https://evenea.pl | D31: Poland | E31: PLN | F31: оба варианта | G31: Default: payments go through an online payment provider via Evenea and are settled to the organizer; organizer may connect their own processors (PayU, tPay, PayPal, dotpay, InPay) and then pays only Evenea's commission, settling processing fees directly with the processor. Fee by invoice. Settlement timing article not opened. | H31: percent_plus_fixed | I31: • Commission: 2.9% +1.0 — 1 PLN + 2.9% of gross value of each sold PAID ticket (+23% VAT = 3.9 PLN net / 4.80 PLN gross on a 100 PLN ticket) — Always on the organizer's side. Free tickets carry no commission. | K31: включён: False; свой процессинг: True; Evenea payment operator, PayU, tPay, PayPal, dotpay, InPay; Extra online-payment/transfer commission 2.8% of the order's gross value (+23% VAT) when using Evenea's operator - by default charged to the buyer, organizer can take it on; доп. сбор: 2.8% net of order gross value | L31: platform commission: organizer; processing commission: buyer by default (switchable) | M31: free, no commission | O31: See help article 'Kiedy otrzymam pieniadze' (not read) | Q31: Evenea commission and processing commission both exclusive of 23% VAT; VAT added | R31: • Article last updated 2022-03-08, may be stale | U31: Polish self-service registration + ticketing for events, courses, conferences, charity runs | V31: page | W31: https://evenea.zendesk.com/hc/pl/articles/360011963880-Ile-wynosi-prowizja (help article)
A32: Центр. и Вост. Европа, Балканы, Прибалтика | B32: Tixx.pl | C32: https://tixx.pl | D32: Poland | E32: PLN | F32: direct merchant | G32: Ticket money goes straight to the organizer's own account (own bank account with manual matching, or a payment operator such as Przelewy24 under the organizer's contract). Platform fee is a flat subscription. | H32: subscription | I32: • STARTER (up to 1 M PLN annual turnover): 0% +0 290/мес 3190/год — unlimited events and tickets, 1 admin account, newsletter once a month, e-mail + phone support Mon-Fri 10-16 — first month free; no setup fee listed • PREMIUM: 0% +0 990/мес 9900/год — unlimited events/tickets, 5 admin accounts, newsletter twice a month, 24/7 phone support — annual price = ~825 PLN/month | K32: включён: False; свой процессинг: True; Przelewy24, BLIK, cards via organizer's operator; operator fee can be added to the order total and passed to the buyer | L32: organizer (flat subscription); buyer service fee optional and kept by the organizer | O32: Immediate to organizer's account | Q32: prices net of VAT | R32: • One-time setup fee may apply for large events needing customization or a dedicated server (amount not given) • Setup takes about two weeks; payment-provider contract longer • Savings calculator assumes a competitor at 5% + 5 PLN per ticket | T32: Custom solutions on request | U32: Polish 'ticketing without commission' subscription system; clubs, theatres, event organizers with own bank/Przelewy24 | V32: page | W32: https://tixx.pl/cennik (price list) https://tixx.pl/ (homepage and FAQ)
A33: Центр. и Вост. Европа, Балканы, Прибалтика | B33: Biletyna / biletyna.PRO | C33: https://biletyna.pl | D33: Poland | E33: PLN | F33: оба варианта | G33: biletyna.PRO 'own sales': money goes directly to the organizer once booked (organizer signs a contract with an online payment operator such as Tpay or PayU separately). Sales through the biletyna.pl portal go to a separate subaccount and are transferred after the event. | H33: negotiated | K33: включён: False; свой процессинг: True; Tpay, PayU; operator fees not described | O33: Own sales: direct; portal sales: after the event | R33: • No prices: 'we treat every client individually'; onboarding 'a few working hours'; invoicing module free • The 2025/26 'biletyna.PRO news' PDF claims organizers 'paid 0 PLN commission for launching and running campaigns' (marketing campaign module), not ticket fees | S33: • {"name": "hardware (ticket machine, printers, terminal)", "price": "not public"} | T33: Contact wspolpraca@biletyna.pl | U33: Polish marketplace (biletyna.pl) plus biletyna.PRO ticket system for venues and organizers; 6.1 M tickets sold in 2024 (company claim) | V33: page | W33: https://biletyna.pro/produkty/sprzedaz-wlasna (product page)
A34: Центр. и Вост. Европа, Балканы, Прибалтика | B34: Cooltix | C34: https://organizers.cooltix.com | D34: Hungary | E34: HUF | F34: оба варианта | G34: Default Cooltix Payment (Stripe): money collected by Stripe, fees deducted from proceeds and invoiced monthly, automatic payout 3 workdays after the event for Hungary-seated organizers (5 for others); early payout only from Intermediate package with individual assessment. Alternative: organizer connects own provider (Stripe, SimplePay, SZEP cards): income goes directly to the organizer, Cooltix fees invoiced monthly / card on file. | H34: percent_plus_fixed | I34: • Online ticket sales: 2.7% +47 — standard events — net of VAT; HUF • Seated events: 3.4% +60 — events with seat map • Offline / onsite sales: 1% +10 — box office via app | K34: включён: False; свой процессинг: True; Cooltix Payment (Stripe), Stripe, SimplePay, SZEP card (OTP, MBH, MKB); Cooltix Payment Provider 1.5% + 0.25 EUR per transaction (EU pricing page; HU equivalent not given); own provider: no Cooltix surcharge | L34: buyer: Cooltix is built so the BUYER pays a 'handling fee' set by the organizer (up to 10% of ticket price) which covers card processing and Cooltix fee; any amount above Cooltix's own fee is the organizer's extra income. Organizer can absorb instead. | M34: no fee on free tickets | N34: seated events 3.4% + 60 Ft (vs 2.7% + 47 Ft) | O34: see money_flow_note | P34: Handling fee never refunded and Cooltix fees still charged on refunded tickets; organizer-initiated refunds follow the same rule; successful chargebacks are deducted from the organizer's income; refunds limited to organizer income less amounts already paid out; no reserve mentioned (but services can be limited if fees unpaid >8 days) | Q34: fees are net, VAT added; prices in HU are in Ft | R34: • Fees by country: all EU except HU and other supported countries 2.5% + EUR 0.25 / seated 3% + EUR 0.50 / offline 1% + EUR 0.10; HU 2.7% + 47 Ft / 3.4% + 60 Ft / 1% + 10 Ft (support article dated 2025-12-02) • Prices net in EUR, VAT extra; revenue kept per currency, conversion costs on organizer • Per-ticket fee is NOT zero for the organizer in Cooltix's own terms - 'no fee deducted from ticket price' means the buyer-paid handling fee funds it | T34: Intermediate package needed for early payout (individual assessment) | U34: Hungarian-born self-service ticketing for festivals, clubs, theatres in HU, SK, CZ, HR and other EU countries; 'organizer earns on handling fee' pitch | V34: page | W34: https://support.cooltix.com/en/articles/11469656-service-fee-by-country (fee table by country) https://organizers.cooltix.com/en/pricing (pricing page (EUR): 2.5%+0.25, seated 3%+0.50, on-site 1%+0.10, payment provider 1.5%+0.25) https://organizers.cooltix.com/sk/ (Slovak organizer page: processing fee cap 10%, own provider invoiced monthly) https://support.cooltix.com/en/articles/6912347-terms-and-conditions-for-organizers (organizer T&Cs: payouts, refunds, chargebacks) https://blog.cooltix.com/hu/legjobb-jegyertekesito-oldalak-magyarorszagon (Cooltix blog quoting HU fee and competitors (biased))
A35: Центр. и Вост. Европа, Балканы, Прибалтика | B35: Cooltix | C35: https://organizers.cooltix.com | D35: EU (other than HU: SK, CZ, HR, RO, etc.) | E35: EUR | F35: оба варианта | G35: Same as Hungary (Stripe-based Cooltix Payment default; payout 5 workdays after event). | H35: percent_plus_fixed | I35: • Online: 2.5% +0.25 • Seated: 3% +0.5 • Offline: 1% +0.1 | K35: включён: False; свой процессинг: True; Stripe-powered Cooltix Payment, own Stripe/SimplePay; Cooltix Payment 1.5% + EUR 0.25 per transaction | L35: buyer handling fee up to 10% of ticket price, organizer keeps surplus | M35: free | N35: 3% + EUR 0.50 | O35: 5 workdays after event (Cooltix Payment) or immediate (own provider) | P35: as above | Q35: net of VAT | R35: • G2 lists Cooltix tiers 'from $0 to $0.75' (snippet, third-party) | U35: Hungarian-born self-service ticketing for festivals, clubs, theatres in HU, SK, CZ, HR and other EU countries; 'organizer earns on handling fee' pitch | V35: page | W35: https://organizers.cooltix.com/en/pricing (pricing page)
A36: Центр. и Вост. Европа, Балканы, Прибалтика | B36: Funcode / Funcode Wizard / Jegyvasarlas.hu | C36: https://funcode.hu | D36: Hungary | E36: HUF | F36: оба варианта | G36: Funcode Wizard: 'ticket income flows directly to the organizer', no entry or monthly costs, quote on request. Jegyvasarlas.hu: provider collects card payments into its own account and settles after the event / monthly (invoice by the 10th, transfer within 10 days). | H36: negotiated | K36: включён: None; свой процессинг: None; SimplePay, SZEP; Jegyvasarlas.hu may pass on SZEP card transaction bank costs on top of commission and convenience fee | L36: configurable by contract | O36: Jegyvasarlas.hu: after event or monthly for venue sales | P36: Jegyvasarlas.hu: commission and convenience fee may still be charged on cancelled events; penalty 8% of ticket price if the event fails for organizer reasons; 30,000 HUF + VAT per started hour admin fee for client errors / force majeure handling | R36: • Jegyvasarlas.hu buyer convenience fee: base 150 HUF + 3% of full ticket price (not on every event; organizer agreement may change it) • Funcode commission rate: not published (quote required) | T36: Quote | U36: Hungarian ticketing: funcode.hu marketplace, Funcode Wizard self-service builder; Jegyvasarlas.hu regional venue network | V36: page | W36: https://www.funcodewizard.hu/ (Wizard page) https://jegyvasarlas.hu/aszf (T&Cs section 11)
A37: Центр. и Вост. Европа, Балканы, Прибалтика | B37: eTichet.ro and Biletin.ro (new Romanian low-fee platforms) | C37: https://www.etichet.ro | D37: Romania (eTichet) | E37: RON | F37: direct merchant | G37: 'We process through your merchant account' - organizer's own merchant account; platform commission deducted per sale. | H37: percent | I37: • Promotional rate: 3.5% — unlimited events, 24/7 support, all features, price locked for the first year — '30% off' the standard 5% • Standard rate: 5% — after the promotion | K37: включён: False; свой процессинг: True; organizer's merchant account; no separate processing fee listed | L37: organizer (calculator default), 100 lei x 100 tickets -> organizer gets 9,650 lei | O37: not stated (direct to merchant account) | Q37: not stated | R37: • Promotion 'limited period'; end date not stated | U37: Small self-service ticketing startups with public price lists | V37: page | W37: https://www.etichet.ro/sell-tickets (organizer pricing page)
A38: Центр. и Вост. Европа, Балканы, Прибалтика | B38: Bilet.bg (Bilet BG OOD) | C38: https://bilet.bg | D38: Bulgaria | E38: BGN | F38: оба варианта | G38: Platform acts as intermediary; organizer can request up to 80% of accumulated sales at any time by e-mail (instant 'Bling' transfer); there are also direct transfers to the organizer's bank or PayPal where Bilet.bg invoices commission after the event. | H38: percent | I38: • Exclusive with Bilet.bg: 6% — incl. VAT — 50% discount for charity events (applies to?) • Non-exclusive (also selling on competing platforms): 7% — incl. VAT — large events: custom offer on request | K38: включён: None; свой процессинг: None; vPOS (Borika, DSK), Stripe, PayPal, bank transfer, cash/POS on courier, kiosks; payment processing fees are non-refundable to buyers; amounts not published | L38: organizer pays commission; buyers pay administrative / processing fees (non-refundable) | O38: up to 80% any time on request; remainder presumably after event (not stated) | P38: Buyer refund only if event cancelled/postponed; admin and payment fees, delivery costs not refunded | Q38: commission quoted 'incl. VAT' (6% / 7% with DDS) | R38: • Buyer name change on ticket: 2 BGN | T38: Custom offers for large events | U38: Bulgarian self-service ticketing marketplace with exclusive-vs-nonexclusive pricing; payouts up to 80% any time | V38: page | W38: https://bilet.bg/bg/sell-with-us (organizer page) https://bilet.bg/bg/terms-of-service (buyer terms)
A39: Центр. и Вост. Европа, Балканы, Прибалтика | B39: Shownet.lt and Paysera Tickets (Lithuanian direct-to-account self-service) | C39: https://shownet.lt | D39: Lithuania (Shownet) | E39: EUR | F39: direct merchant | G39: 'Income from buyers goes directly to your account and is available without delays.' | H39: percent_plus_fixed | I39: • System commission: 2.5% мин 0.06 — 'from 6 cents to 2.5% for 1 ticket (bankings or cards)'; unlimited scanning devices — currency not named on page; EUR assumed; interaction min/%: ticket fee between 0.06 EUR and 2.5% of ticket | K39: включён: None; свой процессинг: None; bank links, cards | L39: not stated | O39: immediate to organizer's account | U39: Self-service ticketing where organizers are paid directly; Paysera Tickets is the payment-processor-built variant (LT/LV/EE and global) | V39: page | W39: https://shownet.lt/to-organizers?lang=en (organizer page)
A40: Центр. и Вост. Европа, Балканы, Прибалтика | B40: Shownet.lt and Paysera Tickets (Lithuanian direct-to-account self-service) | C40: https://shownet.lt | D40: Lithuania / Latvia / Estonia and global (Paysera Tickets) | E40: EUR | F40: direct merchant | G40: Ticket revenue lands in the organizer's Paysera account in real time and is available immediately, before the event. Platform fee collected by Paysera from the same flow. | H40: percent_plus_fixed | I40: • Platform fee: 2% мин 0.15 потолок 1.0 — ticket sales, scanning app, no hidden ticket/admin fees — 2% additional platform fee per payment, min 0.15 EUR, max 1 EUR • Paysera Checkout collection fee (volume tiers, 30-day rolling): 0.9% мин 0.1 потолок 0.4 — 0-250 transactions or up to 12,500 EUR/30 days at 0.90% (0.10-0.40 EUR); 251-500 or 12,501-25,000 EUR at 0.75% (0.10-0.35); 501-750 or 25,001-37,500 EUR at 0.50% (0.10-0.30); above that individual offer — Checkout Modern 0% for LT/LV/EE for some payment initiation methods; unclear if it applies to Tickets; card fee 'unchanged' but not shown | K40: включён: False; свой процессинг: False; Paysera; card rate not shown | L40: not stated | M40: free events cost the organizer nothing | O40: real time | R40: • Page says neither buyers nor organizers pay unexpected ticket or administration fees | T40: >750 transactions or >37,500 EUR / 30 days: individual offer | U40: Self-service ticketing where organizers are paid directly; Paysera Tickets is the payment-processor-built variant (LT/LV/EE and global) | V40: page | W40: https://tickets.paysera.com/lt-LT/information/about-system (Paysera Tickets about page) https://www.paysera.com/v2/lt/kainos/imoku-surinkimas-internetu (Paysera collection price list incl. platform fee)
A41: СНГ без России, Израиль | B41: RegToEvent | C41: https://regtoevent.com | D41: Ukraine / international (EUR price list; Ukrainian legal entities billed in UAH at PrivatBank rate on payment day) | E41: EUR | F41: direct merchant | G41: Buyer's money goes straight to the organizer's own merchant account or IBAN; the RegToEvent fee is withheld from the ticket price or from a 'euro balance' (or added on top for the buyer on request). For organizers without a merchant account RTE offers turnkey processing that collects on their behalf, for transparent events. | H41: percent_plus_fixed | I41: • Free events, 1-100 attendees: 0% +0 — full system — above 100 attendees terms are in the public offer; free-event chat support is paid (99 EUR/month) • Charity, non-profit fundraising: 1.0% +0.2 — full system • Large events, 1000+ generated tickets: 2.0% +0.37 — full system • Small events, up to 999 tickets: 2.9% +0.39 — full system — calculator example: 100 x 50 EUR -> fee 368 EUR (1.84 EUR/ticket) • Seats, time slots or online broadcast, hall up to 1000: 4.5% +0.3 — full system incl. free hall-scheme builder • Seats, time slots or online broadcast, hall over 1000: 5.5% +0.3 — full system • Regular sales (parks, zoos, aquaparks): 2.0% +0 — full system • High-risk (political, abstract-sacral events): 10.0% +1.0 — full system — 2024 third-party article quoted religious/spiritual events at 30% + 0.5 EUR; current page says 10% + 1 EUR | K41: включён: False; свой процессинг: True; Visa/Mastercard via organizer's acquirer, Stripe, Ukrainian merchants / IBAN; payment-system fees are separate and paid by the organizer to the processor | L41: organizer (switchable to buyer on top of ticket price) | M41: free events 0% for 1-100 attendees, over 100 per offer | N41: seat/slot tickets cost 4.5%/5.5% + 0.3 EUR vs 2.9% + 0.39 EUR for plain tickets; hall-scheme builder free; custom scheme from a drawing from 99 EUR | O41: straight to organizer account at payment time (direct); turnkey processing option for organizers with no merchant | P41: not stated on the price page | Q41: not stated | R41: • paid add-ons: on-site check-in kits from 129 EUR/point, check-in software from 149 EUR/event, own white-label ticket 200-400 EUR, event setup 99 EUR, turnkey setup 299 EUR, hall scheme from 99 EUR • networking mobile app 1% + 1 EUR on top and setup fees 299-999 EUR; live-stream packages from 399 EUR • free-event support 99 EUR/month; visitor support widget 300 EUR/month • scanner/hardware rental 11-149 EUR/day plus deposit | S41: • {"name": "check-in on site (kit)", "price": "from 129 EUR per point, 4h slot"} • {"name": "white-label ticket/forms", "price": "200-300 EUR (forms), ticket design 300-400 EUR"} • {"name": "networking app", "price": "+1% +1 EUR, setup 299-999 EUR"} | T41: large/high-risk by public offer, individual quotes for custom work | U41: self-serve ticketing + registration + on-site check-in services for organizers (UA, PL, RO, ES, PT, EN pages); strong direct-merchant model | V41: page | W41: https://regtoevent.com/ua/price/ (price page) https://regtoevent.com/ua/ (home page (direct to organizer merchant/IBAN)) https://kosht.media/yak-stvoryty-ivent-ta-prodavaty-kvytky-onlayn-ohliad-top-3-servisiv/ (2024-09-30 third-party review quoting older RTE tiers)
A42: СНГ без России, Израиль | B42: Event.net.ua | C42: https://event.net.ua | D42: Ukraine | E42: UAH | F42: direct merchant | G42: Payment for tickets goes immediately and only to the organizer's own account; organizer connects Monobank, FinLine, LiqPay or WayForPay. Fiscalisation through checkbox.ua (Monobank) / CashDesk (FinLine). | H42: flat_per_ticket | I42: • Free events: +0.0 — unlimited guests — not for seated events • Free-seating / entrance ticket: +8.0 — regardless of ticket price; no monthly or hidden payments — UAH per ticket • Seated (hall scheme) ticket: 2.5% +12.0 — organizer picks 12 UAH per ticket OR 2.5% (either/or) — hall-scheme connection paid separately (price not published, contact) | K42: включён: False; свой процессинг: True; MonoBank, FinLine, LiqPay, WayForPay; processor rates paid by organizer to the processor | L42: organizer | M42: free events 0 UAH per ticket, unlimited guests, except hall-scheme events | N42: 12 UAH or 2.5% per seated ticket plus a separate hall-scheme connection fee | O42: instant: money goes straight to organizer's merchant account | Q42: not stated | R42: • commission charged per issued ticket for paid events if any ticket exceeds 1 UAH (search snippet) • branding/white-label ticket and landing design and guest-list ticket generation are additional services (no prices) | S42: • {"name": "white-label ticket, landing branding, custom integrations", "price": "not published"} | T42: contact for seated schemes and custom work | U42: Ukrainian SaaS ticketing for organizers, tourist attractions (Kyiv-Pechersk Lavra, Sophia, 100+ sites), recurring events; 200+ organizers, 1.2M+ tickets | V42: page | W42: https://event.net.ua/ (home page price block)
A43: СНГ без России, Израиль | B43: Ukrainian payment-bundled ticket tools: Wayforpay 'Social invoice - sell tickets', Eventmate, Ottry, Social.Invoice Tickets | C43: https://help.wayforpay.com ; https://eventmate.live ; https://ottry.com/promo/tickets | D43: Ukraine | E43: UAH | F43: direct merchant | G43: Wayforpay: payouts to organizer's details. Ottry: funds go to a personal account, payout to an account named in the form. Eventmate: not stated. | H43: percent | I43: • Wayforpay ticket invoice: 2.0% — ticket page, e-mail QR tickets, scanning via web — as quoted by a third-party review dated 2024-09-30 • Eventmate: 6.0% — app-based event page, scanning in the app, mass messaging — free events are free; third-party review 2024-09-30 • Ottry: 5.0% — full package: QR scanning, Apple/Google Pay, promo codes, real-time data — 5% of ticket sales; third-party review 2024-09-30 • Social.Invoice Tickets (earlier Wayforpay product): 2.5% — ticket sales tool — 2021 headline: organizers pay 2.5% instead of 10%; from search snippet only | K43: включён: None; свой процессинг: None | L43: organizer | M43: Eventmate: free events free | Q43: not stated | R43: • figures come from a 2024 third-party article, vendors' own pages were not read (Wayforpay help page blocked) | U43: small/one-off organizers who want a quick ticket page; fee bundled with a payment account | V43: third_party | W43: https://kosht.media/yak-stvoryty-ivent-ta-prodavaty-kvytky-onlayn-ohliad-top-3-servisiv/ (third-party review 2024-09-30) https://mc.today/uk/organizatori-zahodiv-zaplatyat-2-5-komisiyi-zamist-10-rozpovidayemo-pro-novu-platformu-prodazhu-kvitkiv/ (snippet only, 2021-09-27)
A44: СНГ без России, Израиль | B44: Tickchak (Tickchak Ltd, Jerusalem) | C44: https://tickchak.co.il | D44: Israel | E44: ILS | F44: оба варианта | G44: Terms of use section 4: payment either (a) through an external clearing provider where the money is paid to Tickchak, Tickchak deducts its fee and passes the balance to the event manager (collecting), or (b) through the organizer's own clearing terminal/provider connected by the organizer (direct). Which one is the default and whether the fee differs is not published. | H44: mixed | I44: • Small events ('אירועים בקטנה'): — up to 5 events per month (as shown on plan card) — plan card shows a 'free' toggle and 'per month paid annually' wording but no amounts in the scraped text • Large events, personal attention: — personal account management — price not public | K44: включён: None; свой процессинг: True; external clearing providers; terms mention fees for clearing, add-ons and promotion according to a price list shown to event managers privately | N44: seated events supported (feature list) | O44: after fee deduction when paid via Tickchak's provider; timing not published | P44: per Israeli Consumer Protection Law and organizer policy; Tickchak says it is only a technology platform and agent | Q44: not stated | R44: • fees/usage charges/add-ons follow a price list presented to event managers separately (personal area, quote, or separate agreement) and may change • sign-up form asks event size (up to 100 / 1000 / over 1000 tickets) which suggests tiered pricing | S44: • {"name": "branded SMS, own domain, mailing system, audience import, pixels", "price": "not published"} | T44: contact *6565 / info@tickchak.co.il | U44: major Israeli self-serve ticketing for events, festivals, courses, visitor centres, crowdfunding (Givechak); thousands of customers | V44: page | W44: https://tickchak.co.il/terms (terms of use section 4 payments) https://tickchak.co.il/events (plan cards without prices)
A45: СНГ без России, Израиль | B45: Ticks (ticks.co.il) and Eventbuzz (eventbuzz.co.il) | C45: https://ticks.co.il ; https://www.eventbuzz.co.il | D45: Israel | E45: ILS | F45: direct merchant | G45: Ticks home page: buyers pay through the producer's own credit-card clearing provider and the system issues digital tax invoices; commission is charged per ticket sold only, no monthly fee, no commitment. | H45: per_ticket (rate not published) | I45: • Ticks pay-per-ticket: — online sales, SMS with digital ticket, scanner app, seat selection, multi-language, stats — rate behind a 'fair price' block and demo/contact, not in text • Eventbuzz: — event page free to create, marked seating, promoters network, pixels, SMS/e-mail — price not shown | K45: включён: False; свой процессинг: True; producer's own credit-card provider | N45: seat selection supported (Ticks, Eventbuzz) | O45: direct to producer's provider (Ticks) | Q45: not stated | U45: Israeli self-serve ticketing: Ticks (events, conferences, theatres, cinemas, seated halls, customers incl. Tel Aviv municipality, Technion, Israel Railways); Eventbuzz (event pages in minutes with seated halls and promoter network) | V45: page | W45: https://ticks.co.il/ (home page) https://www.eventbuzz.co.il/ (home page)
A46: Латинская Америка | B46: Tikzet | C46: https://www.tikzet.com | D46: Argentina | E46: ARS | F46: direct merchant | G46: Tikzet says it does not hold funds: buyer pays straight into the organizer's own processor account (Mercado Pago, Nave, Uala, Unicobros, Stripe, PayPal, manual bank transfer/CBU). Tikzet's fee is the prepaid ticket credit bought in advance; each sale deducts one credit. | H46: prepaid_credits | I46: • Prepaid ticket bundle (300 tickets): +256 — ARS 256 per ticket at the 300-ticket tier (list ARS 320, '20% off'); calculator runs from 300 to 203,000+ tickets with the unit price falling by volume (only the 300-ticket price was visible). 25 free tickets on sign-up, no credit card. Credits never expire. QR scanner app works offline. — No service fee to buyer ('sin cargo por servicio'): the buyer pays exactly the advertised price. Processor fees are separate and paid by the organizer to the processor. | J46: • 300 tickets: 256 (срок: no expiry; возврат: None) | K46: включён: False; свой процессинг: True; Mercado Pago, Nave, Uala, Unicobros, Stripe, PayPal, bank transfer; Processors charge their own rates; Tikzet says Mercado Pago gives 'preferential commissions' (no number). | L46: organizer | M46: 25 free tickets to start; free events not described. | N46: Not described. | O46: Direct to the organizer's processor account: instant (Mercado Pago, Nave, Uala), same day (automatic transfer, Unicobros). | P46: Organizer manages each purchase and refund. | Q46: Not stated. | R46: • Unit price at higher volumes not visible (JS calculator) • Prepaid credit is consumed per ticket sold - cost is a fixed amount per ticket, independent of ticket price | T46: Sales contact via WhatsApp. | U46: LatAm self-serve ticketing, nightlife/festivals/theatre; 'no service fee', organizer prepays tickets | V46: page | W46: https://www.tikzet.com/pricing (AR pricing calculator) https://www.tikzet.com/payments/ar (payments page)
A47: Латинская Америка | B47: Tikzet | C47: https://www.tikzet.com | D47: Brazil | E47: BRL | F47: direct merchant | G47: Same model as Argentina. | H47: prepaid_credits | I47: • Prepaid ticket bundle (300 tickets): +1.4 — R$1.40 per ticket at 300 tickets (list R$1.75), total R$420; 25 free tickets; no expiry. — Own blog claims competitors charge 10-12.5% (Sympla, Shotgun, Blacktag, Zig). | J47: • 300 tickets: 1.4 (срок: no expiry; возврат: None) | K47: включён: False; свой процессинг: True; Organizer's own processor. | L47: organizer | M47: 25 free tickets. | O47: Direct to organizer account. | Q47: Not stated. | U47: LatAm self-serve ticketing, nightlife/festivals/theatre; 'no service fee', organizer prepays tickets | V47: page | W47: https://www.tikzet.com/pricing/br (BR pricing)
A48: Латинская Америка | B48: Tikzet | C48: https://www.tikzet.com | D48: Mexico | E48: MXN | F48: direct merchant | G48: Same model. | H48: prepaid_credits | I48: • Prepaid ticket bundle (300 tickets): +4.8 — MXN 4.80 per ticket at 300 tickets (list MXN 6.00), total MXN 1,440; 25 free; no expiry. | J48: • 300 tickets: 4.8 (срок: no expiry; возврат: None) | K48: включён: False; свой процессинг: True | L48: organizer | M48: 25 free tickets. | O48: Direct to organizer account. | Q48: Not stated. | U48: LatAm self-serve ticketing, nightlife/festivals/theatre; 'no service fee', organizer prepays tickets | V48: page | W48: https://www.tikzet.com/pricing/mx (MX pricing)
A49: Латинская Америка | B49: Tikzet | C49: https://www.tikzet.com | D49: Colombia | E49: COP | F49: direct merchant | G49: Same model. | H49: prepaid_credits | I49: • Prepaid ticket bundle (300 tickets): +1040 — COP 1,040 per ticket at 300 tickets (list COP 1,300), total COP 312,000; 25 free. | J49: • 300 tickets: 1040 (срок: no expiry; возврат: None) | K49: включён: False; свой процессинг: True | L49: organizer | M49: 25 free tickets. | O49: Direct to organizer account. | Q49: Not stated. | U49: LatAm self-serve ticketing, nightlife/festivals/theatre; 'no service fee', organizer prepays tickets | V49: page | W49: https://www.tikzet.com/pricing/co (CO pricing)
A50: Латинская Америка | B50: Tikzet | C50: https://www.tikzet.com | D50: Chile | E50: CLP | F50: direct merchant | G50: Same model. | H50: prepaid_credits | I50: • Prepaid ticket bundle (300 tickets): +229 — CLP 229 per ticket at 300 tickets (list CLP 287), total CLP 68,700; 25 free. | J50: • 300 tickets: 229 (срок: no expiry; возврат: None) | K50: включён: False; свой процессинг: True | L50: organizer | M50: 25 free tickets. | O50: Direct to organizer account. | Q50: Not stated. | U50: LatAm self-serve ticketing, nightlife/festivals/theatre; 'no service fee', organizer prepays tickets | V50: page | W50: https://www.tikzet.com/pricing/cl (CL pricing)
A51: Латинская Америка | B51: Tikzet | C51: https://www.tikzet.com | D51: Peru | E51: PEN | F51: direct merchant | G51: Same model. | H51: prepaid_credits | I51: • Prepaid ticket bundle (300 tickets): +0.92 — S/0.92 per ticket at 300 tickets (list S/1.15), total S/276; 25 free. | J51: • 300 tickets: 0.92 (срок: no expiry; возврат: None) | K51: включён: False; свой процессинг: True | L51: organizer | M51: 25 free tickets. | O51: Direct to organizer account. | Q51: Not stated. | U51: LatAm self-serve ticketing, nightlife/festivals/theatre; 'no service fee', organizer prepays tickets | V51: page | W51: https://www.tikzet.com/pricing/pe (PE pricing)
A52: Латинская Америка | B52: Tikzet | C52: https://www.tikzet.com | D52: Uruguay | E52: UYU | F52: direct merchant | G52: Same model. | H52: prepaid_credits | I52: • Prepaid ticket bundle (300 tickets): +10 — UYU 10 per ticket at 300 tickets (list UYU 12.5), total UYU 3,000; 25 free. | J52: • 300 tickets: 10 (срок: no expiry; возврат: None) | K52: включён: False; свой процессинг: True | L52: organizer | M52: 25 free tickets. | O52: Direct to organizer account. | Q52: Not stated. | U52: LatAm self-serve ticketing, nightlife/festivals/theatre; 'no service fee', organizer prepays tickets | V52: page | W52: https://www.tikzet.com/pricing/uy (UY pricing)
A53: Латинская Америка | B53: Tickean | C53: https://www.tickean.com | D53: Argentina / Chile / Mexico / Colombia / Peru (same terms on each country site) | E53: ARS (local currency per site) | F53: direct merchant | G53: 'Acredita cada venta via el proveedor de pagos' - each sale credited to the organizer's own payment-provider account, no wait for the event end (subject to reserve/chargeback terms of the processor). The platform earns the buyer's service fee. | H53: free_buyer_pays | I53: • Standard: 0% +0 — 0% commission to the organizer, no activation, monthly fee or minimum tickets, unlimited QR at no cost, WhatsApp Marketing with 1,000 free messages per month ('promotion with conditions'), live dashboard, QR anti-fraud, QR validation from phone browser. — Buyer pays a 15% service fee on top of the ticket price (ticket 10,000 -> buyer pays 11,500). | K53: включён: False; свой процессинг: True; undisclosed 'proveedor de pagos' (cards, Apple Pay, Google Pay); Processor fees not disclosed. | L53: buyer | M53: Not described. | N53: Not mentioned. | O53: Instant per sale via payment provider. | P53: Not read. | Q53: Not stated. | R53: • Operated by Tickean Holdings LLC (US) • Mexico site still shows Argentina contact elements | S53: • {"name": "WhatsApp Marketing", "price": "1,000 messages/month free, beyond that 'with conditions'"} | U53: LatAm self-serve (Argentina, Chile, Mexico, Colombia, Peru, US), 0% to organizer, buyer pays 15% service fee, WhatsApp QR delivery | V53: page | W53: https://www.tickean.com/comisiones-ticketera (pricing/commissions page) https://www.tickean.com.mx/ (Mexico page) https://www.tickean.com/alternativa-a-passline (comparison page)
A54: Латинская Америка | B54: Enter.ar | C54: https://enter.ar | D54: Argentina | E54: ARS | F54: direct merchant | G54: Mercado Pago Marketplace: the sale lands directly in the organizer's Mercado Pago account at purchase time minus Enter's 2% application fee; Enter does not hold funds. | H54: percent | I54: • Standard: 2% — 2% per sale, no contract, no minimums, creating events free. — Mercado Pago's own fee (card, installments) is separate and not stated on the page read. | K54: включён: False; свой процессинг: True; Mercado Pago; Mercado Pago fees separate. | L54: organizer | N54: Not mentioned. | O54: At the moment of purchase, into the organizer's Mercado Pago account. | Q54: Not stated. | R54: • Page is a vendor comparison versus Passline | U54: Argentine producers, Mercado Pago marketplace, flat 2% | V54: page | W54: https://enter.ar/vs/passline (vendor page)
A55: Латинская Америка | B55: MaunaOne | C55: https://maunaone.com | D55: Mexico | E55: MXN | F55: direct merchant | G55: Money goes straight into the organizer's own Stripe account via Stripe Connect; MaunaOne does not touch funds. Fee taken as an application fee per online sale plus (Pro) monthly subscription. | H55: mixed | I55: • Inicia: 5% — Basic sales, calendar, QR check-in, CRM. 5% + IVA on online sales. Self-service support. Cash/transfer sales at POS not included. • Pro: 2% 899/мес 7548/год — 2% + IVA online, no fee on cash/transfer at POS, priority support, advances, private groups, iframe, resellers, own branding, Meta and Google Ads pixels. — MXN 629/month with annual contract (MXN 7,548/year). 20% promo on monthly (MXN 719 + IVA) if bought before 2026-10-31. 'Launch session' MXN 2,500 + IVA, included in Pro annual. • A la medida: — Reduced by volume, integrations, consulting. — Quote. | K55: включён: False; свой процессинг: True; Stripe; Stripe Mexico 3.6% + MXN 3 + IVA per domestic card payment, deducted from the organizer's account by Stripe. | L55: configurable | M55: Not mentioned. | N55: Not mentioned (capacity calendar only). | O55: Stripe's schedule to the organizer's bank. | Q55: Prices exclude IVA (fee quoted '+ IVA'). | R55: • Fee can be passed to buyer as service charge (5% + IVA or 2% + IVA) | S55: • {"name": "Launch session", "price": "MXN 2,500 + IVA"} | T55: Custom plan by quote. | U55: Mexican experiences/events SaaS on Stripe Connect | V55: page | W55: https://maunaone.com/pricing (pricing page) https://maunaone.com/blog/boletia-vs-passline-vs-maunaone (own comparison blog)
